Workbook
Name ActualInvestment: LongTerm!#REF!
Name ActualInvestment: Asset!#REF!
Name avgExpense: DashBoard!$D$27
Name avgIncome: DashBoard!$C$27
Name AvgInvestment: DashBoard!$F$27
Name avgLoanRePayment: DashBoard!$E$27
Name AvgSavings: DashBoard!$G$27
Name BasicSalary: Income!$C$2
Name CurrentMonth: DashBoard!$F$1
Name ExpenseAvg: Expenses!$C$12
Name IncomeAvg: Income!$D$11
Name IntraDayLCount: [1]Ledger!$U$2
Name IntraDayLearnPer: [1]Ledger!$Y$2
Name IntraDayProfit: [1]Ledger!$W$2
Name IntraDayProfitPer: [1]Ledger!$X$2
Name IntraDaySCount: [1]Ledger!$T$2
Name InvestmentAvg: Investment!$C$14
Name InvestmentCurrValue: LongTerm!#REF!
Name InvestmentCurrValue: Asset!#REF!
Name InvestmentProfit: LongTerm!#REF!
Name InvestmentProfit: Asset!#REF!
Name InvestmentQuota: Investment!$C$3
Name INVQuota: Asset!#REF!
Name INVQuota: LongTerm!#REF!
Name INVQuota: #REF!
Name LoanAvg: Loan!$D$13
Name LongTermQuota: Corpus!$F$17
Name StockPortfolioValue: Corpus!$K$4
Name StocksWallet: Investment!$A$3
Name SummartTable: Table3[#All]
Name SummartTable: Table3[#All]
Name SwingInvestment: [1]Ledger!#REF!
Name SwingOpenOrder: [1]Ledger!$Z$3
Name SwingProfit: [1]Ledger!$W$3
Name SwingTradeQuota: Corpus!$F$19
Name TotalInvestment: LongTerm!#REF!
Name TotalInvestment: Asset!#REF!
Name TotalMonth: DashBoard!$H$1
Name TradingFund: LongTerm!#REF!
Name TradingFund: Asset!#REF!
Name TradingQuota: LongTerm!#REF!
Name TradingQuota: Asset!#REF!

Sheet DashBoard
D1: 💼💰 | E1: 📊 DashBoard as of | F1: =DATE(YEAR(TODAY()), MONTH(TODAY()), 1) -> 46113 | G1: 🗓️📈 | H1: =DATEDIF(DATE(2025,10,1), TODAY(), "m") -> 6
B3: 💰⬆️Avg Income | D3: =avgIncome -> 273927.8 | F3: 📈💼Avg Investment | H3: =AvgInvestment -> 98363
B4: 💸⬇️Avg Expense | D4: =avgExpense -> 97550 | F4: 🐖💰Avg Savings | H4: =AvgSavings -> -53299
B5: 🏦🔁Avg Loan Repayment | D5: =avgLoanRePayment -> 166910.2 | F5: 🏛️RBI Balance | H5: =INDEX(RBITable[Transactions], MATCH(CurrentMonth,RBITable[Month],0)) -> 0
B9: 📊 70% of Investment 🚀 | D9: 🪙10% of Investment✨ | E9: 👴14% of Basic Salary📈 | F9: 🎯20% of Investment💸 | H9: 🏠No Allocation So far 📊
A10: 🗂️ | B10: Equity | D10: Gold | E10: Retirement | F10: Fixed Return | H10: Real State
A11: 🎯 | B11: =_xlfn.CEILING.MATH(avgIncome*30%*70%) -> 57525 | D11: =_xlfn.CEILING.MATH(avgIncome*30%*10%) -> 8218 | E11: =_xlfn.CEILING.MATH(15515) -> 15515 | F11: =_xlfn.CEILING.MATH(avgIncome*30%*20%) -> 16436 | H11: =_xlfn.CEILING.MATH(avgIncome*0%) -> 0
A12: ✅ | B12: =AVERAGE(Investment!D14:E14) -> 1859 | D12: =AVERAGEIF(Investment!F14:I14,">0") -> 4405.5 | E12: =Investment!K14 -> 15515 | F12: =Investment!L14 -> 12500
A13: 💰 | B13: =SUMIFS(CorpusTable[Invested],CorpusTable[Type],DashBoard!B10) -> 2829087 | D13: =SUMIFS(CorpusTable[Invested],CorpusTable[Type],DashBoard!D10) -> 422438 | E13: =SUMIFS(CorpusTable[Invested],CorpusTable[Type],DashBoard!E10) -> 1040101 | F13: =SUMIFS(CorpusTable[Invested],CorpusTable[Type],DashBoard!F10) -> 2699100 | H13: =SUMIFS(CorpusTable[Invested],CorpusTable[Type],DashBoard!H10) -> 700000
A14: 💼 | B14: =SUMIFS(CorpusTable[Current Value],CorpusTable[Type],DashBoard!B10) -> 5015237.9 | D14: =SUMIFS(CorpusTable[Current Value],CorpusTable[Type],DashBoard!D10) -> 878605.98 | E14: =SUMIFS(CorpusTable[Current Value],CorpusTable[Type],DashBoard!E10) -> 1521019.5 | F14: =SUMIFS(CorpusTable[Current Value],CorpusTable[Type],DashBoard!F10) -> 3479947.6 | H14: =SUMIFS(CorpusTable[Current Value],CorpusTable[Type],DashBoard!H10) -> 1650000
A15: 💸 | B15: =SUMIFS(CorpusTable[Return],CorpusTable[Type],DashBoard!B10) -> 2186150.9 | D15: =SUMIFS(CorpusTable[Return],CorpusTable[Type],DashBoard!D10) -> 456167.98 | E15: =SUMIFS(CorpusTable[Return],CorpusTable[Type],DashBoard!E10) -> 480918.54 | F15: =SUMIFS(CorpusTable[Return],CorpusTable[Type],DashBoard!F10) -> 780847.64 | H15: =SUMIFS(CorpusTable[Return],CorpusTable[Type],DashBoard!H10) -> 950000
A16: % | B16: =SUMIFS(CorpusTable[Return%],CorpusTable[Type],DashBoard!B10) -> 1.5464654 | D16: =SUMIFS(CorpusTable[Return%],CorpusTable[Type],DashBoard!D10) -> 3.2641885 | E16: =SUMIFS(CorpusTable[Return%],CorpusTable[Type],DashBoard!E10) -> 0.46237677 | F16: =SUMIFS(CorpusTable[Return%],CorpusTable[Type],DashBoard!F10) -> 0.52474854 | H16: =SUMIFS(CorpusTable[Return%],CorpusTable[Type],DashBoard!H10) -> 1.3571429
B18: Expected | C18: 200000 | D18: 120000 | E18: 137000 | F18: 75000 | H18: 400000
B19: Month | C19: Income | D19: Expense | E19: Loan Repayment | F19: Investment | G19: Savings | H19: RBI Balance
B20: 45962 | C20: =_xlfn.IFNA(INDEX( IncomeTable[Total In Hand], MATCH(Table3[[#This Row],[Month]], IncomeTable[Month], 0) ),0) -> 360556 | D20: =_xlfn.IFNA(INDEX( ExpenseTable[Actual Expense], MATCH(Table3[[#This Row],[Month]], ExpenseTable[Month], 0) ),0) -> 76341 | E20: =_xlfn.IFNA(INDEX( LoanTable[Total Loan], MATCH(Table3[[#This Row],[Month]], LoanTable[Month], 0) ),0) -> 244200 | F20: =_xlfn.IFNA(INDEX( InvestmentTable[Total Investment], MATCH(Table3[[#This Row],[Month]], InvestmentTable[Entry Month], 0) ),0) -> 71670 | G20: =Table3[[#This Row],[Income]]-Table3[[#This Row],[Expense]]-Table3[[#This Row],[Loan Repayment]]-Table3[[#This Row],[Investment]] -> -31655 | H20: =_xlfn.IFNA(INDEX(RBITable[Transactions], MATCH(Table3[[#This Row],[Month]],RBITable[Month],0)),"") -> 82008
B21: 45992 | C21: =_xlfn.IFNA(INDEX( IncomeTable[Total In Hand], MATCH(Table3[[#This Row],[Month]], IncomeTable[Month], 0) ),0) -> 281023 | D21: =_xlfn.IFNA(INDEX( ExpenseTable[Actual Expense], MATCH(Table3[[#This Row],[Month]], ExpenseTable[Month], 0) ),0) -> 105100 | E21: =_xlfn.IFNA(INDEX( LoanTable[Total Loan], MATCH(Table3[[#This Row],[Month]], LoanTable[Month], 0) ),0) -> 124803 | F21: =_xlfn.IFNA(INDEX( InvestmentTable[Total Investment], MATCH(Table3[[#This Row],[Month]], InvestmentTable[Entry Month], 0) ),0) -> 86773 | G21: =Table3[[#This Row],[Income]]-Table3[[#This Row],[Expense]]-Table3[[#This Row],[Loan Repayment]]-Table3[[#This Row],[Investment]] -> -35653 | H21: =_xlfn.IFNA(INDEX(RBITable[Transactions], MATCH(Table3[[#This Row],[Month]],RBITable[Month],0)),"") -> 35985
B22: 46023 | C22: =_xlfn.IFNA(INDEX( IncomeTable[Total In Hand], MATCH(Table3[[#This Row],[Month]], IncomeTable[Month], 0) ),0) -> 256525 | D22: =_xlfn.IFNA(INDEX( ExpenseTable[Actual Expense], MATCH(Table3[[#This Row],[Month]], ExpenseTable[Month], 0) ),0) -> 121465 | E22: =_xlfn.IFNA(INDEX( LoanTable[Total Loan], MATCH(Table3[[#This Row],[Month]], LoanTable[Month], 0) ),0) -> 158488 | F22: =_xlfn.IFNA(INDEX( InvestmentTable[Total Investment], MATCH(Table3[[#This Row],[Month]], InvestmentTable[Entry Month], 0) ),0) -> -26320 | G22: =Table3[[#This Row],[Income]]-Table3[[#This Row],[Expense]]-Table3[[#This Row],[Loan Repayment]]-Table3[[#This Row],[Investment]] -> 2892 | H22: =_xlfn.IFNA(INDEX(RBITable[Transactions], MATCH(Table3[[#This Row],[Month]],RBITable[Month],0)),"") -> -10069
B23: 46054 | C23: =_xlfn.IFNA(INDEX( IncomeTable[Total In Hand], MATCH(Table3[[#This Row],[Month]], IncomeTable[Month], 0) ),0) -> 207702 | D23: =_xlfn.IFNA(INDEX( ExpenseTable[Actual Expense], MATCH(Table3[[#This Row],[Month]], ExpenseTable[Month], 0) ),0) -> 71006 | E23: =_xlfn.IFNA(INDEX( LoanTable[Total Loan], MATCH(Table3[[#This Row],[Month]], LoanTable[Month], 0) ),0) -> 154962 | F23: =_xlfn.IFNA(INDEX( InvestmentTable[Total Investment], MATCH(Table3[[#This Row],[Month]], InvestmentTable[Entry Month], 0) ),0) -> 105136 | G23: =Table3[[#This Row],[Income]]-Table3[[#This Row],[Expense]]-Table3[[#This Row],[Loan Repayment]]-Table3[[#This Row],[Investment]] -> -123402 | H23: =_xlfn.IFNA(INDEX(RBITable[Transactions], MATCH(Table3[[#This Row],[Month]],RBITable[Month],0)),"") -> -56151
B24: 46082 | C24: =_xlfn.IFNA(INDEX( IncomeTable[Total In Hand], MATCH(Table3[[#This Row],[Month]], IncomeTable[Month], 0) ),0) -> 263833 | D24: =_xlfn.IFNA(INDEX( ExpenseTable[Actual Expense], MATCH(Table3[[#This Row],[Month]], ExpenseTable[Month], 0) ),0) -> 113838 | E24: =_xlfn.IFNA(INDEX( LoanTable[Total Loan], MATCH(Table3[[#This Row],[Month]], LoanTable[Month], 0) ),0) -> 152098 | F24: =_xlfn.IFNA(INDEX( InvestmentTable[Total Investment], MATCH(Table3[[#This Row],[Month]], InvestmentTable[Entry Month], 0) ),0) -> 129873 | G24: =Table3[[#This Row],[Income]]-Table3[[#This Row],[Expense]]-Table3[[#This Row],[Loan Repayment]]-Table3[[#This Row],[Investment]] -> -131976 | H24: =_xlfn.IFNA(INDEX(RBITable[Transactions], MATCH(Table3[[#This Row],[Month]],RBITable[Month],0)),"") -> -102264
B25: 46113 | C25: =_xlfn.IFNA(INDEX( IncomeTable[Total In Hand], MATCH(Table3[[#This Row],[Month]], IncomeTable[Month], 0) ),0) -> 0 | D25: =_xlfn.IFNA(INDEX( ExpenseTable[Actual Expense], MATCH(Table3[[#This Row],[Month]], ExpenseTable[Month], 0) ),0) -> 0 | E25: =_xlfn.IFNA(INDEX( LoanTable[Total Loan], MATCH(Table3[[#This Row],[Month]], LoanTable[Month], 0) ),0) -> 0 | F25: =_xlfn.IFNA(INDEX( InvestmentTable[Total Investment], MATCH(Table3[[#This Row],[Month]], InvestmentTable[Entry Month], 0) ),0) -> 0 | G25: =Table3[[#This Row],[Income]]-Table3[[#This Row],[Expense]]-Table3[[#This Row],[Loan Repayment]]-Table3[[#This Row],[Investment]] -> 0 | H25: =_xlfn.IFNA(INDEX(RBITable[Transactions], MATCH(Table3[[#This Row],[Month]],RBITable[Month],0)),"") -> 0
B26: Total | C26: =SUBTOTAL(109,Table3[Income]) -> 1369639 | D26: =SUBTOTAL(109,Table3[Expense]) -> 487750 | E26: =SUBTOTAL(109,Table3[Loan Repayment]) -> 834551 | F26: =SUBTOTAL(109,Table3[Investment]) -> 367132 | G26: =SUBTOTAL(109,Table3[Savings]) -> -319794
B27: Avg | C27: =AVERAGEIF(Table3[Income],">0") -> 273927.8 | D27: =AVERAGEIF(Table3[Expense],">0") -> 97550 | E27: =AVERAGEIF(Table3[Loan Repayment],">0") -> 166910.2 | F27: =AVERAGEIF(Table3[Investment],">0") -> 98363 | G27: =AVERAGE(Table3[Savings]) -> -53299

Sheet Income
B2: Basic | C2: 110854
B3: Year | C3: Month | D3: Total In Hand | E3: Salary Credit | F3: NPS Deduction | G3: EPF Deduction | H3: EPF Loan Deduction | I3: Lease Phone Deduction | J3: Lease Vehcile Dedution | K3: Incentive Bonus | L3: Rati | M3: Family | N3: Investment Return | O3: Loan Return
B4: =TEXT(IncomeTable[[#This Row],[Month]],"YYYY") -> 2025 | C4: 45962 | D4: =SUM(IncomeTable[[#This Row],[Salary Credit]:[Loan Return]])-IncomeTable[[#This Row],[NPS Deduction]]-IncomeTable[[#This Row],[EPF Deduction]] -> 360556 | E4: 196352 | F4: 15515 | G4: 26604 | H4: 22170 | I4: 1920 | J4: 0 | K4: 140114 | L4: 0 | M4: 0 | N4: 0 | O4: 0
B5: =TEXT(IncomeTable[[#This Row],[Month]],"YYYY") -> 2025 | C5: 45992 | D5: =SUM(IncomeTable[[#This Row],[Salary Credit]:[Loan Return]])-IncomeTable[[#This Row],[NPS Deduction]]-IncomeTable[[#This Row],[EPF Deduction]] -> 281023 | E5: 196933 | F5: 15515 | G5: 26604 | H5: 22170 | I5: 1920 | J5: 0 | K5: 0 | L5: 0 | M5: 0 | N5: 60000 | O5: 0
B6: =TEXT(IncomeTable[[#This Row],[Month]],"YYYY") -> 2026 | C6: 46023 | D6: =SUM(IncomeTable[[#This Row],[Salary Credit]:[Loan Return]])-IncomeTable[[#This Row],[NPS Deduction]]-IncomeTable[[#This Row],[EPF Deduction]] -> 256525 | E6: 197435 | F6: 15515 | G6: 26604 | H6: 22170 | I6: 1920 | J6: 0 | K6: 0 | L6: 0 | M6: 0 | N6: 35000 | O6: 0
B7: =TEXT(IncomeTable[[#This Row],[Month]],"YYYY") -> 2026 | C7: 46054 | D7: =SUM(IncomeTable[[#This Row],[Salary Credit]:[Loan Return]])-IncomeTable[[#This Row],[NPS Deduction]]-IncomeTable[[#This Row],[EPF Deduction]] -> 207702 | E7: 158612 | F7: 15515 | G7: 26604 | H7: 22170 | I7: 1920 | J7: 25000 | K7: 0 | L7: 0 | M7: 0 | N7: 0 | O7: 0
B8: =TEXT(IncomeTable[[#This Row],[Month]],"YYYY") -> 2026 | C8: 46082 | D8: =SUM(IncomeTable[[#This Row],[Salary Credit]:[Loan Return]])-IncomeTable[[#This Row],[NPS Deduction]]-IncomeTable[[#This Row],[EPF Deduction]] -> 263833 | E8: =144815+8068 -> 152883 | F8: 15515 | G8: 26004 | H8: 22170 | I8: 1920 | J8: 25000 | K8: 0 | L8: 0 | M8: 0 | N8: =35000+26860 -> 61860 | O8: 0
B9: =TEXT(IncomeTable[[#This Row],[Month]],"YYYY") -> 2026 | C9: 46113 | D9: =SUM(IncomeTable[[#This Row],[Salary Credit]:[Loan Return]])-IncomeTable[[#This Row],[NPS Deduction]]-IncomeTable[[#This Row],[EPF Deduction]] -> 0
B10: Total | D10: =SUBTOTAL(109,IncomeTable[Total In Hand]) -> 1369639 | E10: =SUBTOTAL(109,IncomeTable[Salary Credit]) -> 902215 | F10: =SUBTOTAL(109,IncomeTable[NPS Deduction]) -> 77575 | G10: =SUBTOTAL(109,IncomeTable[EPF Deduction]) -> 132420 | H10: =SUBTOTAL(109,IncomeTable[EPF Loan Deduction]) -> 110850 | I10: =SUBTOTAL(109,IncomeTable[Lease Phone Deduction]) -> 9600 | J10: =SUBTOTAL(109,IncomeTable[Lease Vehcile Dedution]) -> 50000 | K10: =SUBTOTAL(109,IncomeTable[Incentive Bonus]) -> 140114 | L10: =SUBTOTAL(109,IncomeTable[Rati]) -> 0 | M10: =SUBTOTAL(109,IncomeTable[Family]) -> 0 | N10: =SUBTOTAL(109,IncomeTable[Investment Return]) -> 156860 | O10: =SUBTOTAL(109,IncomeTable[Loan Return]) -> 0
B11: Average | D11: =AVERAGE(IncomeTable[Total In Hand]) -> 228273.17 | E11: =AVERAGE(IncomeTable[Salary Credit]) -> 180443 | F11: =AVERAGE(IncomeTable[NPS Deduction]) -> 15515 | G11: =AVERAGE(IncomeTable[EPF Deduction]) -> 26484 | H11: =AVERAGE(IncomeTable[EPF Loan Deduction]) -> 22170 | I11: =AVERAGE(IncomeTable[Lease Phone Deduction]) -> 1920 | J11: =AVERAGE(IncomeTable[Lease Vehcile Dedution]) -> 10000 | K11: =AVERAGE(IncomeTable[Incentive Bonus]) -> 28022.8 | L11: =AVERAGE(IncomeTable[Rati]) -> 0 | M11: =AVERAGE(IncomeTable[Family]) -> 0 | N11: =AVERAGE(IncomeTable[Investment Return]) -> 31372 | O11: =AVERAGE(IncomeTable[Loan Return]) -> 0

Sheet Expenses
B2: Expected Yearly | C2: =SUM(E2:L2) -> 1466559 | D2: =12*D3 -> 2082996 | E2: =200000+50000 -> 250000 | F2: =25000+15000+20000 -> 60000 | G2: 720000 | H2: 150000 | I2: 120000 | J2: 60000 | K2: 60000 | L2: =_xlfn.CEILING.MATH(12*(BasicSalary*3.5%)) -> 46559
B3: Expected Monthly | C3: =SUM(E3:L3) -> 122214 | D3: =Loan!D3 -> 173583 | E3: =_xlfn.CEILING.MATH(E2/12) -> 20834 | F3: =_xlfn.CEILING.MATH(F2/12) -> 5000 | G3: =_xlfn.CEILING.MATH(G2/12) -> 60000 | H3: =_xlfn.CEILING.MATH(H2/12) -> 12500 | I3: =_xlfn.CEILING.MATH(I2/12) -> 10000 | J3: =_xlfn.CEILING.MATH(J2/12) -> 5000 | K3: =_xlfn.CEILING.MATH(K2/12) -> 5000 | L3: =_xlfn.CEILING.MATH(L2/12) -> 3880
B4: Month | C4: Actual Expense | D4: Loan EMI | E4: Kid | F4: Payments | G4: HouseHold | H4: Transport | I4: Family Care | J4: Shopping | K4: Luxary | L4: Support
B5: 45962 | C5: =SUM(ExpenseTable[[#This Row],[Kid]:[Support]]) -> 76341 | D5: =_xlfn.IFNA(INDEX( LoanTable[Total Loan], MATCH(ExpenseTable[[#This Row],[Month]], LoanTable[Month], 0) ),0) -> 244200 | E5: 2019 | F5: =1400+549+1100 -> 3049 | G5: =10000+8337+5080+3109+2386+1660 -> 30572 | H5: 11272 | I5: 5076 | J5: 14788 | K5: 4684 | L5: 4881
B6: 45992 | C6: =SUM(ExpenseTable[[#This Row],[Kid]:[Support]]) -> 105100 | D6: =_xlfn.IFNA(INDEX( LoanTable[Total Loan], MATCH(ExpenseTable[[#This Row],[Month]], LoanTable[Month], 0) ),0) -> 124803 | E6: 1193 | F6: =938+492+7494+199 -> 9123 | G6: =10260+7494+6341+500+3440+680+2047+827+99+335+1985+569+5600+5199+440+1450+1272+2494 -> 51032 | H6: =10500+6320+4480+5014+750-300 -> 26764 | I6: 3440 | J6: 2998 | K6: =2450+5900 -> 8350 | L6: 2200
B7: 46023 | C7: =SUM(ExpenseTable[[#This Row],[Kid]:[Support]]) -> 121465 | D7: =_xlfn.IFNA(INDEX( LoanTable[Total Loan], MATCH(ExpenseTable[[#This Row],[Month]], LoanTable[Month], 0) ),0) -> 158488 | E7: 845 | F7: =17950+4430+199+1112+2348 -> 26039 | G7: =15311+9591+6483+5350+5267 -> 42002 | H7: 32383 | I7: 13737 | J7: 445 | K7: =522+2894 -> 3416 | L7: 2598
B8: 46054 | C8: =SUM(ExpenseTable[[#This Row],[Kid]:[Support]]) -> 71006 | D8: =_xlfn.IFNA(INDEX( LoanTable[Total Loan], MATCH(ExpenseTable[[#This Row],[Month]], LoanTable[Month], 0) ),0) -> 154962 | E8: 1500 | F8: =800+199+150 -> 1149 | G8: =21960+2819+691 -> 25470 | H8: =7743+173 -> 7916 | I8: 24777 | J8: 6123 | K8: 2430 | L8: 1641
B9: 46082 | C9: =SUM(ExpenseTable[[#This Row],[Kid]:[Support]]) -> 113838 | D9: =_xlfn.IFNA(INDEX( LoanTable[Total Loan], MATCH(ExpenseTable[[#This Row],[Month]], LoanTable[Month], 0) ),0) -> 152098 | E9: 6097 | F9: =16551+199+35 -> 16785 | G9: =28951+9867+6513+5579+3003+3988 -> 57901 | H9: 1150 | I9: 6598 | J9: 20612 | K9: 2901 | L9: 1794
B10: 46113 | C10: =SUM(ExpenseTable[[#This Row],[Kid]:[Support]]) -> 0 | D10: =_xlfn.IFNA(INDEX( LoanTable[Total Loan], MATCH(ExpenseTable[[#This Row],[Month]], LoanTable[Month], 0) ),0) -> 0
B11: Total | C11: =SUBTOTAL(109,ExpenseTable[Actual Expense]) -> 487750 | D11: =SUBTOTAL(109,ExpenseTable[Loan EMI]) -> 834551 | E11: =SUBTOTAL(109,ExpenseTable[Kid]) -> 11654 | F11: =SUBTOTAL(109,ExpenseTable[Payments]) -> 56145 | G11: =SUBTOTAL(109,ExpenseTable[HouseHold]) -> 206977 | H11: =SUBTOTAL(109,ExpenseTable[Transport]) -> 79485 | I11: =SUBTOTAL(109,ExpenseTable[Family Care]) -> 53628 | J11: =SUBTOTAL(109,ExpenseTable[Shopping]) -> 44966 | K11: =SUBTOTAL(109,ExpenseTable[Luxary]) -> 21781 | L11: =SUBTOTAL(109,ExpenseTable[Support]) -> 13114
B12: Average | C12: =IFERROR(AVERAGE(ExpenseTable[Actual Expense]),0) -> 81291.667 | D12: =IFERROR(AVERAGE(ExpenseTable[Loan EMI]),0) -> 139091.83 | E12: =IFERROR(AVERAGE(ExpenseTable[Kid]),0) -> 2330.8 | F12: =IFERROR(AVERAGE(ExpenseTable[Payments]),0) -> 11229 | G12: =IFERROR(AVERAGE(ExpenseTable[HouseHold]),0) -> 41395.4 | H12: =IFERROR(AVERAGE(ExpenseTable[Transport]),0) -> 15897 | I12: =IFERROR(AVERAGE(ExpenseTable[Family Care]),0) -> 10725.6 | J12: =IFERROR(AVERAGE(ExpenseTable[Shopping]),0) -> 8993.2 | K12: =IFERROR(AVERAGE(ExpenseTable[Luxary]),0) -> 4356.2 | L12: =IFERROR(AVERAGE(ExpenseTable[Support]),0) -> 2622.8

Sheet Loan
B2: Opening Balance | E2: 4888992 | F2: 278700 | G2: 1574800 | H2: 471495 | I2: =1200000-(23000*5) -> 1085000 | J2: 120000 | K2: 89000 | L2: 56500 | M2: 50000 | N2: 75000 | O2: 135000 | P2: 40000 | R2: Balance | S2: Till 2026 | T2: EMI
B3: EMI | D3: =SUM(E3:P3) -> 173583 | E3: =IF(LoanTable[[#Totals],[Home Loan]]>0,18000) -> 18000 | F3: =IF(LoanTable[[#Totals],[Personal Loan]]>0,46450) -> 46450 | G3: =IF(LoanTable[[#Totals],[Car Loan]]>0,36800) -> 36800 | H3: =IF(LoanTable[[#Totals],[NBFC Loan (LIC)]]>0,2250) -> 2250 | I3: =IF(LoanTable[[#Totals],[EPF Loan]]>0,23000) -> 23000 | J3: =IF(LoanTable[[#Totals],[EPF Loan]]>0,13333) -> 13333 | K3: =IF(LoanTable[[#Totals],[Gadaget EMI]]>0,9000) -> 9000 | L3: =IF(LoanTable[[#Totals],[Credit Card EMI]]>0,12750) -> 12750 | M3: =IF(LoanTable[[#Totals],[Family loan]]>0,5000) -> 5000 | N3: =IF(LoanTable[[#Totals],[Credit Purchase]]>0,5000) -> 5000 | O3: =LoanTable[[#Totals],[Credit Card Due Till Nov -25 ]] -> 0 | P3: =IF(LoanTable[[#Totals],[Secret Partner]]>0,2000) -> 2000
B4: Year | C4: Month | D4: Total Loan | E4: Home Loan | F4: Personal Loan | G4: Car Loan | H4: NBFC Loan (LIC) | I4: EPF Loan | J4: Education Loan | K4: Gadaget EMI | L4: Credit Card EMI | M4: Family loan | N4: Credit Purchase | O4: Credit Card Due Till Nov -25 | P4: Secret Partner
B5: =TEXT(LoanTable[[#This Row],[Month]],"yyyy") -> 2025 | C5: 45962 | D5: =SUM(LoanTable[[#This Row],[Home Loan]:[Secret Partner]]) -> 244200 | E5: 18000 | F5: 46450 | G5: 0 | H5: 0 | I5: 23000 | J5: 0 | K5: 9000 | L5: 12750 | M5: 0 | N5: 0 | O5: 135000 | P5: 0
B6: =TEXT(LoanTable[[#This Row],[Month]],"yyyy") -> 2025 | C6: 45992 | D6: =SUM(LoanTable[[#This Row],[Home Loan]:[Secret Partner]]) -> 124803 | E6: 18000 | F6: 46450 | G6: 0 | H6: 15603 | I6: 23000 | J6: 0 | K6: 9000 | L6: 12750 | M6: 0 | N6: 0 | O6: 0 | P6: 0
B7: =TEXT(LoanTable[[#This Row],[Month]],"yyyy") -> 2026 | C7: 46023 | D7: =SUM(LoanTable[[#This Row],[Home Loan]:[Secret Partner]]) -> 158488 | E7: 18000 | F7: 46450 | G7: 0 | H7: 25640 | I7: 23000 | J7: 13648 | K7: 9000 | L7: 12750 | M7: 10000 | N7: 0 | O7: 0 | P7: 0
B8: =TEXT(LoanTable[[#This Row],[Month]],"yyyy") -> 2026 | C8: 46054 | D8: =SUM(LoanTable[[#This Row],[Home Loan]:[Secret Partner]]) -> 154962 | E8: 18000 | F8: 46450 | G8: 36800 | H8: 0 | I8: 23000 | J8: 13648 | K8: 9000 | L8: 8064 | M8: 0 | N8: 0 | O8: 0 | P8: 0
B9: =TEXT(LoanTable[[#This Row],[Month]],"yyyy") -> 2026 | C9: 46082 | D9: =SUM(LoanTable[[#This Row],[Home Loan]:[Secret Partner]]) -> 152098 | E9: 18000 | F9: 46450 | G9: 36800 | H9: 0 | I9: 23000 | J9: 13648 | K9: 9000 | L9: 5200 | M9: 0 | N9: 0 | O9: 0 | P9: 0
B10: =TEXT(LoanTable[[#This Row],[Month]],"yyyy") -> 2026 | C10: 46113 | D10: =SUM(LoanTable[[#This Row],[Home Loan]:[Secret Partner]]) -> 0
B11: =TEXT(LoanTable[[#This Row],[Month]],"yyyy") -> 1900 | D11: =SUM(LoanTable[[#This Row],[Home Loan]:[Secret Partner]]) -> 0
B12: Total | D12: =SUBTOTAL(109,LoanTable[Total Loan]) -> 834551 | E12: =E2-SUM(LoanTable[Home Loan]) -> 4798992 | F12: =F2-SUM(LoanTable[Personal Loan]) -> 46450 | G12: =G2-SUM(LoanTable[Car Loan]) -> 1501200 | H12: =H2-SUM(LoanTable[NBFC Loan (LIC)]) -> 430252 | I12: =I2-SUM(LoanTable[EPF Loan]) -> 970000 | K12: =K2-SUM(LoanTable[Gadaget EMI]) -> 44000 | L12: =L2-SUM(LoanTable[Credit Card EMI]) -> 4986 | M12: =M2-SUM(LoanTable[Family loan]) -> 40000 | N12: =N2-SUM(LoanTable[Credit Purchase]) -> 75000 | O12: =O2-SUM(LoanTable[Credit Card Due Till Nov -25 ]) -> 0 | P12: =P2-SUM(LoanTable[Secret Partner]) -> 40000
B13: Average | D13: =IFERROR(AVERAGE(LoanTable[Total Loan]),0) -> 119221.57 | E13: =IFERROR(AVERAGE(LoanTable[Home Loan]),0) -> 18000 | F13: =IFERROR(AVERAGE(LoanTable[Personal Loan]),0) -> 46450 | G13: =IFERROR(AVERAGE(LoanTable[Car Loan]),0) -> 14720 | H13: =IFERROR(AVERAGE(LoanTable[NBFC Loan (LIC)]),0) -> 8248.6 | I13: =IFERROR(AVERAGE(LoanTable[EPF Loan]),0) -> 23000 | K13: =IFERROR(AVERAGE(LoanTable[Gadaget EMI]),0) -> 9000 | L13: =IFERROR(AVERAGE(LoanTable[Credit Card EMI]),0) -> 10302.8 | M13: =IFERROR(AVERAGE(LoanTable[Family loan]),0) -> 2000 | N13: =IFERROR(AVERAGE(LoanTable[Credit Purchase]),0) -> 0 | O13: =IFERROR(AVERAGE(LoanTable[Credit Card Due Till Nov -25 ]),0) -> 27000 | P13: =IFERROR(AVERAGE(LoanTable[Secret Partner]),0) -> 0
H19: S.No | I19: Remaing Month | J19: Merchnat | K19: EMI Amount | L19: Tenure | M19: Total repayment | N19: Loan Distributor | O19: Remaining | P19: This Month | Q19: Remarks
H20: 1 | I20: =L20-DATEDIF(DATE(2025,11,1), TODAY(), "m") -> 13 | J20: LIC Intrest | K20: 27735 | L20: =13+DATEDIF(DATE(2025,11,1), TODAY(), "m") -> 18 | M20: =K20*L20 -> 499230 | N20: LIC | O20: =I20*K20 -> 360555 | P20: =IF(I20>0,K20) -> 27735
H21: 2 | I21: =L21-DATEDIF(DATE(2025,11,1), TODAY(), "m") -> 8 | J21: Home Loan | K21: 18000 | L21: 13 | M21: =K21*L21 -> 234000 | N21: Bhabhi | O21: =I21*K21 -> 144000 | P21: =IF(I21>0,K21) -> 18000
H22: 3 | I22: =L22-DATEDIF(DATE(2025,11,1), TODAY(), "m") -> 1 | J22: Personal Loan | K22: 46450 | L22: 6 | M22: =K22*L22 -> 278700 | N22: HSBC | O22: =I22*K22 -> 46450 | P22: =IF(I22>0,K22) -> 46450
H23: 4 | I23: =L23-DATEDIF(DATE(2025,11,1), TODAY(), "m") -> 8 | J23: NBFC Loan (LIC) | K23: 4250 | L23: 13 | M23: =K23*L23 -> 55250 | O23: =I23*K23 -> 34000 | P23: =IF(I23>0,K23) -> 4250
H24: 5 | I24: =L24-DATEDIF(DATE(2025,11,1), TODAY(), "m") -> 8 | J24: EPF Loan | K24: 23000 | L24: 13 | M24: =K24*L24 -> 299000 | N24: IDFC | O24: =I24*K24 -> 184000 | P24: =IF(I24>0,K24) -> 23000
H25: 6 | I25: =L25-DATEDIF(DATE(2025,11,1), TODAY(), "m") -> 1 | J25: Rati Iphone EMI | K25: =7000 -> 7000 | L25: 6 | M25: =K25*L25 -> 42000 | N25: SBI | O25: =I25*K25 -> 7000 | P25: =IF(I25>0,K25) -> 7000
H26: 7 | I26: =L26-DATEDIF(DATE(2025,11,1), TODAY(), "m") -> 8 | J26: My Iphone | K26: 2000 | L26: 13 | M26: =K26*L26 -> 26000 | N26: Salary | O26: =I26*K26 -> 16000 | P26: =IF(I26>0,K26) -> 2000
H27: 8 | I27: =L27-DATEDIF(DATE(2025,11,1), TODAY(), "m") -> 0 | J27: Orchid Hosptility | K27: 5200 | L27: 5 | M27: =K27*L27 -> 26000 | N27: AXIS Flipkart CC | O27: =I27*K27 -> 0 | P27: =IF(I27>0,K27) -> FALSE
H28: 9 | I28: =L28-DATEDIF(DATE(2025,11,1), TODAY(), "m") -> -2 | J28: MakeMytrip | K28: =2125 -> 2125 | L28: 3 | M28: =K28*L28 -> 6375 | O28: =I28*K28 -> -4250 | P28: =IF(I28>0,K28) -> FALSE | Q28: =SUM(P27:P31) -> 0
H29: 10 | I29: =L29-DATEDIF(DATE(2025,11,1), TODAY(), "m") -> -1 | J29: MakeMytrip | K29: =2691.99+172.51 -> 2864.5 | L29: 4 | M29: =K29*L29 -> 11458 | O29: =I29*K29 -> -2864.5 | P29: =IF(I29>0,K29) -> FALSE
H30: 11 | I30: =L30-DATEDIF(DATE(2025,11,1), TODAY(), "m") -> -2 | J30: MakeMytrip | K30: =1804+31 -> 1835 | L30: 3 | M30: =K30*L30 -> 5505 | O30: =I30*K30 -> -3670 | P30: =IF(I30>0,K30) -> FALSE
H31: 12 | I31: =L31-DATEDIF(DATE(2025,11,1), TODAY(), "m") -> -2 | J31: MakeMytrip | K31: =679+7 -> 686 | L31: 3 | M31: =K31*L31 -> 2058 | O31: =I31*K31 -> -1372 | P31: =IF(I31>0,K31) -> FALSE
H32: 13 | I32: =L32-DATEDIF(DATE(2025,11,1), TODAY(), "m") -> 10 | J32: Bhaiya | K32: 5000 | L32: =10+DATEDIF(DATE(2025,11,1), TODAY(), "m") -> 15 | M32: =K32*L32 -> 75000 | O32: =I32*K32 -> 50000 | P32: =IF(I32>0,K32) -> 5000
H33: 14 | I33: =L33-DATEDIF(DATE(2025,11,1), TODAY(), "m") -> 5 | J33: Abhishek Interior | K33: 15000 | L33: =5+DATEDIF(DATE(2025,11,1), TODAY(), "m") -> 10 | M33: =K33*L33 -> 150000 | O33: =I33*K33 -> 75000 | P33: =IF(I33>0,K33) -> 15000
H34: 15 | I34: =L34-DATEDIF(DATE(2025,11,1), TODAY(), "m") -> 12 | J34: Secret Partner | K34: 5000 | L34: =12+DATEDIF(DATE(2025,11,1), TODAY(), "m") -> 17 | M34: =K34*L34 -> 85000 | O34: =I34*K34 -> 60000 | P34: =IF(I34>0,K34) -> 5000
H35: 16 | I35: =L35-DATEDIF(DATE(2026,1,1), TODAY(), "m") -> 0 | J35: MakeMytrip | K35: =5200/3 -> 1733.3333 | L35: 3 | M35: =K35*L35 -> 5200 | N35: HSBC CC | O35: =I35*K35 -> 0 | P35: =IF(I35>0,K35) -> FALSE | Q35: Bomaby Trip
H36: 17 | I36: =L36-DATEDIF(DATE(2026,1,1), TODAY(), "m") -> 3 | J36: MakeMytrip | K36: 2000 | L36: 6 | M36: =K36*L36 -> 12000 | N36: AXIS Flipkart CC | O36: =I36*K36 -> 6000 | P36: =IF(I36>0,K36) -> 2000 | Q36: Mummy Flight Ticket
H37: 18 | I37: =L37-DATEDIF(DATE(2026,3,1), TODAY(), "m") -> 2 | J37: Flipkar | K37: 4000 | L37: 3 | M37: =K37*L37 -> 12000 | N37: AXIS Flipkart CC | O37: =I37*K37 -> 8000 | P37: =IF(I37>0,K37) -> 4000 | Q37: Didi Mobile
H38: 19 | I38: =L38-DATEDIF(DATE(2026,2,1), TODAY(), "m") -> 34 | J38: Car Loan | K38: 36800 | L38: 36 | M38: =K38*L38 -> 1324800 | N38: Salary | O38: =I38*K38 -> 1251200 | P38: =IF(I38>0,K38) -> 36800 | Q38: Car Loan
H39: 20 | I39: =L39-DATEDIF(DATE(2026,3,1), TODAY(), "m") -> 5 | J39: MakeMytrip | K39: 1900 | L39: 6 | M39: =K39*L39 -> 11400 | N39: HSBC CC | O39: =I39*K39 -> 9500 | P39: =IF(I39>0,K39) -> 1900 | Q39: Mummy Return Ticket
I40: Total | K40: =SUM(K20:K36) -> 169878.83 | L40: =SUM(L20:L36) -> 151 | M40: =SUM(M20:M36) -> 1812776 | N40: =SUM(N20:N36) -> 0 | O40: =SUM(O20:O36) -> 970848.5 | P40: =SUM(P20:P36) -> 155435

Sheet Investment
C2: Investment Quota | D2: ="Equity Limit : " -> Equity Limit : | E2: =_xlfn.FLOOR.MATH(InvestmentQuota*65%) -> 44513 | F2: ="Gold Limit : " -> Gold Limit : | I2: =_xlfn.FLOOR.MATH((InvestmentQuota*15%)) -> 10272 | J2: ="Fixed Return Limit : " -> Fixed Return Limit : | L2: =_xlfn.FLOOR.MATH(InvestmentQuota*20%) -> 13696 | M2: Real State | N2: 0
C3: =AVERAGE(IncomeTable[Total In Hand])*30% -> 68481.95 | D3: =E2*15% -> 6676.95 | E3: =E2*85% -> 37836.05 | F3: =I2*40% -> 4108.8 | G3: =I2*40% -> 4108.8 | H3: =I2*20% -> 2054.4 | I3: =I2*0% -> 0 | J3: =_xlfn.FLOOR.MATH(BasicSalary*24%) -> 26604 | K3: =_xlfn.FLOOR.MATH(BasicSalary*14%) -> 15519 | L3: 12500
C4: =3861068+(TotalMonth*InvestmentQuota) -> 4271959.7
B6: Entry Month | C6: Total Investment | D6: Stocks | E6: Mutual Fund | F6: Gold MF | G6: Gold ETF | H6: Gold | I6: SGB | J6: EPF | K6: NPS | L6: Sukanya Samriddhi | M6: Land | N6: Flat
B7: 45962 | C7: =SUM(InvestmentTable[[#This Row],[Stocks]:[Flat]]) -> 71670 | D7: =_xlfn.CEILING.MATH(SUMIFS(InvestTransactionTable[Invested Value],InvestTransactionTable[Type],"Stocks",InvestTransactionTable[Month],InvestmentTable[[#This Row],[Entry Month]])) -> 0 | E7: =_xlfn.CEILING.MATH(SUMIFS(InvestTransactionTable[Invested Value],InvestTransactionTable[Type],"Mutual Fund",InvestTransactionTable[Month],InvestmentTable[[#This Row],[Entry Month]])) -> 17055 | F7: =_xlfn.CEILING.MATH(SUMIFS(InvestTransactionTable[Invested Value],InvestTransactionTable[Type],"Gold MF",InvestTransactionTable[Month],InvestmentTable[[#This Row],[Entry Month]])) -> 0 | G7: =_xlfn.CEILING.MATH(SUMIFS(InvestTransactionTable[Invested Value],InvestTransactionTable[Type],"Gold ETF",InvestTransactionTable[Month],InvestmentTable[[#This Row],[Entry Month]])) -> 0 | H7: =_xlfn.CEILING.MATH(SUMIFS(InvestTransactionTable[Invested Value],InvestTransactionTable[Type],"Gold",InvestTransactionTable[Month],InvestmentTable[[#This Row],[Entry Month]])) -> 0 | I7: =_xlfn.CEILING.MATH(SUMIFS(InvestTransactionTable[Invested Value],InvestTransactionTable[Type],"Gold",InvestTransactionTable[Month],InvestmentTable[[#This Row],[Entry Month]])) -> 0 | J7: 26600 | K7: 15515 | L7: 12500 | M7: 0 | N7: 0
B8: 45992 | C8: =SUM(InvestmentTable[[#This Row],[Stocks]:[Flat]]) -> 86773 | D8: =12990+10000 -> 22990 | E8: =_xlfn.CEILING.MATH(SUMIFS(InvestTransactionTable[Invested Value],InvestTransactionTable[Type],"Mutual Fund",InvestTransactionTable[Month],InvestmentTable[[#This Row],[Entry Month]])) -> 7402 | F8: =_xlfn.CEILING.MATH(SUMIFS(InvestTransactionTable[Invested Value],InvestTransactionTable[Type],"Gold MF",InvestTransactionTable[Month],InvestmentTable[[#This Row],[Entry Month]])) -> 1766 | G8: =_xlfn.CEILING.MATH(SUMIFS(InvestTransactionTable[Invested Value],InvestTransactionTable[Type],"Gold ETF",InvestTransactionTable[Month],InvestmentTable[[#This Row],[Entry Month]])) -> 0 | H8: =_xlfn.CEILING.MATH(SUMIFS(InvestTransactionTable[Invested Value],InvestTransactionTable[Type],"Gold",InvestTransactionTable[Month],InvestmentTable[[#This Row],[Entry Month]])) -> 0 | I8: =_xlfn.CEILING.MATH(SUMIFS(InvestTransactionTable[Invested Value],InvestTransactionTable[Type],"Gold",InvestTransactionTable[Month],InvestmentTable[[#This Row],[Entry Month]])) -> 0 | J8: 26600 | K8: 15515 | L8: 12500 | M8: 0 | N8: 0
B9: 46023 | C9: =SUM(InvestmentTable[[#This Row],[Stocks]:[Flat]]) -> -26320 | D9: =575+5000+5000-200000 -> -189425 | E9: =_xlfn.CEILING.MATH(SUMIFS(InvestTransactionTable[Invested Value],InvestTransactionTable[Type],"Mutual Fund",InvestTransactionTable[Month],InvestmentTable[[#This Row],[Entry Month]])) -> 83993 | F9: =_xlfn.CEILING.MATH(SUMIFS(InvestTransactionTable[Invested Value],InvestTransactionTable[Type],"Gold MF",InvestTransactionTable[Month],InvestmentTable[[#This Row],[Entry Month]])) -> 6000 | G9: =_xlfn.CEILING.MATH(SUMIFS(InvestTransactionTable[Invested Value],InvestTransactionTable[Type],"Gold ETF",InvestTransactionTable[Month],InvestmentTable[[#This Row],[Entry Month]])) -> 19097 | H9: =_xlfn.CEILING.MATH(SUMIFS(InvestTransactionTable[Invested Value],InvestTransactionTable[Type],"Gold",InvestTransactionTable[Month],InvestmentTable[[#This Row],[Entry Month]])) -> 0 | I9: =_xlfn.CEILING.MATH(SUMIFS(InvestTransactionTable[Invested Value],InvestTransactionTable[Type],"Gold",InvestTransactionTable[Month],InvestmentTable[[#This Row],[Entry Month]])) -> 0 | J9: 26000 | K9: 15515 | L9: 12500 | M9: 0 | N9: 0
B10: 46054 | C10: =SUM(InvestmentTable[[#This Row],[Stocks]:[Flat]]) -> 105136 | D10: 0 | E10: =_xlfn.CEILING.MATH(SUMIFS(InvestTransactionTable[Invested Value],InvestTransactionTable[Type],"Mutual Fund",InvestTransactionTable[Month],InvestmentTable[[#This Row],[Entry Month]])) -> 35002 | F10: =_xlfn.CEILING.MATH(SUMIFS(InvestTransactionTable[Invested Value],InvestTransactionTable[Type],"Gold MF",InvestTransactionTable[Month],InvestmentTable[[#This Row],[Entry Month]])) -> 4000 | G10: =_xlfn.CEILING.MATH(SUMIFS(InvestTransactionTable[Invested Value],InvestTransactionTable[Type],"Gold ETF",InvestTransactionTable[Month],InvestmentTable[[#This Row],[Entry Month]])) -> 12119 | H10: =_xlfn.CEILING.MATH(SUMIFS(InvestTransactionTable[Invested Value],InvestTransactionTable[Type],"Gold",InvestTransactionTable[Month],InvestmentTable[[#This Row],[Entry Month]])) -> 0 | I10: =_xlfn.CEILING.MATH(SUMIFS(InvestTransactionTable[Invested Value],InvestTransactionTable[Type],"Gold",InvestTransactionTable[Month],InvestmentTable[[#This Row],[Entry Month]])) -> 0 | J10: 26000 | K10: 15515 | L10: 12500 | M10: 0 | N10: 0
B11: 46082 | C11: =SUM(InvestmentTable[[#This Row],[Stocks]:[Flat]]) -> 129873 | D11: =50000+10000+3000 -> 63000 | E11: =_xlfn.CEILING.MATH(SUMIFS(InvestTransactionTable[Invested Value],InvestTransactionTable[Type],"Mutual Fund",InvestTransactionTable[Month],InvestmentTable[[#This Row],[Entry Month]])) -> 2976 | F11: =_xlfn.CEILING.MATH(SUMIFS(InvestTransactionTable[Invested Value],InvestTransactionTable[Type],"Gold MF",InvestTransactionTable[Month],InvestmentTable[[#This Row],[Entry Month]])) -> 4000 | G11: =_xlfn.CEILING.MATH(SUMIFS(InvestTransactionTable[Invested Value],InvestTransactionTable[Type],"Gold ETF",InvestTransactionTable[Month],InvestmentTable[[#This Row],[Entry Month]])) -> 5882 | H11: =_xlfn.CEILING.MATH(SUMIFS(InvestTransactionTable[Invested Value],InvestTransactionTable[Type],"Gold",InvestTransactionTable[Month],InvestmentTable[[#This Row],[Entry Month]])) -> 0 | I11: =_xlfn.CEILING.MATH(SUMIFS(InvestTransactionTable[Invested Value],InvestTransactionTable[Type],"Gold",InvestTransactionTable[Month],InvestmentTable[[#This Row],[Entry Month]])) -> 0 | J11: 26000 | K11: 15515 | L11: 12500 | M11: 0 | N11: 0
B12: 46113 | C12: =SUM(InvestmentTable[[#This Row],[Stocks]:[Flat]]) -> 0 | E12: =_xlfn.CEILING.MATH(SUMIFS(InvestTransactionTable[Invested Value],InvestTransactionTable[Type],"Mutual Fund",InvestTransactionTable[Month],InvestmentTable[[#This Row],[Entry Month]])) -> 0 | F12: =_xlfn.CEILING.MATH(SUMIFS(InvestTransactionTable[Invested Value],InvestTransactionTable[Type],"Gold MF",InvestTransactionTable[Month],InvestmentTable[[#This Row],[Entry Month]])) -> 0 | G12: =_xlfn.CEILING.MATH(SUMIFS(InvestTransactionTable[Invested Value],InvestTransactionTable[Type],"Gold ETF",InvestTransactionTable[Month],InvestmentTable[[#This Row],[Entry Month]])) -> 0 | H12: =_xlfn.CEILING.MATH(SUMIFS(InvestTransactionTable[Invested Value],InvestTransactionTable[Type],"Gold",InvestTransactionTable[Month],InvestmentTable[[#This Row],[Entry Month]])) -> 0 | I12: =_xlfn.CEILING.MATH(SUMIFS(InvestTransactionTable[Invested Value],InvestTransactionTable[Type],"Gold",InvestTransactionTable[Month],InvestmentTable[[#This Row],[Entry Month]])) -> 0
B13: Total | C13: =SUBTOTAL(109,InvestmentTable[Total Investment]) -> 367132 | D13: =SUBTOTAL(109,InvestmentTable[Stocks]) -> -103435 | E13: =SUBTOTAL(109,InvestmentTable[Mutual Fund]) -> 146428 | F13: =SUBTOTAL(109,InvestmentTable[Gold MF]) -> 15766 | G13: =SUBTOTAL(109,InvestmentTable[Gold ETF]) -> 37098 | H13: =SUBTOTAL(109,InvestmentTable[Gold]) -> 0 | I13: =SUBTOTAL(109,InvestmentTable[SGB]) -> 0 | J13: =SUBTOTAL(109,InvestmentTable[EPF]) -> 131200 | K13: =SUBTOTAL(109,InvestmentTable[NPS]) -> 77575 | L13: =SUBTOTAL(109,InvestmentTable[Sukanya Samriddhi]) -> 62500 | M13: =SUBTOTAL(109,InvestmentTable[Land]) -> 0 | N13: =SUBTOTAL(109,InvestmentTable[Flat]) -> 0
B14: Average | C14: =IFERROR(AVERAGE(InvestmentTable[Total Investment]),0) -> 61188.667 | D14: =IFERROR(_xlfn.CEILING.MATH(AVERAGE(InvestmentTable[Stocks])),0) -> -20687 | E14: =IFERROR(_xlfn.CEILING.MATH(AVERAGE(InvestmentTable[Mutual Fund])),0) -> 24405 | F14: =IFERROR(_xlfn.CEILING.MATH(AVERAGE(InvestmentTable[Gold MF])),0) -> 2628 | G14: =IFERROR(_xlfn.CEILING.MATH(AVERAGE(InvestmentTable[Gold ETF])),0) -> 6183 | H14: =IFERROR(_xlfn.CEILING.MATH(AVERAGE(InvestmentTable[Gold])),0) -> 0 | I14: =IFERROR(_xlfn.CEILING.MATH(AVERAGE(InvestmentTable[SGB])),0) -> 0 | J14: =IFERROR(_xlfn.CEILING.MATH(AVERAGE(InvestmentTable[EPF])),0) -> 26240 | K14: =IFERROR(_xlfn.CEILING.MATH(AVERAGE(InvestmentTable[NPS])),0) -> 15515 | L14: =IFERROR(_xlfn.CEILING.MATH(AVERAGE(InvestmentTable[Sukanya Samriddhi])),0) -> 12500 | M14: =IFERROR(_xlfn.CEILING.MATH(AVERAGE(InvestmentTable[Land])),0) -> 0 | N14: =IFERROR(_xlfn.CEILING.MATH(AVERAGE(InvestmentTable[Flat])),0) -> 0

Sheet Corpus
B1: Corpus - 2 Crore Till Dec 2027
B3: Asset | C3: Type | D3: Invested Till Oct 25 | E3: Actual Till Oct-25 | F3: Profit Till Oct-25 | G3: Allocation % Till Oct 25 | H3: Return % Till Date | I3: Invested Since Nov-25 | J3: Allocation % | K3: Invested | L3: Current Value | M3: Return | N3: Return% | O3: Wallet
B4: Stocks | C4: Equity | D4: 2186094 | E4: 3800000 | F4: =CorpusTable[[#This Row],[Actual Till Oct-25]]-CorpusTable[[#This Row],[Invested Till Oct 25]] -> 1613906 | G4: =CorpusTable[[#This Row],[Invested Till Oct 25]]/CorpusTable[[#Totals],[Invested Till Oct 25]] -> 0.29850016 | H4: =IFERROR((CorpusTable[[#This Row],[Actual Till Oct-25]]-CorpusTable[[#This Row],[Invested Till Oct 25]])/CorpusTable[[#This Row],[Invested Till Oct 25]],0) -> 0.73826011 | I4: =InvestmentTable[[#Totals],[Stocks]] -> -103435 | J4: =CorpusTable[[#This Row],[Invested Since Nov-25]]/CorpusTable[[#Totals],[Invested Since Nov-25]] -> -0.2817379 | K4: =CorpusTable[[#This Row],[Invested Till Oct 25]]+CorpusTable[[#This Row],[Invested Since Nov-25]] -> 2082659 | L4: =SUMIFS(AllocationTable[CURRENT VALUE],AllocationTable[TYPE],CorpusTable[[#This Row],[Asset]])+CorpusTable[[#This Row],[Wallet]] -> 3690870 | M4: =CorpusTable[[#This Row],[Current Value]]-CorpusTable[[#This Row],[Invested]] -> 1608211 | N4: =IFERROR(CorpusTable[[#This Row],[Return]]/CorpusTable[[#This Row],[Invested]],"-") -> 0.7721912 | O4: 99
B5: Mutual Fund | C5: Equity | D5: 600000 | E5: 1225000 | F5: =CorpusTable[[#This Row],[Actual Till Oct-25]]-CorpusTable[[#This Row],[Invested Till Oct 25]] -> 625000 | G5: =CorpusTable[[#This Row],[Invested Till Oct 25]]/CorpusTable[[#Totals],[Invested Till Oct 25]] -> 0.081926988 | H5: =IFERROR((CorpusTable[[#This Row],[Actual Till Oct-25]]-CorpusTable[[#This Row],[Invested Till Oct 25]])/CorpusTable[[#This Row],[Invested Till Oct 25]],0) -> 1.0416667 | I5: =InvestmentTable[[#Totals],[Mutual Fund]] -> 146428 | J5: =CorpusTable[[#This Row],[Invested Since Nov-25]]/CorpusTable[[#Totals],[Invested Since Nov-25]] -> 0.39884292 | K5: =CorpusTable[[#This Row],[Invested Till Oct 25]]+CorpusTable[[#This Row],[Invested Since Nov-25]] -> 746428 | L5: =SUMIFS(AllocationTable[CURRENT VALUE],AllocationTable[TYPE],CorpusTable[[#This Row],[Asset]])+CorpusTable[[#This Row],[Wallet]] -> 1324367.9 | M5: =CorpusTable[[#This Row],[Current Value]]-CorpusTable[[#This Row],[Invested]] -> 577939.93 | N5: =IFERROR(CorpusTable[[#This Row],[Return]]/CorpusTable[[#This Row],[Invested]],"-") -> 0.77427419
B6: Sukanya Samriddhi | C6: Fixed Return | D6: 705400 | E6: 795391 | F6: =CorpusTable[[#This Row],[Actual Till Oct-25]]-CorpusTable[[#This Row],[Invested Till Oct 25]] -> 89991 | G6: =CorpusTable[[#This Row],[Invested Till Oct 25]]/CorpusTable[[#Totals],[Invested Till Oct 25]] -> 0.096318829 | H6: =IFERROR((CorpusTable[[#This Row],[Actual Till Oct-25]]-CorpusTable[[#This Row],[Invested Till Oct 25]])/CorpusTable[[#This Row],[Invested Till Oct 25]],0) -> 0.12757443 | I6: =InvestmentTable[[#Totals],[Sukanya Samriddhi]] -> 62500 | J6: =CorpusTable[[#This Row],[Invested Since Nov-25]]/CorpusTable[[#Totals],[Invested Since Nov-25]] -> 0.1702385 | K6: =CorpusTable[[#This Row],[Invested Till Oct 25]]+CorpusTable[[#This Row],[Invested Since Nov-25]] -> 767900 | L6: =SUMIFS(AllocationTable[CURRENT VALUE],AllocationTable[TYPE],CorpusTable[[#This Row],[Asset]])+CorpusTable[[#This Row],[Wallet]] -> 921405.24 | M6: =CorpusTable[[#This Row],[Current Value]]-CorpusTable[[#This Row],[Invested]] -> 153505.24 | N6: =IFERROR(CorpusTable[[#This Row],[Return]]/CorpusTable[[#This Row],[Invested]],"-") -> 0.19990264
B7: EPF/PPF | C7: Fixed Return | D7: 1800000 | E7: =2344530+100000+61306 -> 2505836 | F7: =CorpusTable[[#This Row],[Actual Till Oct-25]]-CorpusTable[[#This Row],[Invested Till Oct 25]] -> 705836 | G7: =CorpusTable[[#This Row],[Invested Till Oct 25]]/CorpusTable[[#Totals],[Invested Till Oct 25]] -> 0.24578096 | H7: =IFERROR((CorpusTable[[#This Row],[Actual Till Oct-25]]-CorpusTable[[#This Row],[Invested Till Oct 25]])/CorpusTable[[#This Row],[Invested Till Oct 25]],0) -> 0.39213111 | I7: =InvestmentTable[[#Totals],[EPF]] -> 131200 | J7: =CorpusTable[[#This Row],[Invested Since Nov-25]]/CorpusTable[[#Totals],[Invested Since Nov-25]] -> 0.35736465 | K7: =CorpusTable[[#This Row],[Invested Till Oct 25]]+CorpusTable[[#This Row],[Invested Since Nov-25]] -> 1931200 | L7: =SUMIFS(AllocationTable[CURRENT VALUE],AllocationTable[TYPE],CorpusTable[[#This Row],[Asset]])+CorpusTable[[#This Row],[Wallet]] -> 2558542.4 | M7: =CorpusTable[[#This Row],[Current Value]]-CorpusTable[[#This Row],[Invested]] -> 627342.4 | N7: =IFERROR(CorpusTable[[#This Row],[Return]]/CorpusTable[[#This Row],[Invested]],"-") -> 0.3248459
B8: NPS | C8: Retirement | D8: 962526 | E8: 1500788 | F8: =CorpusTable[[#This Row],[Actual Till Oct-25]]-CorpusTable[[#This Row],[Invested Till Oct 25]] -> 538262 | G8: =CorpusTable[[#This Row],[Invested Till Oct 25]]/CorpusTable[[#Totals],[Invested Till Oct 25]] -> 0.13142809 | H8: =IFERROR((CorpusTable[[#This Row],[Actual Till Oct-25]]-CorpusTable[[#This Row],[Invested Till Oct 25]])/CorpusTable[[#This Row],[Invested Till Oct 25]],0) -> 0.55921814 | I8: =InvestmentTable[[#Totals],[NPS]] -> 77575 | J8: =CorpusTable[[#This Row],[Invested Since Nov-25]]/CorpusTable[[#Totals],[Invested Since Nov-25]] -> 0.21130002 | K8: =CorpusTable[[#This Row],[Invested Till Oct 25]]+CorpusTable[[#This Row],[Invested Since Nov-25]] -> 1040101 | L8: =SUMIFS(AllocationTable[CURRENT VALUE],AllocationTable[TYPE],CorpusTable[[#This Row],[Asset]])+CorpusTable[[#This Row],[Wallet]] -> 1521019.5 | M8: =CorpusTable[[#This Row],[Current Value]]-CorpusTable[[#This Row],[Invested]] -> 480918.54 | N8: =IFERROR(CorpusTable[[#This Row],[Return]]/CorpusTable[[#This Row],[Invested]],"-") -> 0.46237677
B9: Gold MF | C9: Gold | D9: 29000 | E9: 43000 | F9: =CorpusTable[[#This Row],[Actual Till Oct-25]]-CorpusTable[[#This Row],[Invested Till Oct 25]] -> 14000 | G9: =CorpusTable[[#This Row],[Invested Till Oct 25]]/CorpusTable[[#Totals],[Invested Till Oct 25]] -> 0.0039598044 | H9: =IFERROR((CorpusTable[[#This Row],[Actual Till Oct-25]]-CorpusTable[[#This Row],[Invested Till Oct 25]])/CorpusTable[[#This Row],[Invested Till Oct 25]],0) -> 0.48275862 | I9: =InvestmentTable[[#Totals],[Gold MF]] -> 15766 | J9: =CorpusTable[[#This Row],[Invested Since Nov-25]]/CorpusTable[[#Totals],[Invested Since Nov-25]] -> 0.042943682 | K9: =CorpusTable[[#This Row],[Invested Till Oct 25]]+CorpusTable[[#This Row],[Invested Since Nov-25]] -> 44766 | L9: =SUMIFS(AllocationTable[CURRENT VALUE],AllocationTable[TYPE],CorpusTable[[#This Row],[Asset]])+CorpusTable[[#This Row],[Wallet]] -> 72019.929 | M9: =CorpusTable[[#This Row],[Current Value]]-CorpusTable[[#This Row],[Invested]] -> 27253.929 | N9: =IFERROR(CorpusTable[[#This Row],[Return]]/CorpusTable[[#This Row],[Invested]],"-") -> 0.60880867
B10: Gold ETF | C10: Gold | D10: 88324 | E10: 117000 | F10: =CorpusTable[[#This Row],[Actual Till Oct-25]]-CorpusTable[[#This Row],[Invested Till Oct 25]] -> 28676 | G10: =CorpusTable[[#This Row],[Invested Till Oct 25]]/CorpusTable[[#Totals],[Invested Till Oct 25]] -> 0.012060199 | H10: =IFERROR((CorpusTable[[#This Row],[Actual Till Oct-25]]-CorpusTable[[#This Row],[Invested Till Oct 25]])/CorpusTable[[#This Row],[Invested Till Oct 25]],0) -> 0.32466827 | I10: =InvestmentTable[[#Totals],[Gold ETF]] -> 37098 | J10: =CorpusTable[[#This Row],[Invested Since Nov-25]]/CorpusTable[[#Totals],[Invested Since Nov-25]] -> 0.10104812 | K10: =CorpusTable[[#This Row],[Invested Till Oct 25]]+CorpusTable[[#This Row],[Invested Since Nov-25]] -> 125422 | L10: =SUMIFS(AllocationTable[CURRENT VALUE],AllocationTable[TYPE],CorpusTable[[#This Row],[Asset]])+CorpusTable[[#This Row],[Wallet]] -> 179271.05 | M10: =CorpusTable[[#This Row],[Current Value]]-CorpusTable[[#This Row],[Invested]] -> 53849.05 | N10: =IFERROR(CorpusTable[[#This Row],[Return]]/CorpusTable[[#This Row],[Invested]],"-") -> 0.42934294
B11: Gold | C11: Gold | D11: =9500*5.5 -> 52250 | E11: =10500*5.5 -> 57750 | F11: =CorpusTable[[#This Row],[Actual Till Oct-25]]-CorpusTable[[#This Row],[Invested Till Oct 25]] -> 5500 | G11: =CorpusTable[[#This Row],[Invested Till Oct 25]]/CorpusTable[[#Totals],[Invested Till Oct 25]] -> 0.0071344752 | H11: =IFERROR((CorpusTable[[#This Row],[Actual Till Oct-25]]-CorpusTable[[#This Row],[Invested Till Oct 25]])/CorpusTable[[#This Row],[Invested Till Oct 25]],0) -> 0.10526316 | I11: =InvestmentTable[[#Totals],[Gold]] -> 0 | J11: =CorpusTable[[#This Row],[Invested Since Nov-25]]/CorpusTable[[#Totals],[Invested Since Nov-25]] -> 0 | K11: =CorpusTable[[#This Row],[Invested Till Oct 25]]+CorpusTable[[#This Row],[Invested Since Nov-25]] -> 52250 | L11: =SUMIFS(AllocationTable[CURRENT VALUE],AllocationTable[TYPE],CorpusTable[[#This Row],[Asset]])+CorpusTable[[#This Row],[Wallet]] -> 77055 | M11: =CorpusTable[[#This Row],[Current Value]]-CorpusTable[[#This Row],[Invested]] -> 24805 | N11: =IFERROR(CorpusTable[[#This Row],[Return]]/CorpusTable[[#This Row],[Invested]],"-") -> 0.47473684
B12: SGB | C12: Gold | D12: 200000 | E12: =36*12500 -> 450000 | F12: =CorpusTable[[#This Row],[Actual Till Oct-25]]-CorpusTable[[#This Row],[Invested Till Oct 25]] -> 250000 | G12: =CorpusTable[[#This Row],[Invested Till Oct 25]]/CorpusTable[[#Totals],[Invested Till Oct 25]] -> 0.027308996 | H12: =IFERROR((CorpusTable[[#This Row],[Actual Till Oct-25]]-CorpusTable[[#This Row],[Invested Till Oct 25]])/CorpusTable[[#This Row],[Invested Till Oct 25]],0) -> 1.25 | I12: =InvestmentTable[[#Totals],[SGB]] -> 0 | J12: =CorpusTable[[#This Row],[Invested Since Nov-25]]/CorpusTable[[#Totals],[Invested Since Nov-25]] -> 0 | K12: =CorpusTable[[#This Row],[Invested Till Oct 25]]+CorpusTable[[#This Row],[Invested Since Nov-25]] -> 200000 | L12: =SUMIFS(AllocationTable[CURRENT VALUE],AllocationTable[TYPE],CorpusTable[[#This Row],[Asset]])+CorpusTable[[#This Row],[Wallet]] -> 550260 | M12: =CorpusTable[[#This Row],[Current Value]]-CorpusTable[[#This Row],[Invested]] -> 350260 | N12: =IFERROR(CorpusTable[[#This Row],[Return]]/CorpusTable[[#This Row],[Invested]],"-") -> 1.7513
B13: Flat | C13: Real State | D13: 0 | E13: 0 | F13: =CorpusTable[[#This Row],[Actual Till Oct-25]]-CorpusTable[[#This Row],[Invested Till Oct 25]] -> 0 | G13: =CorpusTable[[#This Row],[Invested Till Oct 25]]/CorpusTable[[#Totals],[Invested Till Oct 25]] -> 0 | H13: =IFERROR((CorpusTable[[#This Row],[Actual Till Oct-25]]-CorpusTable[[#This Row],[Invested Till Oct 25]])/CorpusTable[[#This Row],[Invested Till Oct 25]],0) -> 0 | I13: =InvestmentTable[[#Totals],[Flat]] -> 0 | J13: =CorpusTable[[#This Row],[Invested Since Nov-25]]/CorpusTable[[#Totals],[Invested Since Nov-25]] -> 0 | K13: =CorpusTable[[#This Row],[Invested Till Oct 25]]+CorpusTable[[#This Row],[Invested Since Nov-25]] -> 0 | L13: =SUMIFS(AllocationTable[CURRENT VALUE],AllocationTable[TYPE],CorpusTable[[#This Row],[Asset]])+CorpusTable[[#This Row],[Wallet]] -> 0 | M13: =CorpusTable[[#This Row],[Current Value]]-CorpusTable[[#This Row],[Invested]] -> 0 | N13: =IFERROR(CorpusTable[[#This Row],[Return]]/CorpusTable[[#This Row],[Invested]],"-") -> -
B14: Land | C14: Real State | D14: 700000 | E14: =1100*1500 -> 1650000 | F14: =CorpusTable[[#This Row],[Actual Till Oct-25]]-CorpusTable[[#This Row],[Invested Till Oct 25]] -> 950000 | G14: =CorpusTable[[#This Row],[Invested Till Oct 25]]/CorpusTable[[#Totals],[Invested Till Oct 25]] -> 0.095581486 | H14: =IFERROR((CorpusTable[[#This Row],[Actual Till Oct-25]]-CorpusTable[[#This Row],[Invested Till Oct 25]])/CorpusTable[[#This Row],[Invested Till Oct 25]],0) -> 1.3571429 | I14: =InvestmentTable[[#Totals],[Land]] -> 0 | J14: =CorpusTable[[#This Row],[Invested Since Nov-25]]/CorpusTable[[#Totals],[Invested Since Nov-25]] -> 0 | K14: =CorpusTable[[#This Row],[Invested Till Oct 25]]+CorpusTable[[#This Row],[Invested Since Nov-25]] -> 700000 | L14: =SUMIFS(AllocationTable[CURRENT VALUE],AllocationTable[TYPE],CorpusTable[[#This Row],[Asset]])+CorpusTable[[#This Row],[Wallet]] -> 1650000 | M14: =CorpusTable[[#This Row],[Current Value]]-CorpusTable[[#This Row],[Invested]] -> 950000 | N14: =IFERROR(CorpusTable[[#This Row],[Return]]/CorpusTable[[#This Row],[Invested]],"-") -> 1.3571429
B15: Total | D15: =SUBTOTAL(109,CorpusTable[Invested Till Oct 25]) -> 7323594 | E15: =SUBTOTAL(109,CorpusTable[Actual Till Oct-25]) -> 12144765 | F15: =SUBTOTAL(109,CorpusTable[Profit Till Oct-25]) -> 4821171 | G15: =SUBTOTAL(109,CorpusTable[Allocation % Till Oct 25]) -> 1 | H15: =SUBTOTAL(101,CorpusTable[Return % Till Date]) -> 0.57988031 | I15: =SUBTOTAL(109,CorpusTable[Invested Since Nov-25]) -> 367132 | J15: =SUBTOTAL(109,CorpusTable[Allocation %]) -> 1 | K15: =SUBTOTAL(109,CorpusTable[Invested]) -> 7690726 | L15: =SUBTOTAL(109,CorpusTable[Current Value]) -> 12544811 | M15: =SUBTOTAL(109,CorpusTable[Return]) -> 4854085.1 | N15: =SUBTOTAL(101,CorpusTable[Return%]) -> 0.7154922
D17: Long Term | E17: 0.7 | F17: =C18*E17 -> 1916098.1
B18: Actual Stocks Allocation | C18: =SUMIF(AllocationTable[TYPE],"Stocks",AllocationTable[AA])+O4 -> 2737283
D19: Swing Trade | E19: 0.3 | F19: =C18*E19 -> 821184.9
B21: Month | C21: Transactions
B22: 45931 | C22: 128000
B23: 45962 | C23: =IFERROR(C22-INDEX( Table3[Month], MATCH(RBITable[[#This Row],[Month]], RBITable[Month], 0) ),0) -> 82008
B24: 45992 | C24: =IFERROR(C23-INDEX( Table3[Month], MATCH(RBITable[[#This Row],[Month]], RBITable[Month], 0) ),0) -> 35985
B25: 46023 | C25: =IFERROR(C24-INDEX( Table3[Month], MATCH(RBITable[[#This Row],[Month]], RBITable[Month], 0) ),0) -> -10069
B26: 46054 | C26: =IFERROR(C25-INDEX( Table3[Month], MATCH(RBITable[[#This Row],[Month]], RBITable[Month], 0) ),0) -> -56151
B27: 46082 | C27: =IFERROR(C26-INDEX( Table3[Month], MATCH(RBITable[[#This Row],[Month]], RBITable[Month], 0) ),0) -> -102264
B28: 46113 | C28: =IFERROR(C27-INDEX( Table3[Month], MATCH(RBITable[[#This Row],[Month]], RBITable[Month], 0) ),0) -> 0
B29: 46143 | C29: =IFERROR(C28-INDEX( Table3[Month], MATCH(RBITable[[#This Row],[Month]], RBITable[Month], 0) ),0) -> 0
B30: 46174 | C30: =IFERROR(C29-INDEX( Table3[Month], MATCH(RBITable[[#This Row],[Month]], RBITable[Month], 0) ),0) -> 0
B31: 46204 | C31: =IFERROR(C30-INDEX( Table3[Month], MATCH(RBITable[[#This Row],[Month]], RBITable[Month], 0) ),0) -> 0
B32: 46235 | C32: =IFERROR(C31-INDEX( Table3[Month], MATCH(RBITable[[#This Row],[Month]], RBITable[Month], 0) ),0) -> 0
B33: 46266 | C33: =IFERROR(C32-INDEX( Table3[Month], MATCH(RBITable[[#This Row],[Month]], RBITable[Month], 0) ),0) -> 0
B34: 46296 | C34: =IFERROR(C33-INDEX( Table3[Month], MATCH(RBITable[[#This Row],[Month]], RBITable[Month], 0) ),0) -> 0
... B36: 46357 | C36: =IFERROR(C35-INDEX( Table3[Month], MATCH(RBITable[[#This Row],[Month]], RBITable[Month], 0) ),0) -> 0

Sheet LongTerm
A1: TRADE | B1: TYPE | C1: SECTOR | D1: QNT | E1: AVG. | F1: LTP | G1: Available Quota | H1: PROFIT | I1: PROFIT% | J1: CURRENT VALUE | K1: EA% | L1: AA% | M1: EA | N1: AA | O1: MARKET CAP
A2: MCX | B2: Stocks | C2: =VLOOKUP(AllocationTable9[[#This Row],[TRADE]],AllocationTable[[TRADE]:[SECTOR]],2,0) -> FINANCIAL SERVICES | D2: 90 | E2: 708.17 | F2: =VLOOKUP(AllocationTable9[[#This Row],[TRADE]],LatestDump!A:I,4,0) -> 2669.4 | G2: =AllocationTable9[[#This Row],[EA]]-AllocationTable9[[#This Row],[AA]] -> 36264.7 | H2: =(AllocationTable9[[#This Row],[QNT]]*AllocationTable9[[#This Row],[LTP]])-(AllocationTable9[[#This Row],[QNT]]*AllocationTable9[[#This Row],[AVG.]]) -> 176510.7 | I2: =IFERROR(AllocationTable9[[#This Row],[PROFIT]]/AllocationTable9[[#This Row],[AA]],0) -> 2.7694339 | J2: =AllocationTable9[[#This Row],[QNT]]*AllocationTable9[[#This Row],[LTP]] -> 240246 | K2: =AllocationTable9[[#This Row],[EA]]/AllocationTable9[[#Totals],[EA]] -> 0.078125 | L2: =AllocationTable9[[#This Row],[AA]]/AllocationTable9[[#Totals],[AA]] -> 0.051913118 | M2: 100000 | N2: =AllocationTable9[[#This Row],[QNT]]*AllocationTable9[[#This Row],[AVG.]] -> 63735.3 | O2: MCAP
A3: IRFC | B3: Stocks | C3: =VLOOKUP(AllocationTable9[[#This Row],[TRADE]],AllocationTable[[TRADE]:[SECTOR]],2,0) -> ENGINEERING & CAPITAL GOODS | D3: 750 | E3: 36.22 | F3: =VLOOKUP(AllocationTable9[[#This Row],[TRADE]],LatestDump!A:I,4,0) -> 100.26 | G3: =AllocationTable9[[#This Row],[EA]]-AllocationTable9[[#This Row],[AA]] -> 22835 | H3: =(AllocationTable9[[#This Row],[QNT]]*AllocationTable9[[#This Row],[LTP]])-(AllocationTable9[[#This Row],[QNT]]*AllocationTable9[[#This Row],[AVG.]]) -> 48030 | I3: =IFERROR(AllocationTable9[[#This Row],[PROFIT]]/AllocationTable9[[#This Row],[AA]],0) -> 1.7680839 | J3: =AllocationTable9[[#This Row],[QNT]]*AllocationTable9[[#This Row],[LTP]] -> 75195 | K3: =AllocationTable9[[#This Row],[EA]]/AllocationTable9[[#Totals],[EA]] -> 0.0390625 | L3: =AllocationTable9[[#This Row],[AA]]/AllocationTable9[[#Totals],[AA]] -> 0.022126198 | M3: 50000 | N3: =AllocationTable9[[#This Row],[QNT]]*AllocationTable9[[#This Row],[AVG.]] -> 27165 | O3: LCAP
A4: ATHERENERG | B4: Stocks | C4: =VLOOKUP(AllocationTable9[[#This Row],[TRADE]],AllocationTable[[TRADE]:[SECTOR]],2,0) -> AUTO ANCILLARY | D4: 100 | E4: 315.91 | F4: =VLOOKUP(AllocationTable9[[#This Row],[TRADE]],LatestDump!A:I,4,0) -> 863.45 | G4: =AllocationTable9[[#This Row],[EA]]-AllocationTable9[[#This Row],[AA]] -> 18409 | H4: =(AllocationTable9[[#This Row],[QNT]]*AllocationTable9[[#This Row],[LTP]])-(AllocationTable9[[#This Row],[QNT]]*AllocationTable9[[#This Row],[AVG.]]) -> 54754 | I4: =IFERROR(AllocationTable9[[#This Row],[PROFIT]]/AllocationTable9[[#This Row],[AA]],0) -> 1.7332152 | J4: =AllocationTable9[[#This Row],[QNT]]*AllocationTable9[[#This Row],[LTP]] -> 86345 | K4: =AllocationTable9[[#This Row],[EA]]/AllocationTable9[[#Totals],[EA]] -> 0.0390625 | L4: =AllocationTable9[[#This Row],[AA]]/AllocationTable9[[#Totals],[AA]] -> 0.025731224 | M4: 50000 | N4: =AllocationTable9[[#This Row],[QNT]]*AllocationTable9[[#This Row],[AVG.]] -> 31591 | O4: SCAP
A5: VEDL | B5: Stocks | C5: =VLOOKUP(AllocationTable9[[#This Row],[TRADE]],AllocationTable[[TRADE]:[SECTOR]],2,0) -> METALS | D5: 200 | E5: 347 | F5: =VLOOKUP(AllocationTable9[[#This Row],[TRADE]],LatestDump!A:I,4,0) -> 745.15 | G5: =AllocationTable9[[#This Row],[EA]]-AllocationTable9[[#This Row],[AA]] -> -9400 | H5: =(AllocationTable9[[#This Row],[QNT]]*AllocationTable9[[#This Row],[LTP]])-(AllocationTable9[[#This Row],[QNT]]*AllocationTable9[[#This Row],[AVG.]]) -> 79630 | I5: =IFERROR(AllocationTable9[[#This Row],[PROFIT]]/AllocationTable9[[#This Row],[AA]],0) -> 1.1474063 | J5: =AllocationTable9[[#This Row],[QNT]]*AllocationTable9[[#This Row],[LTP]] -> 149030 | K5: =AllocationTable9[[#This Row],[EA]]/AllocationTable9[[#Totals],[EA]] -> 0.046875 | L5: =AllocationTable9[[#This Row],[AA]]/AllocationTable9[[#Totals],[AA]] -> 0.05652708 | M5: 60000 | N5: =AllocationTable9[[#This Row],[QNT]]*AllocationTable9[[#This Row],[AVG.]] -> 69400 | O5: LCAP
A6: ETERNAL | B6: Stocks | C6: =VLOOKUP(AllocationTable9[[#This Row],[TRADE]],AllocationTable[[TRADE]:[SECTOR]],2,0) -> IT | D6: 400 | E6: 136.07 | F6: =VLOOKUP(AllocationTable9[[#This Row],[TRADE]],LatestDump!A:I,4,0) -> 240 | G6: =AllocationTable9[[#This Row],[EA]]-AllocationTable9[[#This Row],[AA]] -> -4428 | H6: =(AllocationTable9[[#This Row],[QNT]]*AllocationTable9[[#This Row],[LTP]])-(AllocationTable9[[#This Row],[QNT]]*AllocationTable9[[#This Row],[AVG.]]) -> 41572 | I6: =IFERROR(AllocationTable9[[#This Row],[PROFIT]]/AllocationTable9[[#This Row],[AA]],0) -> 0.76379805 | J6: =AllocationTable9[[#This Row],[QNT]]*AllocationTable9[[#This Row],[LTP]] -> 96000 | K6: =AllocationTable9[[#This Row],[EA]]/AllocationTable9[[#Totals],[EA]] -> 0.0390625 | L6: =AllocationTable9[[#This Row],[AA]]/AllocationTable9[[#Totals],[AA]] -> 0.044332217 | M6: 50000 | N6: =AllocationTable9[[#This Row],[QNT]]*AllocationTable9[[#This Row],[AVG.]] -> 54428 | O6: LCAP
A7: BSE | B7: Stocks | C7: =VLOOKUP(AllocationTable9[[#This Row],[TRADE]],AllocationTable[[TRADE]:[SECTOR]],2,0) -> FINANCIAL SERVICES | D7: 125 | E7: 1863.78 | F7: =VLOOKUP(AllocationTable9[[#This Row],[TRADE]],LatestDump!A:I,4,0) -> 3281.2 | G7: =AllocationTable9[[#This Row],[EA]]-AllocationTable9[[#This Row],[AA]] -> -32972.5 | H7: =(AllocationTable9[[#This Row],[QNT]]*AllocationTable9[[#This Row],[LTP]])-(AllocationTable9[[#This Row],[QNT]]*AllocationTable9[[#This Row],[AVG.]]) -> 177177.5 | I7: =IFERROR(AllocationTable9[[#This Row],[PROFIT]]/AllocationTable9[[#This Row],[AA]],0) -> 0.76050821 | J7: =AllocationTable9[[#This Row],[QNT]]*AllocationTable9[[#This Row],[LTP]] -> 410150 | K7: =AllocationTable9[[#This Row],[EA]]/AllocationTable9[[#Totals],[EA]] -> 0.15625 | L7: =AllocationTable9[[#This Row],[AA]]/AllocationTable9[[#Totals],[AA]] -> 0.18975872 | M7: 200000 | N7: =AllocationTable9[[#This Row],[QNT]]*AllocationTable9[[#This Row],[AVG.]] -> 232972.5 | O7: LCAP
A8: M&M | B8: Stocks | C8: =VLOOKUP(AllocationTable9[[#This Row],[TRADE]],AllocationTable[[TRADE]:[SECTOR]],2,0) -> AUTO ANCILLARY | D8: 20 | E8: 1945.77 | F8: =VLOOKUP(AllocationTable9[[#This Row],[TRADE]],LatestDump!A:I,4,0) -> 3261.8 | G8: =AllocationTable9[[#This Row],[EA]]-AllocationTable9[[#This Row],[AA]] -> 11084.6 | H8: =(AllocationTable9[[#This Row],[QNT]]*AllocationTable9[[#This Row],[LTP]])-(AllocationTable9[[#This Row],[QNT]]*AllocationTable9[[#This Row],[AVG.]]) -> 26320.6 | I8: =IFERROR(AllocationTable9[[#This Row],[PROFIT]]/AllocationTable9[[#This Row],[AA]],0) -> 0.67635435 | J8: =AllocationTable9[[#This Row],[QNT]]*AllocationTable9[[#This Row],[LTP]] -> 65236 | K8: =AllocationTable9[[#This Row],[EA]]/AllocationTable9[[#Totals],[EA]] -> 0.0390625 | L8: =AllocationTable9[[#This Row],[AA]]/AllocationTable9[[#Totals],[AA]] -> 0.03169703 | M8: 50000 | N8: =AllocationTable9[[#This Row],[QNT]]*AllocationTable9[[#This Row],[AVG.]] -> 38915.4 | O8: LCAP
A9: HBLENGINE | B9: Stocks | C9: =VLOOKUP(AllocationTable9[[#This Row],[TRADE]],AllocationTable[[TRADE]:[SECTOR]],2,0) -> AUTO ANCILLARY | D9: 350 | E9: 455.79 | F9: =VLOOKUP(AllocationTable9[[#This Row],[TRADE]],LatestDump!A:I,4,0) -> 730.65 | G9: =AllocationTable9[[#This Row],[EA]]-AllocationTable9[[#This Row],[AA]] -> -9526.5 | H9: =(AllocationTable9[[#This Row],[QNT]]*AllocationTable9[[#This Row],[LTP]])-(AllocationTable9[[#This Row],[QNT]]*AllocationTable9[[#This Row],[AVG.]]) -> 96201 | I9: =IFERROR(AllocationTable9[[#This Row],[PROFIT]]/AllocationTable9[[#This Row],[AA]],0) -> 0.60304087 | J9: =AllocationTable9[[#This Row],[QNT]]*AllocationTable9[[#This Row],[LTP]] -> 255727.5 | K9: =AllocationTable9[[#This Row],[EA]]/AllocationTable9[[#Totals],[EA]] -> 0.1171875 | L9: =AllocationTable9[[#This Row],[AA]]/AllocationTable9[[#Totals],[AA]] -> 0.12993613 | M9: 150000 | N9: =AllocationTable9[[#This Row],[QNT]]*AllocationTable9[[#This Row],[AVG.]] -> 159526.5 | O9: MCAP
A10: ICICIAMC | B10: Stocks | C10: =VLOOKUP(AllocationTable9[[#This Row],[TRADE]],AllocationTable[[TRADE]:[SECTOR]],2,0) -> FINANCIAL SERVICES | D10: 6 | E10: 2165 | F10: =VLOOKUP(AllocationTable9[[#This Row],[TRADE]],LatestDump!A:I,4,0) -> 3390.2 | G10: =AllocationTable9[[#This Row],[EA]]-AllocationTable9[[#This Row],[AA]] -> 17010 | H10: =(AllocationTable9[[#This Row],[QNT]]*AllocationTable9[[#This Row],[LTP]])-(AllocationTable9[[#This Row],[QNT]]*AllocationTable9[[#This Row],[AVG.]]) -> 7351.2 | I10: =IFERROR(AllocationTable9[[#This Row],[PROFIT]]/AllocationTable9[[#This Row],[AA]],0) -> 0.56591224 | J10: =AllocationTable9[[#This Row],[QNT]]*AllocationTable9[[#This Row],[LTP]] -> 20341.2 | K10: =AllocationTable9[[#This Row],[EA]]/AllocationTable9[[#Totals],[EA]] -> 0.0234375 | L10: =AllocationTable9[[#This Row],[AA]]/AllocationTable9[[#Totals],[AA]] -> 0.010580501 | M10: 30000 | N10: =AllocationTable9[[#This Row],[QNT]]*AllocationTable9[[#This Row],[AVG.]] -> 12990 | O10: LCAP
A11: KPIGREEN | B11: Stocks | C11: =VLOOKUP(AllocationTable9[[#This Row],[TRADE]],AllocationTable[[TRADE]:[SECTOR]],2,0) -> ENGINEERING & CAPITAL GOODS | D11: 250 | E11: 281.8 | F11: =VLOOKUP(AllocationTable9[[#This Row],[TRADE]],LatestDump!A:I,4,0) -> 411.1 | G11: =AllocationTable9[[#This Row],[EA]]-AllocationTable9[[#This Row],[AA]] -> -20450 | H11: =(AllocationTable9[[#This Row],[QNT]]*AllocationTable9[[#This Row],[LTP]])-(AllocationTable9[[#This Row],[QNT]]*AllocationTable9[[#This Row],[AVG.]]) -> 32325 | I11: =IFERROR(AllocationTable9[[#This Row],[PROFIT]]/AllocationTable9[[#This Row],[AA]],0) -> 0.45883605 | J11: =AllocationTable9[[#This Row],[QNT]]*AllocationTable9[[#This Row],[LTP]] -> 102775 | K11: =AllocationTable9[[#This Row],[EA]]/AllocationTable9[[#Totals],[EA]] -> 0.0390625 | L11: =AllocationTable9[[#This Row],[AA]]/AllocationTable9[[#Totals],[AA]] -> 0.057382316 | M11: 50000 | N11: =AllocationTable9[[#This Row],[QNT]]*AllocationTable9[[#This Row],[AVG.]] -> 70450 | O11: MCAP
A12: GOLDBEES | B12: GOLD | C12: =VLOOKUP(AllocationTable9[[#This Row],[TRADE]],AllocationTable[[TRADE]:[SECTOR]],2,0) -> Gold | D12: 1400 | E12: 85.29 | F12: =VLOOKUP(AllocationTable9[[#This Row],[TRADE]],LatestDump!A:I,4,0) -> 123.55 | G12: =AllocationTable9[[#This Row],[EA]]-AllocationTable9[[#This Row],[AA]] -> 30594 | H12: =(AllocationTable9[[#This Row],[QNT]]*AllocationTable9[[#This Row],[LTP]])-(AllocationTable9[[#This Row],[QNT]]*AllocationTable9[[#This Row],[AVG.]]) -> 53564 | I12: =IFERROR(AllocationTable9[[#This Row],[PROFIT]]/AllocationTable9[[#This Row],[AA]],0) -> 0.44858717 | J12: =AllocationTable9[[#This Row],[QNT]]*AllocationTable9[[#This Row],[LTP]] -> 172970 | K12: =AllocationTable9[[#This Row],[EA]]/AllocationTable9[[#Totals],[EA]] -> 0.1171875 | L12: =AllocationTable9[[#This Row],[AA]]/AllocationTable9[[#Totals],[AA]] -> 0.097257528 | M12: 150000 | N12: =AllocationTable9[[#This Row],[QNT]]*AllocationTable9[[#This Row],[AVG.]] -> 119406 | O12: LCAP
A13: NETWEB | B13: Stocks | C13: =VLOOKUP(AllocationTable9[[#This Row],[TRADE]],AllocationTable[[TRADE]:[SECTOR]],2,0) -> SOFTWARE SERVICES | D13: 25 | E13: 2456.64 | F13: =VLOOKUP(AllocationTable9[[#This Row],[TRADE]],LatestDump!A:I,4,0) -> 3346.2 | G13: =AllocationTable9[[#This Row],[EA]]-AllocationTable9[[#This Row],[AA]] -> -11416 | H13: =(AllocationTable9[[#This Row],[QNT]]*AllocationTable9[[#This Row],[LTP]])-(AllocationTable9[[#This Row],[QNT]]*AllocationTable9[[#This Row],[AVG.]]) -> 22239 | I13: =IFERROR(AllocationTable9[[#This Row],[PROFIT]]/AllocationTable9[[#This Row],[AA]],0) -> 0.36210434 | J13: =AllocationTable9[[#This Row],[QNT]]*AllocationTable9[[#This Row],[LTP]] -> 83655 | K13: =AllocationTable9[[#This Row],[EA]]/AllocationTable9[[#Totals],[EA]] -> 0.0390625 | L13: =AllocationTable9[[#This Row],[AA]]/AllocationTable9[[#Totals],[AA]] -> 0.050024022 | M13: 50000 | N13: =AllocationTable9[[#This Row],[QNT]]*AllocationTable9[[#This Row],[AVG.]] -> 61416 | O13: MCAP
... A17: INDHOTEL | B17: Stocks | C17: =VLOOKUP(AllocationTable9[[#This Row],[TRADE]],AllocationTable[[TRADE]:[SECTOR]],2,0) -> TOURISM & HOSPITALITY | D17: 70 | E17: 692.81 | F17: =VLOOKUP(AllocationTable9[[#This Row],[TRADE]],LatestDump!A:I,4,0) -> 641.5 | G17: =AllocationTable9[[#This Row],[EA]]-AllocationTable9[[#This Row],[AA]] -> 1503.3 | H17: =(AllocationTable9[[#This Row],[QNT]]*AllocationTable9[[#This Row],[LTP]])-(AllocationTable9[[#This Row],[QNT]]*AllocationTable9[[#This Row],[AVG.]]) -> -3591.7 | I17: =IFERROR(AllocationTable9[[#This Row],[PROFIT]]/AllocationTable9[[#This Row],[AA]],0) -> -0.074060709 | J17: =AllocationTable9[[#This Row],[QNT]]*AllocationTable9[[#This Row],[LTP]] -> 44905 | K17: =AllocationTable9[[#This Row],[EA]]/AllocationTable9[[#Totals],[EA]] -> 0.0390625 | L17: =AllocationTable9[[#This Row],[AA]]/AllocationTable9[[#Totals],[AA]] -> 0.039501107 | M17: 50000 | N17: =AllocationTable9[[#This Row],[QNT]]*AllocationTable9[[#This Row],[AVG.]] -> 48496.7 | O17: LCAP
D18: =SUBTOTAL(109,AllocationTable9[QNT]) -> 4611 | E18: =SUBTOTAL(101,AllocationTable9[AVG.]) -> 771.36437 | G18: =SUBTOTAL(109,AllocationTable9[Available Quota]) -> 52269.85 | H18: =SUBTOTAL(109,AllocationTable9[PROFIT]) -> 832753.05 | I18: =SUBTOTAL(101,AllocationTable9[PROFIT%]) -> 0.76206634 | J18: =SUBTOTAL(109,AllocationTable9[CURRENT VALUE]) -> 2060483.2 | K18: =SUBTOTAL(109,AllocationTable9[EA%]) -> 1 | L18: =SUBTOTAL(109,AllocationTable9[AA%]) -> 1 | M18: =SUBTOTAL(109,AllocationTable9[EA]) -> 1280000 | N18: =SUBTOTAL(109,AllocationTable9[AA]) -> 1227730.1
A19: GOLDBEES
A20: Physical Gold
A21: SBI Gold Direct Plan Growth
A22: SGB
A23: Aditya Birla Sun Life ELSS Tax Saver Growth
A24: Axis ELSS Tax Saver Direct Plan Growth
A25: JioBlackRock Flexi Cap Fund Direct Growth
A26: Parag Parikh Flexi Cap Fund Direct Growth
A27: Parag Parikh Flexi Cap Fund Direct Growth-Self
A28: Mirae Asset Large & Midcap Fund Direct Growth
A29: HDFC BSE Sensex Index Fund Direct Growth
A30: ICICI Prudential Technology Direct Plan Growth
... A41: NPS

Sheet Asset
A1: TRADE | B1: SECTOR | C1: TYPE | D1: Term | E1: QNT | F1: AVG. | G1: LTP | H1: High | I1: Available Quota | J1: CALL | K1: Last Buy | L1: 1st Target | M1: 2nd Target | N1: 3rd Target | O1: PROFIT | P1: PROFIT% | Q1: CURRENT VALUE | R1: Till 2025 | S1: ESIP | T1: EA% | U1: EA | V1: AA% | W1: AA | X1: SIP% | Y1: Tier | Z1: Stop Loss % | AA1: Initial Stop-Loss % | AB1: Partial Profit % | AC1: Final Target % | AD1: Trailing Stop Rule
A2: EPF/PPF | B2: Fixed Return | C2: EPF/PPF | D2: Fixed | E2: =_xlfn.IFNA(VLOOKUP(AllocationTable[[#This Row],[TRADE]],LatestDump!A:H,2,FALSE),0) + (_xlfn.IFNA(VLOOKUP(AllocationTable[[#This Row],[TRADE]],LongTerm!A:D,4,0),0)) -> 160 | F2: =IFERROR( ( _xlfn.IFNA(VLOOKUP(AllocationTable[[#This Row],[TRADE]],LatestDump!A:H,5,FALSE),0) + _xlfn.IFNA(VLOOKUP(AllocationTable[[#This Row],[TRADE]],AllocationTable9[[TRADE]:[AA]],14,0),0) ) / AllocationTable[[#This Row],[QNT]], 0) -> 12081.25 | G2: =_xlfn.IFNA(ROUND(VLOOKUP(AllocationTable[[#This Row],[TRADE]],LatestDump!A:H,4,FALSE),2),0) -> 15990.89 | I2: =AllocationTable[[#This Row],[EA]]-AllocationTable[[#This Row],[AA]] -> 76200 | J2: =IF(AllocationTable[[#This Row],[Term]]="Trading",IF(AllocationTable[[#This Row],[PROFIT%]]>AllocationTable[[#This Row],[Final Target %]]%,"Book Profit",IF(AllocationTable[[#This Row],[PROFIT%]]>AllocationTable[[#This Row],[Partial Profit %]]%,"Book Partial Profit",IF(AllocationTable[[#This Row],[PROFIT%]]<=AllocationTable[[#This Row],[Stop Loss %]]%,"Book Loss",IF(AllocationTable[[#This Row],[Available Quota]]>AllocationTable[[#This Row],[LTP]],"TOP UP","HOLD")))),IF(AllocationTable[[#This Row],[Available Quota]]>AllocationTable[[#This Row],[LTP]],"TOP UP","HOLD")) -> TOP UP | L2: =IF(AllocationTable[[#This Row],[SIP%]]>0,_xlfn.CEILING.MATH(AllocationTable[[#This Row],[High]]-(AllocationTable[[#This Row],[High]]*AllocationTable[[#This Row],[SIP%]]%))&" ,Qnt: " &(_xlfn.CEILING.MATH((AllocationTable[[#This Row],[Available Quota]]*14%)/AllocationTable[[#This Row],[LTP]])),IF(AllocationTable[[#This Row],[SIP%]]<0,"EXIT","SIP")) -> SIP | M2: =IF(AllocationTable[[#This Row],[SIP%]]>0,_xlfn.CEILING.MATH(AllocationTable[[#This Row],[High]]-(AllocationTable[[#This Row],[High]]*2*AllocationTable[[#This Row],[SIP%]]%))&" ,Qnt: " &(_xlfn.CEILING.MATH((AllocationTable[[#This Row],[Available Quota]]*30%)/AllocationTable[[#This Row],[LTP]])),IF(AllocationTable[[#This Row],[SIP%]]<0,"EXIT","SIP")) -> SIP | N2: =IF(AllocationTable[[#This Row],[SIP%]]>0,_xlfn.CEILING.MATH(AllocationTable[[#This Row],[High]]-(AllocationTable[[#This Row],[High]]*3*AllocationTable[[#This Row],[SIP%]]%))&" ,Qnt: " &(_xlfn.CEILING.MATH((AllocationTable[[#This Row],[Available Quota]]*56%)/AllocationTable[[#This Row],[LTP]])),IF(AllocationTable[[#This Row],[SIP%]]<0,"EXIT","SIP")) -> SIP | O2: =AllocationTable[[#This Row],[CURRENT VALUE]]-AllocationTable[[#This Row],[AA]] -> 625542.4 | P2: =IFERROR(AllocationTable[[#This Row],[PROFIT]]/AllocationTable[[#This Row],[AA]],0) -> 0.32361221 | Q2: =AllocationTable[[#This Row],[QNT]]*AllocationTable[[#This Row],[LTP]] -> 2558542.4 | R2: 1853200 | S2: 26000 | T2: 0 | U2: =IF(AllocationTable[[#This Row],[TYPE]]="Stocks",IF(AllocationTable[[#This Row],[Term]]="Long Term",LongTermQuota*AllocationTable[[#This Row],[EA%]]%,SwingTradeQuota*AllocationTable[[#This Row],[EA%]]%),AllocationTable[[#This Row],[Till 2025]]+(TotalMonth*AllocationTable[[#This Row],[ESIP]])) -> 2009200 | V2: =AllocationTable[[#This Row],[AA]]/AllocationTable[[#Totals],[AA]] -> 0.22376589 | W2: =AllocationTable[[#This Row],[QNT]]*AllocationTable[[#This Row],[AVG.]] -> 1933000 | X2: 0
A3: Physical Gold | B3: Gold | C3: Gold | D3: Gold | E3: =_xlfn.IFNA(VLOOKUP(AllocationTable[[#This Row],[TRADE]],LatestDump!A:H,2,FALSE),0) + (_xlfn.IFNA(VLOOKUP(AllocationTable[[#This Row],[TRADE]],LongTerm!A:D,4,0),0)) -> 5.5 | F3: =IFERROR( ( _xlfn.IFNA(VLOOKUP(AllocationTable[[#This Row],[TRADE]],LatestDump!A:H,5,FALSE),0) + _xlfn.IFNA(VLOOKUP(AllocationTable[[#This Row],[TRADE]],AllocationTable9[[TRADE]:[AA]],14,0),0) ) / AllocationTable[[#This Row],[QNT]], 0) -> 9500 | G3: =_xlfn.IFNA(ROUND(VLOOKUP(AllocationTable[[#This Row],[TRADE]],LatestDump!A:H,4,FALSE),2),0) -> 14010 | H3: 15585 | I3: =AllocationTable[[#This Row],[EA]]-AllocationTable[[#This Row],[AA]] -> 12000 | J3: =IF(AllocationTable[[#This Row],[Term]]="Trading",IF(AllocationTable[[#This Row],[PROFIT%]]>AllocationTable[[#This Row],[Final Target %]]%,"Book Profit",IF(AllocationTable[[#This Row],[PROFIT%]]>AllocationTable[[#This Row],[Partial Profit %]]%,"Book Partial Profit",IF(AllocationTable[[#This Row],[PROFIT%]]<=AllocationTable[[#This Row],[Stop Loss %]]%,"Book Loss",IF(AllocationTable[[#This Row],[Available Quota]]>AllocationTable[[#This Row],[LTP]],"TOP UP","HOLD")))),IF(AllocationTable[[#This Row],[Available Quota]]>AllocationTable[[#This Row],[LTP]],"TOP UP","HOLD")) -> HOLD | L3: =IF(AllocationTable[[#This Row],[SIP%]]>0,_xlfn.CEILING.MATH(AllocationTable[[#This Row],[High]]-(AllocationTable[[#This Row],[High]]*AllocationTable[[#This Row],[SIP%]]%))&" ,Qnt: " &(_xlfn.CEILING.MATH((AllocationTable[[#This Row],[Available Quota]]*14%)/AllocationTable[[#This Row],[LTP]])),IF(AllocationTable[[#This Row],[SIP%]]<0,"EXIT","SIP")) -> SIP | M3: =IF(AllocationTable[[#This Row],[SIP%]]>0,_xlfn.CEILING.MATH(AllocationTable[[#This Row],[High]]-(AllocationTable[[#This Row],[High]]*2*AllocationTable[[#This Row],[SIP%]]%))&" ,Qnt: " &(_xlfn.CEILING.MATH((AllocationTable[[#This Row],[Available Quota]]*30%)/AllocationTable[[#This Row],[LTP]])),IF(AllocationTable[[#This Row],[SIP%]]<0,"EXIT","SIP")) -> SIP | N3: =IF(AllocationTable[[#This Row],[SIP%]]>0,_xlfn.CEILING.MATH(AllocationTable[[#This Row],[High]]-(AllocationTable[[#This Row],[High]]*3*AllocationTable[[#This Row],[SIP%]]%))&" ,Qnt: " &(_xlfn.CEILING.MATH((AllocationTable[[#This Row],[Available Quota]]*56%)/AllocationTable[[#This Row],[LTP]])),IF(AllocationTable[[#This Row],[SIP%]]<0,"EXIT","SIP")) -> SIP | O3: =AllocationTable[[#This Row],[CURRENT VALUE]]-AllocationTable[[#This Row],[AA]] -> 24805 | P3: =IFERROR(AllocationTable[[#This Row],[PROFIT]]/AllocationTable[[#This Row],[AA]],0) -> 0.47473684 | Q3: =AllocationTable[[#This Row],[QNT]]*AllocationTable[[#This Row],[LTP]] -> 77055 | R3: 52250 | S3: 2000 | T3: 0 | U3: =IF(AllocationTable[[#This Row],[TYPE]]="Stocks",IF(AllocationTable[[#This Row],[Term]]="Long Term",LongTermQuota*AllocationTable[[#This Row],[EA%]]%,SwingTradeQuota*AllocationTable[[#This Row],[EA%]]%),AllocationTable[[#This Row],[Till 2025]]+(TotalMonth*AllocationTable[[#This Row],[ESIP]])) -> 64250 | V3: =AllocationTable[[#This Row],[AA]]/AllocationTable[[#Totals],[AA]] -> 0.006048509 | W3: =AllocationTable[[#This Row],[QNT]]*AllocationTable[[#This Row],[AVG.]] -> 52250 | X3: 0
A4: GOLDBEES | B4: Gold | C4: Gold ETF | D4: Gold | E4: =_xlfn.IFNA(VLOOKUP(AllocationTable[[#This Row],[TRADE]],LatestDump!A:H,2,FALSE),0) + (_xlfn.IFNA(VLOOKUP(AllocationTable[[#This Row],[TRADE]],LongTerm!A:D,4,0),0)) -> 1451 | F4: =IFERROR( ( _xlfn.IFNA(VLOOKUP(AllocationTable[[#This Row],[TRADE]],LatestDump!A:H,5,FALSE),0) + _xlfn.IFNA(VLOOKUP(AllocationTable[[#This Row],[TRADE]],AllocationTable9[[TRADE]:[AA]],14,0),0) ) / AllocationTable[[#This Row],[QNT]], 0) -> 86.41878 | G4: =_xlfn.IFNA(ROUND(VLOOKUP(AllocationTable[[#This Row],[TRADE]],LatestDump!A:H,4,FALSE),2),0) -> 123.55 | H4: 139 | I4: =AllocationTable[[#This Row],[EA]]-AllocationTable[[#This Row],[AA]] -> -13069.45 | J4: =IF(AllocationTable[[#This Row],[Term]]="Trading",IF(AllocationTable[[#This Row],[PROFIT%]]>AllocationTable[[#This Row],[Final Target %]]%,"Book Profit",IF(AllocationTable[[#This Row],[PROFIT%]]>AllocationTable[[#This Row],[Partial Profit %]]%,"Book Partial Profit",IF(AllocationTable[[#This Row],[PROFIT%]]<=AllocationTable[[#This Row],[Stop Loss %]]%,"Book Loss",IF(AllocationTable[[#This Row],[Available Quota]]>AllocationTable[[#This Row],[LTP]],"TOP UP","HOLD")))),IF(AllocationTable[[#This Row],[Available Quota]]>AllocationTable[[#This Row],[LTP]],"TOP UP","HOLD")) -> HOLD | L4: =IF(AllocationTable[[#This Row],[SIP%]]>0,_xlfn.CEILING.MATH(AllocationTable[[#This Row],[High]]-(AllocationTable[[#This Row],[High]]*AllocationTable[[#This Row],[SIP%]]%))&" ,Qnt: " &(_xlfn.CEILING.MATH((AllocationTable[[#This Row],[Available Quota]]*14%)/AllocationTable[[#This Row],[LTP]])),IF(AllocationTable[[#This Row],[SIP%]]<0,"EXIT","SIP")) -> 133 ,Qnt: -14 | M4: =IF(AllocationTable[[#This Row],[SIP%]]>0,_xlfn.CEILING.MATH(AllocationTable[[#This Row],[High]]-(AllocationTable[[#This Row],[High]]*2*AllocationTable[[#This Row],[SIP%]]%))&" ,Qnt: " &(_xlfn.CEILING.MATH((AllocationTable[[#This Row],[Available Quota]]*30%)/AllocationTable[[#This Row],[LTP]])),IF(AllocationTable[[#This Row],[SIP%]]<0,"EXIT","SIP")) -> 126 ,Qnt: -31 | N4: =IF(AllocationTable[[#This Row],[SIP%]]>0,_xlfn.CEILING.MATH(AllocationTable[[#This Row],[High]]-(AllocationTable[[#This Row],[High]]*3*AllocationTable[[#This Row],[SIP%]]%))&" ,Qnt: " &(_xlfn.CEILING.MATH((AllocationTable[[#This Row],[Available Quota]]*56%)/AllocationTable[[#This Row],[LTP]])),IF(AllocationTable[[#This Row],[SIP%]]<0,"EXIT","SIP")) -> 119 ,Qnt: -59 | O4: =AllocationTable[[#This Row],[CURRENT VALUE]]-AllocationTable[[#This Row],[AA]] -> 53877.4 | P4: =IFERROR(AllocationTable[[#This Row],[PROFIT]]/AllocationTable[[#This Row],[AA]],0) -> 0.4296661 | Q4: =AllocationTable[[#This Row],[QNT]]*AllocationTable[[#This Row],[LTP]] -> 179271.05 | R4: 88324.2 | S4: 4000 | T4: 0 | U4: =IF(AllocationTable[[#This Row],[TYPE]]="Stocks",IF(AllocationTable[[#This Row],[Term]]="Long Term",LongTermQuota*AllocationTable[[#This Row],[EA%]]%,SwingTradeQuota*AllocationTable[[#This Row],[EA%]]%),AllocationTable[[#This Row],[Till 2025]]+(TotalMonth*AllocationTable[[#This Row],[ESIP]])) -> 112324.2 | V4: =AllocationTable[[#This Row],[AA]]/AllocationTable[[#Totals],[AA]] -> 0.014515686 | W4: =AllocationTable[[#This Row],[QNT]]*AllocationTable[[#This Row],[AVG.]] -> 125393.65 | X4: 5
A5: SBI Gold Direct Plan Growth | B5: Gold | C5: Gold MF | D5: Gold | E5: =_xlfn.IFNA(VLOOKUP(AllocationTable[[#This Row],[TRADE]],LatestDump!A:H,2,FALSE),0) + (_xlfn.IFNA(VLOOKUP(AllocationTable[[#This Row],[TRADE]],LongTerm!A:D,4,0),0)) -> 1578.692 | F5: =IFERROR( ( _xlfn.IFNA(VLOOKUP(AllocationTable[[#This Row],[TRADE]],LatestDump!A:H,5,FALSE),0) + _xlfn.IFNA(VLOOKUP(AllocationTable[[#This Row],[TRADE]],AllocationTable9[[TRADE]:[AA]],14,0),0) ) / AllocationTable[[#This Row],[QNT]], 0) -> 31.036814 | G5: =_xlfn.IFNA(ROUND(VLOOKUP(AllocationTable[[#This Row],[TRADE]],LatestDump!A:H,4,FALSE),2),0) -> 45.62 | H5: 52 | I5: =AllocationTable[[#This Row],[EA]]-AllocationTable[[#This Row],[AA]] -> 8002.43 | J5: =IF(AllocationTable[[#This Row],[Term]]="Trading",IF(AllocationTable[[#This Row],[PROFIT%]]>AllocationTable[[#This Row],[Final Target %]]%,"Book Profit",IF(AllocationTable[[#This Row],[PROFIT%]]>AllocationTable[[#This Row],[Partial Profit %]]%,"Book Partial Profit",IF(AllocationTable[[#This Row],[PROFIT%]]<=AllocationTable[[#This Row],[Stop Loss %]]%,"Book Loss",IF(AllocationTable[[#This Row],[Available Quota]]>AllocationTable[[#This Row],[LTP]],"TOP UP","HOLD")))),IF(AllocationTable[[#This Row],[Available Quota]]>AllocationTable[[#This Row],[LTP]],"TOP UP","HOLD")) -> TOP UP | L5: =IF(AllocationTable[[#This Row],[SIP%]]>0,_xlfn.CEILING.MATH(AllocationTable[[#This Row],[High]]-(AllocationTable[[#This Row],[High]]*AllocationTable[[#This Row],[SIP%]]%))&" ,Qnt: " &(_xlfn.CEILING.MATH((AllocationTable[[#This Row],[Available Quota]]*14%)/AllocationTable[[#This Row],[LTP]])),IF(AllocationTable[[#This Row],[SIP%]]<0,"EXIT","SIP")) -> 50 ,Qnt: 25 | M5: =IF(AllocationTable[[#This Row],[SIP%]]>0,_xlfn.CEILING.MATH(AllocationTable[[#This Row],[High]]-(AllocationTable[[#This Row],[High]]*2*AllocationTable[[#This Row],[SIP%]]%))&" ,Qnt: " &(_xlfn.CEILING.MATH((AllocationTable[[#This Row],[Available Quota]]*30%)/AllocationTable[[#This Row],[LTP]])),IF(AllocationTable[[#This Row],[SIP%]]<0,"EXIT","SIP")) -> 47 ,Qnt: 53 | N5: =IF(AllocationTable[[#This Row],[SIP%]]>0,_xlfn.CEILING.MATH(AllocationTable[[#This Row],[High]]-(AllocationTable[[#This Row],[High]]*3*AllocationTable[[#This Row],[SIP%]]%))&" ,Qnt: " &(_xlfn.CEILING.MATH((AllocationTable[[#This Row],[Available Quota]]*56%)/AllocationTable[[#This Row],[LTP]])),IF(AllocationTable[[#This Row],[SIP%]]<0,"EXIT","SIP")) -> 45 ,Qnt: 99 | O5: =AllocationTable[[#This Row],[CURRENT VALUE]]-AllocationTable[[#This Row],[AA]] -> 23022.359 | P5: =IFERROR(AllocationTable[[#This Row],[PROFIT]]/AllocationTable[[#This Row],[AA]],0) -> 0.46986736 | Q5: =AllocationTable[[#This Row],[QNT]]*AllocationTable[[#This Row],[LTP]] -> 72019.929 | R5: 33000 | S5: 4000 | T5: 10 | U5: =IF(AllocationTable[[#This Row],[TYPE]]="Stocks",IF(AllocationTable[[#This Row],[Term]]="Long Term",LongTermQuota*AllocationTable[[#This Row],[EA%]]%,SwingTradeQuota*AllocationTable[[#This Row],[EA%]]%),AllocationTable[[#This Row],[Till 2025]]+(TotalMonth*AllocationTable[[#This Row],[ESIP]])) -> 57000 | V5: =AllocationTable[[#This Row],[AA]]/AllocationTable[[#Totals],[AA]] -> 0.0056720046 | W5: =AllocationTable[[#This Row],[QNT]]*AllocationTable[[#This Row],[AVG.]] -> 48997.57 | X5: 5
A6: Land | B6: Land | C6: Land | D6: Land | E6: =_xlfn.IFNA(VLOOKUP(AllocationTable[[#This Row],[TRADE]],LatestDump!A:H,2,FALSE),0) + (_xlfn.IFNA(VLOOKUP(AllocationTable[[#This Row],[TRADE]],LongTerm!A:D,4,0),0)) -> 1500 | F6: =IFERROR( ( _xlfn.IFNA(VLOOKUP(AllocationTable[[#This Row],[TRADE]],LatestDump!A:H,5,FALSE),0) + _xlfn.IFNA(VLOOKUP(AllocationTable[[#This Row],[TRADE]],AllocationTable9[[TRADE]:[AA]],14,0),0) ) / AllocationTable[[#This Row],[QNT]], 0) -> 466 | G6: =_xlfn.IFNA(ROUND(VLOOKUP(AllocationTable[[#This Row],[TRADE]],LatestDump!A:H,4,FALSE),2),0) -> 1100 | H6: 1100 | I6: =AllocationTable[[#This Row],[EA]]-AllocationTable[[#This Row],[AA]] -> 0 | J6: =IF(AllocationTable[[#This Row],[Term]]="Trading",IF(AllocationTable[[#This Row],[PROFIT%]]>AllocationTable[[#This Row],[Final Target %]]%,"Book Profit",IF(AllocationTable[[#This Row],[PROFIT%]]>AllocationTable[[#This Row],[Partial Profit %]]%,"Book Partial Profit",IF(AllocationTable[[#This Row],[PROFIT%]]<=AllocationTable[[#This Row],[Stop Loss %]]%,"Book Loss",IF(AllocationTable[[#This Row],[Available Quota]]>AllocationTable[[#This Row],[LTP]],"TOP UP","HOLD")))),IF(AllocationTable[[#This Row],[Available Quota]]>AllocationTable[[#This Row],[LTP]],"TOP UP","HOLD")) -> HOLD | L6: =IF(AllocationTable[[#This Row],[SIP%]]>0,_xlfn.CEILING.MATH(AllocationTable[[#This Row],[High]]-(AllocationTable[[#This Row],[High]]*AllocationTable[[#This Row],[SIP%]]%))&" ,Qnt: " &(_xlfn.CEILING.MATH((AllocationTable[[#This Row],[Available Quota]]*14%)/AllocationTable[[#This Row],[LTP]])),IF(AllocationTable[[#This Row],[SIP%]]<0,"EXIT","SIP")) -> SIP | M6: =IF(AllocationTable[[#This Row],[SIP%]]>0,_xlfn.CEILING.MATH(AllocationTable[[#This Row],[High]]-(AllocationTable[[#This Row],[High]]*2*AllocationTable[[#This Row],[SIP%]]%))&" ,Qnt: " &(_xlfn.CEILING.MATH((AllocationTable[[#This Row],[Available Quota]]*30%)/AllocationTable[[#This Row],[LTP]])),IF(AllocationTable[[#This Row],[SIP%]]<0,"EXIT","SIP")) -> SIP | N6: =IF(AllocationTable[[#This Row],[SIP%]]>0,_xlfn.CEILING.MATH(AllocationTable[[#This Row],[High]]-(AllocationTable[[#This Row],[High]]*3*AllocationTable[[#This Row],[SIP%]]%))&" ,Qnt: " &(_xlfn.CEILING.MATH((AllocationTable[[#This Row],[Available Quota]]*56%)/AllocationTable[[#This Row],[LTP]])),IF(AllocationTable[[#This Row],[SIP%]]<0,"EXIT","SIP")) -> SIP | O6: =AllocationTable[[#This Row],[CURRENT VALUE]]-AllocationTable[[#This Row],[AA]] -> 951000 | P6: =IFERROR(AllocationTable[[#This Row],[PROFIT]]/AllocationTable[[#This Row],[AA]],0) -> 1.360515 | Q6: =AllocationTable[[#This Row],[QNT]]*AllocationTable[[#This Row],[LTP]] -> 1650000 | R6: 699000 | S6: 0 | T6: 0 | U6: =IF(AllocationTable[[#This Row],[TYPE]]="Stocks",IF(AllocationTable[[#This Row],[Term]]="Long Term",LongTermQuota*AllocationTable[[#This Row],[EA%]]%,SwingTradeQuota*AllocationTable[[#This Row],[EA%]]%),AllocationTable[[#This Row],[Till 2025]]+(TotalMonth*AllocationTable[[#This Row],[ESIP]])) -> 699000 | V6: =AllocationTable[[#This Row],[AA]]/AllocationTable[[#Totals],[AA]] -> 0.080916895 | W6: =AllocationTable[[#This Row],[QNT]]*AllocationTable[[#This Row],[AVG.]] -> 699000 | X6: 0
A7: Motilal Oswal Nifty India Defence Index Fund Direct Growth | B7: MF-Defence Fund | C7: Mutual Fund | D7: MF | E7: =_xlfn.IFNA(VLOOKUP(AllocationTable[[#This Row],[TRADE]],LatestDump!A:H,2,FALSE),0) + (_xlfn.IFNA(VLOOKUP(AllocationTable[[#This Row],[TRADE]],LongTerm!A:D,4,0),0)) -> 9197.764 | F7: =IFERROR( ( _xlfn.IFNA(VLOOKUP(AllocationTable[[#This Row],[TRADE]],LatestDump!A:H,5,FALSE),0) + _xlfn.IFNA(VLOOKUP(AllocationTable[[#This Row],[TRADE]],AllocationTable9[[TRADE]:[AA]],14,0),0) ) / AllocationTable[[#This Row],[QNT]], 0) -> 10.273831 | G7: =_xlfn.IFNA(ROUND(VLOOKUP(AllocationTable[[#This Row],[TRADE]],LatestDump!A:H,4,FALSE),2),0) -> 10.89 | H7: 11 | I7: =AllocationTable[[#This Row],[EA]]-AllocationTable[[#This Row],[AA]] -> -40997.04 | J7: =IF(AllocationTable[[#This Row],[Term]]="Trading",IF(AllocationTable[[#This Row],[PROFIT%]]>AllocationTable[[#This Row],[Final Target %]]%,"Book Profit",IF(AllocationTable[[#This Row],[PROFIT%]]>AllocationTable[[#This Row],[Partial Profit %]]%,"Book Partial Profit",IF(AllocationTable[[#This Row],[PROFIT%]]<=AllocationTable[[#This Row],[Stop Loss %]]%,"Book Loss",IF(AllocationTable[[#This Row],[Available Quota]]>AllocationTable[[#This Row],[LTP]],"TOP UP","HOLD")))),IF(AllocationTable[[#This Row],[Available Quota]]>AllocationTable[[#This Row],[LTP]],"TOP UP","HOLD")) -> HOLD | L7: =IF(AllocationTable[[#This Row],[SIP%]]>0,_xlfn.CEILING.MATH(AllocationTable[[#This Row],[High]]-(AllocationTable[[#This Row],[High]]*AllocationTable[[#This Row],[SIP%]]%))&" ,Qnt: " &(_xlfn.CEILING.MATH((AllocationTable[[#This Row],[Available Quota]]*14%)/AllocationTable[[#This Row],[LTP]])),IF(AllocationTable[[#This Row],[SIP%]]<0,"EXIT","SIP")) -> 11 ,Qnt: -527 | M7: =IF(AllocationTable[[#This Row],[SIP%]]>0,_xlfn.CEILING.MATH(AllocationTable[[#This Row],[High]]-(AllocationTable[[#This Row],[High]]*2*AllocationTable[[#This Row],[SIP%]]%))&" ,Qnt: " &(_xlfn.CEILING.MATH((AllocationTable[[#This Row],[Available Quota]]*30%)/AllocationTable[[#This Row],[LTP]])),IF(AllocationTable[[#This Row],[SIP%]]<0,"EXIT","SIP")) -> 10 ,Qnt: -1129 | N7: =IF(AllocationTable[[#This Row],[SIP%]]>0,_xlfn.CEILING.MATH(AllocationTable[[#This Row],[High]]-(AllocationTable[[#This Row],[High]]*3*AllocationTable[[#This Row],[SIP%]]%))&" ,Qnt: " &(_xlfn.CEILING.MATH((AllocationTable[[#This Row],[Available Quota]]*56%)/AllocationTable[[#This Row],[LTP]])),IF(AllocationTable[[#This Row],[SIP%]]<0,"EXIT","SIP")) -> 10 ,Qnt: -2108 | O7: =AllocationTable[[#This Row],[CURRENT VALUE]]-AllocationTable[[#This Row],[AA]] -> 5667.38 | P7: =IFERROR(AllocationTable[[#This Row],[PROFIT]]/AllocationTable[[#This Row],[AA]],0) -> 0.059974642 | Q7: =AllocationTable[[#This Row],[QNT]]*AllocationTable[[#This Row],[LTP]] -> 100163.65 | R7: 35499.23 | S7: 3000 | T7: 0 | U7: =IF(AllocationTable[[#This Row],[TYPE]]="Stocks",IF(AllocationTable[[#This Row],[Term]]="Long Term",LongTermQuota*AllocationTable[[#This Row],[EA%]]%,SwingTradeQuota*AllocationTable[[#This Row],[EA%]]%),AllocationTable[[#This Row],[Till 2025]]+(TotalMonth*AllocationTable[[#This Row],[ESIP]])) -> 53499.23 | V7: =AllocationTable[[#This Row],[AA]]/AllocationTable[[#Totals],[AA]] -> 0.010938977 | W7: =AllocationTable[[#This Row],[QNT]]*AllocationTable[[#This Row],[AVG.]] -> 94496.27 | X7: 5
A8: Aditya Birla Sun Life ELSS Tax Saver Growth | B8: MF-ELSS | C8: Mutual Fund | D8: MF | E8: =_xlfn.IFNA(VLOOKUP(AllocationTable[[#This Row],[TRADE]],LatestDump!A:H,2,FALSE),0) + (_xlfn.IFNA(VLOOKUP(AllocationTable[[#This Row],[TRADE]],LongTerm!A:D,4,0),0)) -> 62.585 | F8: =IFERROR( ( _xlfn.IFNA(VLOOKUP(AllocationTable[[#This Row],[TRADE]],LatestDump!A:H,5,FALSE),0) + _xlfn.IFNA(VLOOKUP(AllocationTable[[#This Row],[TRADE]],AllocationTable9[[TRADE]:[AA]],14,0),0) ) / AllocationTable[[#This Row],[QNT]], 0) -> 39.087002 | G8: =_xlfn.IFNA(ROUND(VLOOKUP(AllocationTable[[#This Row],[TRADE]],LatestDump!A:H,4,FALSE),2),0) -> 59.16 | H8: 64 | I8: =AllocationTable[[#This Row],[EA]]-AllocationTable[[#This Row],[AA]] -> 0 | J8: =IF(AllocationTable[[#This Row],[Term]]="Trading",IF(AllocationTable[[#This Row],[PROFIT%]]>AllocationTable[[#This Row],[Final Target %]]%,"Book Profit",IF(AllocationTable[[#This Row],[PROFIT%]]>AllocationTable[[#This Row],[Partial Profit %]]%,"Book Partial Profit",IF(AllocationTable[[#This Row],[PROFIT%]]<=AllocationTable[[#This Row],[Stop Loss %]]%,"Book Loss",IF(AllocationTable[[#This Row],[Available Quota]]>AllocationTable[[#This Row],[LTP]],"TOP UP","HOLD")))),IF(AllocationTable[[#This Row],[Available Quota]]>AllocationTable[[#This Row],[LTP]],"TOP UP","HOLD")) -> HOLD | L8: =IF(AllocationTable[[#This Row],[SIP%]]>0,_xlfn.CEILING.MATH(AllocationTable[[#This Row],[High]]-(AllocationTable[[#This Row],[High]]*AllocationTable[[#This Row],[SIP%]]%))&" ,Qnt: " &(_xlfn.CEILING.MATH((AllocationTable[[#This Row],[Available Quota]]*14%)/AllocationTable[[#This Row],[LTP]])),IF(AllocationTable[[#This Row],[SIP%]]<0,"EXIT","SIP")) -> EXIT | M8: =IF(AllocationTable[[#This Row],[SIP%]]>0,_xlfn.CEILING.MATH(AllocationTable[[#This Row],[High]]-(AllocationTable[[#This Row],[High]]*2*AllocationTable[[#This Row],[SIP%]]%))&" ,Qnt: " &(_xlfn.CEILING.MATH((AllocationTable[[#This Row],[Available Quota]]*30%)/AllocationTable[[#This Row],[LTP]])),IF(AllocationTable[[#This Row],[SIP%]]<0,"EXIT","SIP")) -> EXIT | N8: =IF(AllocationTable[[#This Row],[SIP%]]>0,_xlfn.CEILING.MATH(AllocationTable[[#This Row],[High]]-(AllocationTable[[#This Row],[High]]*3*AllocationTable[[#This Row],[SIP%]]%))&" ,Qnt: " &(_xlfn.CEILING.MATH((AllocationTable[[#This Row],[Available Quota]]*56%)/AllocationTable[[#This Row],[LTP]])),IF(AllocationTable[[#This Row],[SIP%]]<0,"EXIT","SIP")) -> EXIT | O8: =AllocationTable[[#This Row],[CURRENT VALUE]]-AllocationTable[[#This Row],[AA]] -> 1256.2686 | P8: =IFERROR(AllocationTable[[#This Row],[PROFIT]]/AllocationTable[[#This Row],[AA]],0) -> 0.51354664 | Q8: =AllocationTable[[#This Row],[QNT]]*AllocationTable[[#This Row],[LTP]] -> 3702.5286 | R8: 2446.26 | S8: 0 | T8: 0 | U8: =IF(AllocationTable[[#This Row],[TYPE]]="Stocks",IF(AllocationTable[[#This Row],[Term]]="Long Term",LongTermQuota*AllocationTable[[#This Row],[EA%]]%,SwingTradeQuota*AllocationTable[[#This Row],[EA%]]%),AllocationTable[[#This Row],[Till 2025]]+(TotalMonth*AllocationTable[[#This Row],[ESIP]])) -> 2446.26 | V8: =AllocationTable[[#This Row],[AA]]/AllocationTable[[#Totals],[AA]] -> 0.00028318135 | W8: =AllocationTable[[#This Row],[QNT]]*AllocationTable[[#This Row],[AVG.]] -> 2446.26 | X8: -1
A9: Axis ELSS Tax Saver Direct Plan Growth | B9: MF-ELSS | C9: Mutual Fund | D9: MF | E9: =_xlfn.IFNA(VLOOKUP(AllocationTable[[#This Row],[TRADE]],LatestDump!A:H,2,FALSE),0) + (_xlfn.IFNA(VLOOKUP(AllocationTable[[#This Row],[TRADE]],LongTerm!A:D,4,0),0)) -> 303.371 | F9: =IFERROR( ( _xlfn.IFNA(VLOOKUP(AllocationTable[[#This Row],[TRADE]],LatestDump!A:H,5,FALSE),0) + _xlfn.IFNA(VLOOKUP(AllocationTable[[#This Row],[TRADE]],AllocationTable9[[TRADE]:[AA]],14,0),0) ) / AllocationTable[[#This Row],[QNT]], 0) -> 75.070557 | G9: =_xlfn.IFNA(ROUND(VLOOKUP(AllocationTable[[#This Row],[TRADE]],LatestDump!A:H,4,FALSE),2),0) -> 104.13 | H9: 112 | I9: =AllocationTable[[#This Row],[EA]]-AllocationTable[[#This Row],[AA]] -> 2060.57 | J9: =IF(AllocationTable[[#This Row],[Term]]="Trading",IF(AllocationTable[[#This Row],[PROFIT%]]>AllocationTable[[#This Row],[Final Target %]]%,"Book Profit",IF(AllocationTable[[#This Row],[PROFIT%]]>AllocationTable[[#This Row],[Partial Profit %]]%,"Book Partial Profit",IF(AllocationTable[[#This Row],[PROFIT%]]<=AllocationTable[[#This Row],[Stop Loss %]]%,"Book Loss",IF(AllocationTable[[#This Row],[Available Quota]]>AllocationTable[[#This Row],[LTP]],"TOP UP","HOLD")))),IF(AllocationTable[[#This Row],[Available Quota]]>AllocationTable[[#This Row],[LTP]],"TOP UP","HOLD")) -> TOP UP | L9: =IF(AllocationTable[[#This Row],[SIP%]]>0,_xlfn.CEILING.MATH(AllocationTable[[#This Row],[High]]-(AllocationTable[[#This Row],[High]]*AllocationTable[[#This Row],[SIP%]]%))&" ,Qnt: " &(_xlfn.CEILING.MATH((AllocationTable[[#This Row],[Available Quota]]*14%)/AllocationTable[[#This Row],[LTP]])),IF(AllocationTable[[#This Row],[SIP%]]<0,"EXIT","SIP")) -> EXIT | M9: =IF(AllocationTable[[#This Row],[SIP%]]>0,_xlfn.CEILING.MATH(AllocationTable[[#This Row],[High]]-(AllocationTable[[#This Row],[High]]*2*AllocationTable[[#This Row],[SIP%]]%))&" ,Qnt: " &(_xlfn.CEILING.MATH((AllocationTable[[#This Row],[Available Quota]]*30%)/AllocationTable[[#This Row],[LTP]])),IF(AllocationTable[[#This Row],[SIP%]]<0,"EXIT","SIP")) -> EXIT | N9: =IF(AllocationTable[[#This Row],[SIP%]]>0,_xlfn.CEILING.MATH(AllocationTable[[#This Row],[High]]-(AllocationTable[[#This Row],[High]]*3*AllocationTable[[#This Row],[SIP%]]%))&" ,Qnt: " &(_xlfn.CEILING.MATH((AllocationTable[[#This Row],[Available Quota]]*56%)/AllocationTable[[#This Row],[LTP]])),IF(AllocationTable[[#This Row],[SIP%]]<0,"EXIT","SIP")) -> EXIT | O9: =AllocationTable[[#This Row],[CURRENT VALUE]]-AllocationTable[[#This Row],[AA]] -> 8815.7922 | P9: =IFERROR(AllocationTable[[#This Row],[PROFIT]]/AllocationTable[[#This Row],[AA]],0) -> 0.38709507 | Q9: =AllocationTable[[#This Row],[QNT]]*AllocationTable[[#This Row],[LTP]] -> 31590.022 | R9: 24834.8 | S9: 0 | T9: 0 | U9: =IF(AllocationTable[[#This Row],[TYPE]]="Stocks",IF(AllocationTable[[#This Row],[Term]]="Long Term",LongTermQuota*AllocationTable[[#This Row],[EA%]]%,SwingTradeQuota*AllocationTable[[#This Row],[EA%]]%),AllocationTable[[#This Row],[Till 2025]]+(TotalMonth*AllocationTable[[#This Row],[ESIP]])) -> 24834.8 | V9: =AllocationTable[[#This Row],[AA]]/AllocationTable[[#Totals],[AA]] -> 0.0026363662 | W9: =AllocationTable[[#This Row],[QNT]]*AllocationTable[[#This Row],[AVG.]] -> 22774.23 | X9: -1
A10: JioBlackRock Flexi Cap Fund Direct Growth | B10: MF-Flexi Cap | C10: Mutual Fund | D10: MF | E10: =_xlfn.IFNA(VLOOKUP(AllocationTable[[#This Row],[TRADE]],LatestDump!A:H,2,FALSE),0) + (_xlfn.IFNA(VLOOKUP(AllocationTable[[#This Row],[TRADE]],LongTerm!A:D,4,0),0)) -> 2326.546 | F10: =IFERROR( ( _xlfn.IFNA(VLOOKUP(AllocationTable[[#This Row],[TRADE]],LatestDump!A:H,5,FALSE),0) + _xlfn.IFNA(VLOOKUP(AllocationTable[[#This Row],[TRADE]],AllocationTable9[[TRADE]:[AA]],14,0),0) ) / AllocationTable[[#This Row],[QNT]], 0) -> 9.9209257 | G10: =_xlfn.IFNA(ROUND(VLOOKUP(AllocationTable[[#This Row],[TRADE]],LatestDump!A:H,4,FALSE),2),0) -> 9.66 | H10: 11 | I10: =AllocationTable[[#This Row],[EA]]-AllocationTable[[#This Row],[AA]] -> 7000.54 | J10: =IF(AllocationTable[[#This Row],[Term]]="Trading",IF(AllocationTable[[#This Row],[PROFIT%]]>AllocationTable[[#This Row],[Final Target %]]%,"Book Profit",IF(AllocationTable[[#This Row],[PROFIT%]]>AllocationTable[[#This Row],[Partial Profit %]]%,"Book Partial Profit",IF(AllocationTable[[#This Row],[PROFIT%]]<=AllocationTable[[#This Row],[Stop Loss %]]%,"Book Loss",IF(AllocationTable[[#This Row],[Available Quota]]>AllocationTable[[#This Row],[LTP]],"TOP UP","HOLD")))),IF(AllocationTable[[#This Row],[Available Quota]]>AllocationTable[[#This Row],[LTP]],"TOP UP","HOLD")) -> TOP UP | L10: =IF(AllocationTable[[#This Row],[SIP%]]>0,_xlfn.CEILING.MATH(AllocationTable[[#This Row],[High]]-(AllocationTable[[#This Row],[High]]*AllocationTable[[#This Row],[SIP%]]%))&" ,Qnt: " &(_xlfn.CEILING.MATH((AllocationTable[[#This Row],[Available Quota]]*14%)/AllocationTable[[#This Row],[LTP]])),IF(AllocationTable[[#This Row],[SIP%]]<0,"EXIT","SIP")) -> 11 ,Qnt: 102 | M10: =IF(AllocationTable[[#This Row],[SIP%]]>0,_xlfn.CEILING.MATH(AllocationTable[[#This Row],[High]]-(AllocationTable[[#This Row],[High]]*2*AllocationTable[[#This Row],[SIP%]]%))&" ,Qnt: " &(_xlfn.CEILING.MATH((AllocationTable[[#This Row],[Available Quota]]*30%)/AllocationTable[[#This Row],[LTP]])),IF(AllocationTable[[#This Row],[SIP%]]<0,"EXIT","SIP")) -> 10 ,Qnt: 218 | N10: =IF(AllocationTable[[#This Row],[SIP%]]>0,_xlfn.CEILING.MATH(AllocationTable[[#This Row],[High]]-(AllocationTable[[#This Row],[High]]*3*AllocationTable[[#This Row],[SIP%]]%))&" ,Qnt: " &(_xlfn.CEILING.MATH((AllocationTable[[#This Row],[Available Quota]]*56%)/AllocationTable[[#This Row],[LTP]])),IF(AllocationTable[[#This Row],[SIP%]]<0,"EXIT","SIP")) -> 10 ,Qnt: 406 | O10: =AllocationTable[[#This Row],[CURRENT VALUE]]-AllocationTable[[#This Row],[AA]] -> -607.05564 | P10: =IFERROR(AllocationTable[[#This Row],[PROFIT]]/AllocationTable[[#This Row],[AA]],0) -> -0.02630054 | Q10: =AllocationTable[[#This Row],[QNT]]*AllocationTable[[#This Row],[LTP]] -> 22474.434 | R10: 12082.03 | S10: 3000 | T10: 0 | U10: =IF(AllocationTable[[#This Row],[TYPE]]="Stocks",IF(AllocationTable[[#This Row],[Term]]="Long Term",LongTermQuota*AllocationTable[[#This Row],[EA%]]%,SwingTradeQuota*AllocationTable[[#This Row],[EA%]]%),AllocationTable[[#This Row],[Till 2025]]+(TotalMonth*AllocationTable[[#This Row],[ESIP]])) -> 30082.03 | V10: =AllocationTable[[#This Row],[AA]]/AllocationTable[[#Totals],[AA]] -> 0.0026719349 | W10: =AllocationTable[[#This Row],[QNT]]*AllocationTable[[#This Row],[AVG.]] -> 23081.49 | X10: 5
A11: Parag Parikh Flexi Cap Fund Direct Growth | B11: MF-Flexi Cap | C11: Mutual Fund | D11: MF | E11: =_xlfn.IFNA(VLOOKUP(AllocationTable[[#This Row],[TRADE]],LatestDump!A:H,2,FALSE),0) + (_xlfn.IFNA(VLOOKUP(AllocationTable[[#This Row],[TRADE]],LongTerm!A:D,4,0),0)) -> 1709.336 | F11: =IFERROR( ( _xlfn.IFNA(VLOOKUP(AllocationTable[[#This Row],[TRADE]],LatestDump!A:H,5,FALSE),0) + _xlfn.IFNA(VLOOKUP(AllocationTable[[#This Row],[TRADE]],AllocationTable9[[TRADE]:[AA]],14,0),0) ) / AllocationTable[[#This Row],[QNT]], 0) -> 66.351203 | G11: =_xlfn.IFNA(ROUND(VLOOKUP(AllocationTable[[#This Row],[TRADE]],LatestDump!A:H,4,FALSE),2),0) -> 90.44 | H11: 96 | I11: =AllocationTable[[#This Row],[EA]]-AllocationTable[[#This Row],[AA]] -> 20501.14 | J11: =IF(AllocationTable[[#This Row],[Term]]="Trading",IF(AllocationTable[[#This Row],[PROFIT%]]>AllocationTable[[#This Row],[Final Target %]]%,"Book Profit",IF(AllocationTable[[#This Row],[PROFIT%]]>AllocationTable[[#This Row],[Partial Profit %]]%,"Book Partial Profit",IF(AllocationTable[[#This Row],[PROFIT%]]<=AllocationTable[[#This Row],[Stop Loss %]]%,"Book Loss",IF(AllocationTable[[#This Row],[Available Quota]]>AllocationTable[[#This Row],[LTP]],"TOP UP","HOLD")))),IF(AllocationTable[[#This Row],[Available Quota]]>AllocationTable[[#This Row],[LTP]],"TOP UP","HOLD")) -> TOP UP | L11: =IF(AllocationTable[[#This Row],[SIP%]]>0,_xlfn.CEILING.MATH(AllocationTable[[#This Row],[High]]-(AllocationTable[[#This Row],[High]]*AllocationTable[[#This Row],[SIP%]]%))&" ,Qnt: " &(_xlfn.CEILING.MATH((AllocationTable[[#This Row],[Available Quota]]*14%)/AllocationTable[[#This Row],[LTP]])),IF(AllocationTable[[#This Row],[SIP%]]<0,"EXIT","SIP")) -> 92 ,Qnt: 32 | M11: =IF(AllocationTable[[#This Row],[SIP%]]>0,_xlfn.CEILING.MATH(AllocationTable[[#This Row],[High]]-(AllocationTable[[#This Row],[High]]*2*AllocationTable[[#This Row],[SIP%]]%))&" ,Qnt: " &(_xlfn.CEILING.MATH((AllocationTable[[#This Row],[Available Quota]]*30%)/AllocationTable[[#This Row],[LTP]])),IF(AllocationTable[[#This Row],[SIP%]]<0,"EXIT","SIP")) -> 87 ,Qnt: 69 | N11: =IF(AllocationTable[[#This Row],[SIP%]]>0,_xlfn.CEILING.MATH(AllocationTable[[#This Row],[High]]-(AllocationTable[[#This Row],[High]]*3*AllocationTable[[#This Row],[SIP%]]%))&" ,Qnt: " &(_xlfn.CEILING.MATH((AllocationTable[[#This Row],[Available Quota]]*56%)/AllocationTable[[#This Row],[LTP]])),IF(AllocationTable[[#This Row],[SIP%]]<0,"EXIT","SIP")) -> 82 ,Qnt: 127 | O11: =AllocationTable[[#This Row],[CURRENT VALUE]]-AllocationTable[[#This Row],[AA]] -> 41175.848 | P11: =IFERROR(AllocationTable[[#This Row],[PROFIT]]/AllocationTable[[#This Row],[AA]],0) -> 0.36304989 | Q11: =AllocationTable[[#This Row],[QNT]]*AllocationTable[[#This Row],[LTP]] -> 154592.35 | R11: 88917.64 | S11: 7500 | T11: 0 | U11: =IF(AllocationTable[[#This Row],[TYPE]]="Stocks",IF(AllocationTable[[#This Row],[Term]]="Long Term",LongTermQuota*AllocationTable[[#This Row],[EA%]]%,SwingTradeQuota*AllocationTable[[#This Row],[EA%]]%),AllocationTable[[#This Row],[Till 2025]]+(TotalMonth*AllocationTable[[#This Row],[ESIP]])) -> 133917.64 | V11: =AllocationTable[[#This Row],[AA]]/AllocationTable[[#Totals],[AA]] -> 0.0131292 | W11: =AllocationTable[[#This Row],[QNT]]*AllocationTable[[#This Row],[AVG.]] -> 113416.5 | X11: 5
A12: Parag Parikh Flexi Cap Fund Direct Growth-Self | B12: MF-Flexi Cap | C12: Mutual Fund | D12: MF | E12: =_xlfn.IFNA(VLOOKUP(AllocationTable[[#This Row],[TRADE]],LatestDump!A:H,2,FALSE),0) + (_xlfn.IFNA(VLOOKUP(AllocationTable[[#This Row],[TRADE]],LongTerm!A:D,4,0),0)) -> 278 | F12: =IFERROR( ( _xlfn.IFNA(VLOOKUP(AllocationTable[[#This Row],[TRADE]],LatestDump!A:H,5,FALSE),0) + _xlfn.IFNA(VLOOKUP(AllocationTable[[#This Row],[TRADE]],AllocationTable9[[TRADE]:[AA]],14,0),0) ) / AllocationTable[[#This Row],[QNT]], 0) -> 35.971223 | G12: =_xlfn.IFNA(ROUND(VLOOKUP(AllocationTable[[#This Row],[TRADE]],LatestDump!A:H,4,FALSE),2),0) -> 90.44 | H12: 96 | I12: =AllocationTable[[#This Row],[EA]]-AllocationTable[[#This Row],[AA]] -> 0 | J12: =IF(AllocationTable[[#This Row],[Term]]="Trading",IF(AllocationTable[[#This Row],[PROFIT%]]>AllocationTable[[#This Row],[Final Target %]]%,"Book Profit",IF(AllocationTable[[#This Row],[PROFIT%]]>AllocationTable[[#This Row],[Partial Profit %]]%,"Book Partial Profit",IF(AllocationTable[[#This Row],[PROFIT%]]<=AllocationTable[[#This Row],[Stop Loss %]]%,"Book Loss",IF(AllocationTable[[#This Row],[Available Quota]]>AllocationTable[[#This Row],[LTP]],"TOP UP","HOLD")))),IF(AllocationTable[[#This Row],[Available Quota]]>AllocationTable[[#This Row],[LTP]],"TOP UP","HOLD")) -> HOLD | L12: =IF(AllocationTable[[#This Row],[SIP%]]>0,_xlfn.CEILING.MATH(AllocationTable[[#This Row],[High]]-(AllocationTable[[#This Row],[High]]*AllocationTable[[#This Row],[SIP%]]%))&" ,Qnt: " &(_xlfn.CEILING.MATH((AllocationTable[[#This Row],[Available Quota]]*14%)/AllocationTable[[#This Row],[LTP]])),IF(AllocationTable[[#This Row],[SIP%]]<0,"EXIT","SIP")) -> EXIT | M12: =IF(AllocationTable[[#This Row],[SIP%]]>0,_xlfn.CEILING.MATH(AllocationTable[[#This Row],[High]]-(AllocationTable[[#This Row],[High]]*2*AllocationTable[[#This Row],[SIP%]]%))&" ,Qnt: " &(_xlfn.CEILING.MATH((AllocationTable[[#This Row],[Available Quota]]*30%)/AllocationTable[[#This Row],[LTP]])),IF(AllocationTable[[#This Row],[SIP%]]<0,"EXIT","SIP")) -> EXIT | N12: =IF(AllocationTable[[#This Row],[SIP%]]>0,_xlfn.CEILING.MATH(AllocationTable[[#This Row],[High]]-(AllocationTable[[#This Row],[High]]*3*AllocationTable[[#This Row],[SIP%]]%))&" ,Qnt: " &(_xlfn.CEILING.MATH((AllocationTable[[#This Row],[Available Quota]]*56%)/AllocationTable[[#This Row],[LTP]])),IF(AllocationTable[[#This Row],[SIP%]]<0,"EXIT","SIP")) -> EXIT | O12: =AllocationTable[[#This Row],[CURRENT VALUE]]-AllocationTable[[#This Row],[AA]] -> 15142.32 | P12: =IFERROR(AllocationTable[[#This Row],[PROFIT]]/AllocationTable[[#This Row],[AA]],0) -> 1.514232 | Q12: =AllocationTable[[#This Row],[QNT]]*AllocationTable[[#This Row],[LTP]] -> 25142.32 | R12: 10000 | S12: 0 | T12: 0 | U12: =IF(AllocationTable[[#This Row],[TYPE]]="Stocks",IF(AllocationTable[[#This Row],[Term]]="Long Term",LongTermQuota*AllocationTable[[#This Row],[EA%]]%,SwingTradeQuota*AllocationTable[[#This Row],[EA%]]%),AllocationTable[[#This Row],[Till 2025]]+(TotalMonth*AllocationTable[[#This Row],[ESIP]])) -> 10000 | V12: =AllocationTable[[#This Row],[AA]]/AllocationTable[[#Totals],[AA]] -> 0.0011576094 | W12: =AllocationTable[[#This Row],[QNT]]*AllocationTable[[#This Row],[AVG.]] -> 10000 | X12: -1
A13: HDFC BSE Sensex Index Fund Direct Growth | B13: MF-Index Fund | C13: Mutual Fund | D13: MF | E13: =_xlfn.IFNA(VLOOKUP(AllocationTable[[#This Row],[TRADE]],LatestDump!A:H,2,FALSE),0) + (_xlfn.IFNA(VLOOKUP(AllocationTable[[#This Row],[TRADE]],LongTerm!A:D,4,0),0)) -> 282.19 | F13: =IFERROR( ( _xlfn.IFNA(VLOOKUP(AllocationTable[[#This Row],[TRADE]],LatestDump!A:H,5,FALSE),0) + _xlfn.IFNA(VLOOKUP(AllocationTable[[#This Row],[TRADE]],AllocationTable9[[TRADE]:[AA]],14,0),0) ) / AllocationTable[[#This Row],[QNT]], 0) -> 507.08827 | G13: =_xlfn.IFNA(ROUND(VLOOKUP(AllocationTable[[#This Row],[TRADE]],LatestDump!A:H,4,FALSE),2),0) -> 737.28 | H13: 816 | I13: =AllocationTable[[#This Row],[EA]]-AllocationTable[[#This Row],[AA]] -> 0 | J13: =IF(AllocationTable[[#This Row],[Term]]="Trading",IF(AllocationTable[[#This Row],[PROFIT%]]>AllocationTable[[#This Row],[Final Target %]]%,"Book Profit",IF(AllocationTable[[#This Row],[PROFIT%]]>AllocationTable[[#This Row],[Partial Profit %]]%,"Book Partial Profit",IF(AllocationTable[[#This Row],[PROFIT%]]<=AllocationTable[[#This Row],[Stop Loss %]]%,"Book Loss",IF(AllocationTable[[#This Row],[Available Quota]]>AllocationTable[[#This Row],[LTP]],"TOP UP","HOLD")))),IF(AllocationTable[[#This Row],[Available Quota]]>AllocationTable[[#This Row],[LTP]],"TOP UP","HOLD")) -> HOLD | L13: =IF(AllocationTable[[#This Row],[SIP%]]>0,_xlfn.CEILING.MATH(AllocationTable[[#This Row],[High]]-(AllocationTable[[#This Row],[High]]*AllocationTable[[#This Row],[SIP%]]%))&" ,Qnt: " &(_xlfn.CEILING.MATH((AllocationTable[[#This Row],[Available Quota]]*14%)/AllocationTable[[#This Row],[LTP]])),IF(AllocationTable[[#This Row],[SIP%]]<0,"EXIT","SIP")) -> 776 ,Qnt: 0 | M13: =IF(AllocationTable[[#This Row],[SIP%]]>0,_xlfn.CEILING.MATH(AllocationTable[[#This Row],[High]]-(AllocationTable[[#This Row],[High]]*2*AllocationTable[[#This Row],[SIP%]]%))&" ,Qnt: " &(_xlfn.CEILING.MATH((AllocationTable[[#This Row],[Available Quota]]*30%)/AllocationTable[[#This Row],[LTP]])),IF(AllocationTable[[#This Row],[SIP%]]<0,"EXIT","SIP")) -> 735 ,Qnt: 0 | N13: =IF(AllocationTable[[#This Row],[SIP%]]>0,_xlfn.CEILING.MATH(AllocationTable[[#This Row],[High]]-(AllocationTable[[#This Row],[High]]*3*AllocationTable[[#This Row],[SIP%]]%))&" ,Qnt: " &(_xlfn.CEILING.MATH((AllocationTable[[#This Row],[Available Quota]]*56%)/AllocationTable[[#This Row],[LTP]])),IF(AllocationTable[[#This Row],[SIP%]]<0,"EXIT","SIP")) -> 694 ,Qnt: 0 | O13: =AllocationTable[[#This Row],[CURRENT VALUE]]-AllocationTable[[#This Row],[AA]] -> 64957.803 | P13: =IFERROR(AllocationTable[[#This Row],[PROFIT]]/AllocationTable[[#This Row],[AA]],0) -> 0.45394804 | Q13: =AllocationTable[[#This Row],[QNT]]*AllocationTable[[#This Row],[LTP]] -> 208053.04 | R13: 143095.24 | S13: 0 | T13: 0 | U13: =IF(AllocationTable[[#This Row],[TYPE]]="Stocks",IF(AllocationTable[[#This Row],[Term]]="Long Term",LongTermQuota*AllocationTable[[#This Row],[EA%]]%,SwingTradeQuota*AllocationTable[[#This Row],[EA%]]%),AllocationTable[[#This Row],[Till 2025]]+(TotalMonth*AllocationTable[[#This Row],[ESIP]])) -> 143095.24 | V13: =AllocationTable[[#This Row],[AA]]/AllocationTable[[#Totals],[AA]] -> 0.016564839 | W13: =AllocationTable[[#This Row],[QNT]]*AllocationTable[[#This Row],[AVG.]] -> 143095.24 | X13: 5
A14: Quant Infrastructure Fund Direct Growth | B14: MF-Infra Fund | C14: Mutual Fund | D14: MF | E14: =_xlfn.IFNA(VLOOKUP(AllocationTable[[#This Row],[TRADE]],LatestDump!A:H,2,FALSE),0) + (_xlfn.IFNA(VLOOKUP(AllocationTable[[#This Row],[TRADE]],LongTerm!A:D,4,0),0)) -> 0 | F14: =IFERROR( ( _xlfn.IFNA(VLOOKUP(AllocationTable[[#This Row],[TRADE]],LatestDump!A:H,5,FALSE),0) + _xlfn.IFNA(VLOOKUP(AllocationTable[[#This Row],[TRADE]],AllocationTable9[[TRADE]:[AA]],14,0),0) ) / AllocationTable[[#This Row],[QNT]], 0) -> 0 | G14: =_xlfn.IFNA(ROUND(VLOOKUP(AllocationTable[[#This Row],[TRADE]],LatestDump!A:H,4,FALSE),2),0) -> 0 | H14: 43 | I14: =AllocationTable[[#This Row],[EA]]-AllocationTable[[#This Row],[AA]] -> 27998.63 | J14: =IF(AllocationTable[[#This Row],[Term]]="Trading",IF(AllocationTable[[#This Row],[PROFIT%]]>AllocationTable[[#This Row],[Final Target %]]%,"Book Profit",IF(AllocationTable[[#This Row],[PROFIT%]]>AllocationTable[[#This Row],[Partial Profit %]]%,"Book Partial Profit",IF(AllocationTable[[#This Row],[PROFIT%]]<=AllocationTable[[#This Row],[Stop Loss %]]%,"Book Loss",IF(AllocationTable[[#This Row],[Available Quota]]>AllocationTable[[#This Row],[LTP]],"TOP UP","HOLD")))),IF(AllocationTable[[#This Row],[Available Quota]]>AllocationTable[[#This Row],[LTP]],"TOP UP","HOLD")) -> TOP UP | L14: =IF(AllocationTable[[#This Row],[SIP%]]>0,_xlfn.CEILING.MATH(AllocationTable[[#This Row],[High]]-(AllocationTable[[#This Row],[High]]*AllocationTable[[#This Row],[SIP%]]%))&" ,Qnt: " &(_xlfn.CEILING.MATH((AllocationTable[[#This Row],[Available Quota]]*14%)/AllocationTable[[#This Row],[LTP]])),IF(AllocationTable[[#This Row],[SIP%]]<0,"EXIT","SIP")) -> #DIV/0! | M14: =IF(AllocationTable[[#This Row],[SIP%]]>0,_xlfn.CEILING.MATH(AllocationTable[[#This Row],[High]]-(AllocationTable[[#This Row],[High]]*2*AllocationTable[[#This Row],[SIP%]]%))&" ,Qnt: " &(_xlfn.CEILING.MATH((AllocationTable[[#This Row],[Available Quota]]*30%)/AllocationTable[[#This Row],[LTP]])),IF(AllocationTable[[#This Row],[SIP%]]<0,"EXIT","SIP")) -> #DIV/0! | N14: =IF(AllocationTable[[#This Row],[SIP%]]>0,_xlfn.CEILING.MATH(AllocationTable[[#This Row],[High]]-(AllocationTable[[#This Row],[High]]*3*AllocationTable[[#This Row],[SIP%]]%))&" ,Qnt: " &(_xlfn.CEILING.MATH((AllocationTable[[#This Row],[Available Quota]]*56%)/AllocationTable[[#This Row],[LTP]])),IF(AllocationTable[[#This Row],[SIP%]]<0,"EXIT","SIP")) -> #DIV/0! | O14: =AllocationTable[[#This Row],[CURRENT VALUE]]-AllocationTable[[#This Row],[AA]] -> 0 | P14: =IFERROR(AllocationTable[[#This Row],[PROFIT]]/AllocationTable[[#This Row],[AA]],0) -> 0 | Q14: =AllocationTable[[#This Row],[QNT]]*AllocationTable[[#This Row],[LTP]] -> 0 | R14: 27998.63 | S14: 0 | T14: 0 | U14: =IF(AllocationTable[[#This Row],[TYPE]]="Stocks",IF(AllocationTable[[#This Row],[Term]]="Long Term",LongTermQuota*AllocationTable[[#This Row],[EA%]]%,SwingTradeQuota*AllocationTable[[#This Row],[EA%]]%),AllocationTable[[#This Row],[Till 2025]]+(TotalMonth*AllocationTable[[#This Row],[ESIP]])) -> 27998.63 | V14: =AllocationTable[[#This Row],[AA]]/AllocationTable[[#Totals],[AA]] -> 0 | W14: =AllocationTable[[#This Row],[QNT]]*AllocationTable[[#This Row],[AVG.]] -> 0 | X14: 8
A15: ICICI Prudential Technology Direct Plan Growth | B15: MF-IT Fund | C15: Mutual Fund | D15: MF | E15: =_xlfn.IFNA(VLOOKUP(AllocationTable[[#This Row],[TRADE]],LatestDump!A:H,2,FALSE),0) + (_xlfn.IFNA(VLOOKUP(AllocationTable[[#This Row],[TRADE]],LongTerm!A:D,4,0),0)) -> 444.284 | F15: =IFERROR( ( _xlfn.IFNA(VLOOKUP(AllocationTable[[#This Row],[TRADE]],LatestDump!A:H,5,FALSE),0) + _xlfn.IFNA(VLOOKUP(AllocationTable[[#This Row],[TRADE]],AllocationTable9[[TRADE]:[AA]],14,0),0) ) / AllocationTable[[#This Row],[QNT]], 0) -> 184.69072 | G15: =_xlfn.IFNA(ROUND(VLOOKUP(AllocationTable[[#This Row],[TRADE]],LatestDump!A:H,4,FALSE),2),0) -> 192.51 | H15: 235 | I15: =AllocationTable[[#This Row],[EA]]-AllocationTable[[#This Row],[AA]] -> -10999.67 | J15: =IF(AllocationTable[[#This Row],[Term]]="Trading",IF(AllocationTable[[#This Row],[PROFIT%]]>AllocationTable[[#This Row],[Final Target %]]%,"Book Profit",IF(AllocationTable[[#This Row],[PROFIT%]]>AllocationTable[[#This Row],[Partial Profit %]]%,"Book Partial Profit",IF(AllocationTable[[#This Row],[PROFIT%]]<=AllocationTable[[#This Row],[Stop Loss %]]%,"Book Loss",IF(AllocationTable[[#This Row],[Available Quota]]>AllocationTable[[#This Row],[LTP]],"TOP UP","HOLD")))),IF(AllocationTable[[#This Row],[Available Quota]]>AllocationTable[[#This Row],[LTP]],"TOP UP","HOLD")) -> HOLD | L15: =IF(AllocationTable[[#This Row],[SIP%]]>0,_xlfn.CEILING.MATH(AllocationTable[[#This Row],[High]]-(AllocationTable[[#This Row],[High]]*AllocationTable[[#This Row],[SIP%]]%))&" ,Qnt: " &(_xlfn.CEILING.MATH((AllocationTable[[#This Row],[Available Quota]]*14%)/AllocationTable[[#This Row],[LTP]])),IF(AllocationTable[[#This Row],[SIP%]]<0,"EXIT","SIP")) -> 217 ,Qnt: -7 | M15: =IF(AllocationTable[[#This Row],[SIP%]]>0,_xlfn.CEILING.MATH(AllocationTable[[#This Row],[High]]-(AllocationTable[[#This Row],[High]]*2*AllocationTable[[#This Row],[SIP%]]%))&" ,Qnt: " &(_xlfn.CEILING.MATH((AllocationTable[[#This Row],[Available Quota]]*30%)/AllocationTable[[#This Row],[LTP]])),IF(AllocationTable[[#This Row],[SIP%]]<0,"EXIT","SIP")) -> 198 ,Qnt: -17 | N15: =IF(AllocationTable[[#This Row],[SIP%]]>0,_xlfn.CEILING.MATH(AllocationTable[[#This Row],[High]]-(AllocationTable[[#This Row],[High]]*3*AllocationTable[[#This Row],[SIP%]]%))&" ,Qnt: " &(_xlfn.CEILING.MATH((AllocationTable[[#This Row],[Available Quota]]*56%)/AllocationTable[[#This Row],[LTP]])),IF(AllocationTable[[#This Row],[SIP%]]<0,"EXIT","SIP")) -> 179 ,Qnt: -31 | O15: =AllocationTable[[#This Row],[CURRENT VALUE]]-AllocationTable[[#This Row],[AA]] -> 3473.9828 | P15: =IFERROR(AllocationTable[[#This Row],[PROFIT]]/AllocationTable[[#This Row],[AA]],0) -> 0.04233718 | Q15: =AllocationTable[[#This Row],[QNT]]*AllocationTable[[#This Row],[LTP]] -> 85529.113 | R15: 71055.46 | S15: 0 | T15: 0 | U15: =IF(AllocationTable[[#This Row],[TYPE]]="Stocks",IF(AllocationTable[[#This Row],[Term]]="Long Term",LongTermQuota*AllocationTable[[#This Row],[EA%]]%,SwingTradeQuota*AllocationTable[[#This Row],[EA%]]%),AllocationTable[[#This Row],[Till 2025]]+(TotalMonth*AllocationTable[[#This Row],[ESIP]])) -> 71055.46 | V15: =AllocationTable[[#This Row],[AA]]/AllocationTable[[#Totals],[AA]] -> 0.0094987787 | W15: =AllocationTable[[#This Row],[QNT]]*AllocationTable[[#This Row],[AVG.]] -> 82055.13 | X15: 8
A16: Mirae Asset Large & Midcap Fund Direct Growth | B16: MF-Large & MidCap | C16: Mutual Fund | D16: MF | E16: =_xlfn.IFNA(VLOOKUP(AllocationTable[[#This Row],[TRADE]],LatestDump!A:H,2,FALSE),0) + (_xlfn.IFNA(VLOOKUP(AllocationTable[[#This Row],[TRADE]],LongTerm!A:D,4,0),0)) -> 1716.273 | F16: =IFERROR( ( _xlfn.IFNA(VLOOKUP(AllocationTable[[#This Row],[TRADE]],LatestDump!A:H,5,FALSE),0) + _xlfn.IFNA(VLOOKUP(AllocationTable[[#This Row],[TRADE]],AllocationTable9[[TRADE]:[AA]],14,0),0) ) / AllocationTable[[#This Row],[QNT]], 0) -> 126.37195 | G16: =_xlfn.IFNA(ROUND(VLOOKUP(AllocationTable[[#This Row],[TRADE]],LatestDump!A:H,4,FALSE),2),0) -> 167.47 | H16: 180 | I16: =AllocationTable[[#This Row],[EA]]-AllocationTable[[#This Row],[AA]] -> 0 | J16: =IF(AllocationTable[[#This Row],[Term]]="Trading",IF(AllocationTable[[#This Row],[PROFIT%]]>AllocationTable[[#This Row],[Final Target %]]%,"Book Profit",IF(AllocationTable[[#This Row],[PROFIT%]]>AllocationTable[[#This Row],[Partial Profit %]]%,"Book Partial Profit",IF(AllocationTable[[#This Row],[PROFIT%]]<=AllocationTable[[#This Row],[Stop Loss %]]%,"Book Loss",IF(AllocationTable[[#This Row],[Available Quota]]>AllocationTable[[#This Row],[LTP]],"TOP UP","HOLD")))),IF(AllocationTable[[#This Row],[Available Quota]]>AllocationTable[[#This Row],[LTP]],"TOP UP","HOLD")) -> HOLD | L16: =IF(AllocationTable[[#This Row],[SIP%]]>0,_xlfn.CEILING.MATH(AllocationTable[[#This Row],[High]]-(AllocationTable[[#This Row],[High]]*AllocationTable[[#This Row],[SIP%]]%))&" ,Qnt: " &(_xlfn.CEILING.MATH((AllocationTable[[#This Row],[Available Quota]]*14%)/AllocationTable[[#This Row],[LTP]])),IF(AllocationTable[[#This Row],[SIP%]]<0,"EXIT","SIP")) -> 171 ,Qnt: 0 | M16: =IF(AllocationTable[[#This Row],[SIP%]]>0,_xlfn.CEILING.MATH(AllocationTable[[#This Row],[High]]-(AllocationTable[[#This Row],[High]]*2*AllocationTable[[#This Row],[SIP%]]%))&" ,Qnt: " &(_xlfn.CEILING.MATH((AllocationTable[[#This Row],[Available Quota]]*30%)/AllocationTable[[#This Row],[LTP]])),IF(AllocationTable[[#This Row],[SIP%]]<0,"EXIT","SIP")) -> 162 ,Qnt: 0 | N16: =IF(AllocationTable[[#This Row],[SIP%]]>0,_xlfn.CEILING.MATH(AllocationTable[[#This Row],[High]]-(AllocationTable[[#This Row],[High]]*3*AllocationTable[[#This Row],[SIP%]]%))&" ,Qnt: " &(_xlfn.CEILING.MATH((AllocationTable[[#This Row],[Available Quota]]*56%)/AllocationTable[[#This Row],[LTP]])),IF(AllocationTable[[#This Row],[SIP%]]<0,"EXIT","SIP")) -> 153 ,Qnt: 0 | O16: =AllocationTable[[#This Row],[CURRENT VALUE]]-AllocationTable[[#This Row],[AA]] -> 70535.479 | P16: =IFERROR(AllocationTable[[#This Row],[PROFIT]]/AllocationTable[[#This Row],[AA]],0) -> 0.32521501 | Q16: =AllocationTable[[#This Row],[QNT]]*AllocationTable[[#This Row],[LTP]] -> 287424.24 | R16: 216888.76 | S16: 0 | T16: 0 | U16: =IF(AllocationTable[[#This Row],[TYPE]]="Stocks",IF(AllocationTable[[#This Row],[Term]]="Long Term",LongTermQuota*AllocationTable[[#This Row],[EA%]]%,SwingTradeQuota*AllocationTable[[#This Row],[EA%]]%),AllocationTable[[#This Row],[Till 2025]]+(TotalMonth*AllocationTable[[#This Row],[ESIP]])) -> 216888.76 | V16: =AllocationTable[[#This Row],[AA]]/AllocationTable[[#Totals],[AA]] -> 0.025107246 | W16: =AllocationTable[[#This Row],[QNT]]*AllocationTable[[#This Row],[AVG.]] -> 216888.76 | X16: 5 | Y16: Tier1
A17: Nippon India Pharma Fund Direct Growth | B17: MF-Pharma Fund | C17: Mutual Fund | D17: MF | E17: =_xlfn.IFNA(VLOOKUP(AllocationTable[[#This Row],[TRADE]],LatestDump!A:H,2,FALSE),0) + (_xlfn.IFNA(VLOOKUP(AllocationTable[[#This Row],[TRADE]],LongTerm!A:D,4,0),0)) -> 154.01 | F17: =IFERROR( ( _xlfn.IFNA(VLOOKUP(AllocationTable[[#This Row],[TRADE]],LatestDump!A:H,5,FALSE),0) + _xlfn.IFNA(VLOOKUP(AllocationTable[[#This Row],[TRADE]],AllocationTable9[[TRADE]:[AA]],14,0),0) ) / AllocationTable[[#This Row],[QNT]], 0) -> 435.23349 | G17: =_xlfn.IFNA(ROUND(VLOOKUP(AllocationTable[[#This Row],[TRADE]],LatestDump!A:H,4,FALSE),2),0) -> 557.75 | H17: 575 | I17: =AllocationTable[[#This Row],[EA]]-AllocationTable[[#This Row],[AA]] -> -1000.2 | J17: =IF(AllocationTable[[#This Row],[Term]]="Trading",IF(AllocationTable[[#This Row],[PROFIT%]]>AllocationTable[[#This Row],[Final Target %]]%,"Book Profit",IF(AllocationTable[[#This Row],[PROFIT%]]>AllocationTable[[#This Row],[Partial Profit %]]%,"Book Partial Profit",IF(AllocationTable[[#This Row],[PROFIT%]]<=AllocationTable[[#This Row],[Stop Loss %]]%,"Book Loss",IF(AllocationTable[[#This Row],[Available Quota]]>AllocationTable[[#This Row],[LTP]],"TOP UP","HOLD")))),IF(AllocationTable[[#This Row],[Available Quota]]>AllocationTable[[#This Row],[LTP]],"TOP UP","HOLD")) -> HOLD | L17: =IF(AllocationTable[[#This Row],[SIP%]]>0,_xlfn.CEILING.MATH(AllocationTable[[#This Row],[High]]-(AllocationTable[[#This Row],[High]]*AllocationTable[[#This Row],[SIP%]]%))&" ,Qnt: " &(_xlfn.CEILING.MATH((AllocationTable[[#This Row],[Available Quota]]*14%)/AllocationTable[[#This Row],[LTP]])),IF(AllocationTable[[#This Row],[SIP%]]<0,"EXIT","SIP")) -> 529 ,Qnt: 0 | M17: =IF(AllocationTable[[#This Row],[SIP%]]>0,_xlfn.CEILING.MATH(AllocationTable[[#This Row],[High]]-(AllocationTable[[#This Row],[High]]*2*AllocationTable[[#This Row],[SIP%]]%))&" ,Qnt: " &(_xlfn.CEILING.MATH((AllocationTable[[#This Row],[Available Quota]]*30%)/AllocationTable[[#This Row],[LTP]])),IF(AllocationTable[[#This Row],[SIP%]]<0,"EXIT","SIP")) -> 483 ,Qnt: 0 | N17: =IF(AllocationTable[[#This Row],[SIP%]]>0,_xlfn.CEILING.MATH(AllocationTable[[#This Row],[High]]-(AllocationTable[[#This Row],[High]]*3*AllocationTable[[#This Row],[SIP%]]%))&" ,Qnt: " &(_xlfn.CEILING.MATH((AllocationTable[[#This Row],[Available Quota]]*56%)/AllocationTable[[#This Row],[LTP]])),IF(AllocationTable[[#This Row],[SIP%]]<0,"EXIT","SIP")) -> 437 ,Qnt: -1 | O17: =AllocationTable[[#This Row],[CURRENT VALUE]]-AllocationTable[[#This Row],[AA]] -> 18868.768 | P17: =IFERROR(AllocationTable[[#This Row],[PROFIT]]/AllocationTable[[#This Row],[AA]],0) -> 0.28149605 | Q17: =AllocationTable[[#This Row],[QNT]]*AllocationTable[[#This Row],[LTP]] -> 85899.078 | R17: 66030.11 | S17: 0 | T17: 0 | U17: =IF(AllocationTable[[#This Row],[TYPE]]="Stocks",IF(AllocationTable[[#This Row],[Term]]="Long Term",LongTermQuota*AllocationTable[[#This Row],[EA%]]%,SwingTradeQuota*AllocationTable[[#This Row],[EA%]]%),AllocationTable[[#This Row],[Till 2025]]+(TotalMonth*AllocationTable[[#This Row],[ESIP]])) -> 66030.11 | V17: =AllocationTable[[#This Row],[AA]]/AllocationTable[[#Totals],[AA]] -> 0.0077594915 | W17: =AllocationTable[[#This Row],[QNT]]*AllocationTable[[#This Row],[AVG.]] -> 67030.31 | X17: 8
A18: Axis Small Cap Fund Direct Growth | B18: MF-Small Cap | C18: Mutual Fund | D18: MF | E18: =_xlfn.IFNA(VLOOKUP(AllocationTable[[#This Row],[TRADE]],LatestDump!A:H,2,FALSE),0) + (_xlfn.IFNA(VLOOKUP(AllocationTable[[#This Row],[TRADE]],LongTerm!A:D,4,0),0)) -> 1735.395 | F18: =IFERROR( ( _xlfn.IFNA(VLOOKUP(AllocationTable[[#This Row],[TRADE]],LatestDump!A:H,5,FALSE),0) + _xlfn.IFNA(VLOOKUP(AllocationTable[[#This Row],[TRADE]],AllocationTable9[[TRADE]:[AA]],14,0),0) ) / AllocationTable[[#This Row],[QNT]], 0) -> 93.585397 | G18: =_xlfn.IFNA(ROUND(VLOOKUP(AllocationTable[[#This Row],[TRADE]],LatestDump!A:H,4,FALSE),2),0) -> 116.95 | H18: 123 | I18: =AllocationTable[[#This Row],[EA]]-AllocationTable[[#This Row],[AA]] -> -1999.91 | J18: =IF(AllocationTable[[#This Row],[Term]]="Trading",IF(AllocationTable[[#This Row],[PROFIT%]]>AllocationTable[[#This Row],[Final Target %]]%,"Book Profit",IF(AllocationTable[[#This Row],[PROFIT%]]>AllocationTable[[#This Row],[Partial Profit %]]%,"Book Partial Profit",IF(AllocationTable[[#This Row],[PROFIT%]]<=AllocationTable[[#This Row],[Stop Loss %]]%,"Book Loss",IF(AllocationTable[[#This Row],[Available Quota]]>AllocationTable[[#This Row],[LTP]],"TOP UP","HOLD")))),IF(AllocationTable[[#This Row],[Available Quota]]>AllocationTable[[#This Row],[LTP]],"TOP UP","HOLD")) -> HOLD | L18: =IF(AllocationTable[[#This Row],[SIP%]]>0,_xlfn.CEILING.MATH(AllocationTable[[#This Row],[High]]-(AllocationTable[[#This Row],[High]]*AllocationTable[[#This Row],[SIP%]]%))&" ,Qnt: " &(_xlfn.CEILING.MATH((AllocationTable[[#This Row],[Available Quota]]*14%)/AllocationTable[[#This Row],[LTP]])),IF(AllocationTable[[#This Row],[SIP%]]<0,"EXIT","SIP")) -> EXIT | M18: =IF(AllocationTable[[#This Row],[SIP%]]>0,_xlfn.CEILING.MATH(AllocationTable[[#This Row],[High]]-(AllocationTable[[#This Row],[High]]*2*AllocationTable[[#This Row],[SIP%]]%))&" ,Qnt: " &(_xlfn.CEILING.MATH((AllocationTable[[#This Row],[Available Quota]]*30%)/AllocationTable[[#This Row],[LTP]])),IF(AllocationTable[[#This Row],[SIP%]]<0,"EXIT","SIP")) -> EXIT | N18: =IF(AllocationTable[[#This Row],[SIP%]]>0,_xlfn.CEILING.MATH(AllocationTable[[#This Row],[High]]-(AllocationTable[[#This Row],[High]]*3*AllocationTable[[#This Row],[SIP%]]%))&" ,Qnt: " &(_xlfn.CEILING.MATH((AllocationTable[[#This Row],[Available Quota]]*56%)/AllocationTable[[#This Row],[LTP]])),IF(AllocationTable[[#This Row],[SIP%]]<0,"EXIT","SIP")) -> EXIT | O18: =AllocationTable[[#This Row],[CURRENT VALUE]]-AllocationTable[[#This Row],[AA]] -> 40546.815 | P18: =IFERROR(AllocationTable[[#This Row],[PROFIT]]/AllocationTable[[#This Row],[AA]],0) -> 0.24966078 | Q18: =AllocationTable[[#This Row],[QNT]]*AllocationTable[[#This Row],[LTP]] -> 202954.45 | R18: 160407.72 | S18: 0 | T18: 0 | U18: =IF(AllocationTable[[#This Row],[TYPE]]="Stocks",IF(AllocationTable[[#This Row],[Term]]="Long Term",LongTermQuota*AllocationTable[[#This Row],[EA%]]%,SwingTradeQuota*AllocationTable[[#This Row],[EA%]]%),AllocationTable[[#This Row],[Till 2025]]+(TotalMonth*AllocationTable[[#This Row],[ESIP]])) -> 160407.72 | V18: =AllocationTable[[#This Row],[AA]]/AllocationTable[[#Totals],[AA]] -> 0.018800459 | W18: =AllocationTable[[#This Row],[QNT]]*AllocationTable[[#This Row],[AVG.]] -> 162407.63 | X18: -1
A19: Quant Small Cap Fund Direct Plan Growth | B19: MF-Small Cap | C19: Mutual Fund | D19: MF | E19: =_xlfn.IFNA(VLOOKUP(AllocationTable[[#This Row],[TRADE]],LatestDump!A:H,2,FALSE),0) + (_xlfn.IFNA(VLOOKUP(AllocationTable[[#This Row],[TRADE]],LongTerm!A:D,4,0),0)) -> 227.515 | F19: =IFERROR( ( _xlfn.IFNA(VLOOKUP(AllocationTable[[#This Row],[TRADE]],LatestDump!A:H,5,FALSE),0) + _xlfn.IFNA(VLOOKUP(AllocationTable[[#This Row],[TRADE]],AllocationTable9[[TRADE]:[AA]],14,0),0) ) / AllocationTable[[#This Row],[QNT]], 0) -> 178.00004 | G19: =_xlfn.IFNA(ROUND(VLOOKUP(AllocationTable[[#This Row],[TRADE]],LatestDump!A:H,4,FALSE),2),0) -> 264.3 | H19: 279 | I19: =AllocationTable[[#This Row],[EA]]-AllocationTable[[#This Row],[AA]] -> 0 | J19: =IF(AllocationTable[[#This Row],[Term]]="Trading",IF(AllocationTable[[#This Row],[PROFIT%]]>AllocationTable[[#This Row],[Final Target %]]%,"Book Profit",IF(AllocationTable[[#This Row],[PROFIT%]]>AllocationTable[[#This Row],[Partial Profit %]]%,"Book Partial Profit",IF(AllocationTable[[#This Row],[PROFIT%]]<=AllocationTable[[#This Row],[Stop Loss %]]%,"Book Loss",IF(AllocationTable[[#This Row],[Available Quota]]>AllocationTable[[#This Row],[LTP]],"TOP UP","HOLD")))),IF(AllocationTable[[#This Row],[Available Quota]]>AllocationTable[[#This Row],[LTP]],"TOP UP","HOLD")) -> HOLD | L19: =IF(AllocationTable[[#This Row],[SIP%]]>0,_xlfn.CEILING.MATH(AllocationTable[[#This Row],[High]]-(AllocationTable[[#This Row],[High]]*AllocationTable[[#This Row],[SIP%]]%))&" ,Qnt: " &(_xlfn.CEILING.MATH((AllocationTable[[#This Row],[Available Quota]]*14%)/AllocationTable[[#This Row],[LTP]])),IF(AllocationTable[[#This Row],[SIP%]]<0,"EXIT","SIP")) -> EXIT | M19: =IF(AllocationTable[[#This Row],[SIP%]]>0,_xlfn.CEILING.MATH(AllocationTable[[#This Row],[High]]-(AllocationTable[[#This Row],[High]]*2*AllocationTable[[#This Row],[SIP%]]%))&" ,Qnt: " &(_xlfn.CEILING.MATH((AllocationTable[[#This Row],[Available Quota]]*30%)/AllocationTable[[#This Row],[LTP]])),IF(AllocationTable[[#This Row],[SIP%]]<0,"EXIT","SIP")) -> EXIT | N19: =IF(AllocationTable[[#This Row],[SIP%]]>0,_xlfn.CEILING.MATH(AllocationTable[[#This Row],[High]]-(AllocationTable[[#This Row],[High]]*3*AllocationTable[[#This Row],[SIP%]]%))&" ,Qnt: " &(_xlfn.CEILING.MATH((AllocationTable[[#This Row],[Available Quota]]*56%)/AllocationTable[[#This Row],[LTP]])),IF(AllocationTable[[#This Row],[SIP%]]<0,"EXIT","SIP")) -> EXIT | O19: =AllocationTable[[#This Row],[CURRENT VALUE]]-AllocationTable[[#This Row],[AA]] -> 19634.535 | P19: =IFERROR(AllocationTable[[#This Row],[PROFIT]]/AllocationTable[[#This Row],[AA]],0) -> 0.48483109 | Q19: =AllocationTable[[#This Row],[QNT]]*AllocationTable[[#This Row],[LTP]] -> 60132.215 | R19: 40497.68 | S19: 0 | T19: 0 | U19: =IF(AllocationTable[[#This Row],[TYPE]]="Stocks",IF(AllocationTable[[#This Row],[Term]]="Long Term",LongTermQuota*AllocationTable[[#This Row],[EA%]]%,SwingTradeQuota*AllocationTable[[#This Row],[EA%]]%),AllocationTable[[#This Row],[Till 2025]]+(TotalMonth*AllocationTable[[#This Row],[ESIP]])) -> 40497.68 | V19: =AllocationTable[[#This Row],[AA]]/AllocationTable[[#Totals],[AA]] -> 0.0046880494 | W19: =AllocationTable[[#This Row],[QNT]]*AllocationTable[[#This Row],[AVG.]] -> 40497.68 | X19: -1
A20: Edelweiss US Technology Equity FoF Direct Growth | B20: MF-US IT Funds | C20: Mutual Fund | D20: MF | E20: =_xlfn.IFNA(VLOOKUP(AllocationTable[[#This Row],[TRADE]],LatestDump!A:H,2,FALSE),0) + (_xlfn.IFNA(VLOOKUP(AllocationTable[[#This Row],[TRADE]],LongTerm!A:D,4,0),0)) -> 340.521 | F20: =IFERROR( ( _xlfn.IFNA(VLOOKUP(AllocationTable[[#This Row],[TRADE]],LatestDump!A:H,5,FALSE),0) + _xlfn.IFNA(VLOOKUP(AllocationTable[[#This Row],[TRADE]],AllocationTable9[[TRADE]:[AA]],14,0),0) ) / AllocationTable[[#This Row],[QNT]], 0) -> 32.301708 | G20: =_xlfn.IFNA(ROUND(VLOOKUP(AllocationTable[[#This Row],[TRADE]],LatestDump!A:H,4,FALSE),2),0) -> 32.79 | H20: 35 | I20: =AllocationTable[[#This Row],[EA]]-AllocationTable[[#This Row],[AA]] -> 9000.48 | J20: =IF(AllocationTable[[#This Row],[Term]]="Trading",IF(AllocationTable[[#This Row],[PROFIT%]]>AllocationTable[[#This Row],[Final Target %]]%,"Book Profit",IF(AllocationTable[[#This Row],[PROFIT%]]>AllocationTable[[#This Row],[Partial Profit %]]%,"Book Partial Profit",IF(AllocationTable[[#This Row],[PROFIT%]]<=AllocationTable[[#This Row],[Stop Loss %]]%,"Book Loss",IF(AllocationTable[[#This Row],[Available Quota]]>AllocationTable[[#This Row],[LTP]],"TOP UP","HOLD")))),IF(AllocationTable[[#This Row],[Available Quota]]>AllocationTable[[#This Row],[LTP]],"TOP UP","HOLD")) -> TOP UP | L20: =IF(AllocationTable[[#This Row],[SIP%]]>0,_xlfn.CEILING.MATH(AllocationTable[[#This Row],[High]]-(AllocationTable[[#This Row],[High]]*AllocationTable[[#This Row],[SIP%]]%))&" ,Qnt: " &(_xlfn.CEILING.MATH((AllocationTable[[#This Row],[Available Quota]]*14%)/AllocationTable[[#This Row],[LTP]])),IF(AllocationTable[[#This Row],[SIP%]]<0,"EXIT","SIP")) -> 34 ,Qnt: 39 | M20: =IF(AllocationTable[[#This Row],[SIP%]]>0,_xlfn.CEILING.MATH(AllocationTable[[#This Row],[High]]-(AllocationTable[[#This Row],[High]]*2*AllocationTable[[#This Row],[SIP%]]%))&" ,Qnt: " &(_xlfn.CEILING.MATH((AllocationTable[[#This Row],[Available Quota]]*30%)/AllocationTable[[#This Row],[LTP]])),IF(AllocationTable[[#This Row],[SIP%]]<0,"EXIT","SIP")) -> 32 ,Qnt: 83 | N20: =IF(AllocationTable[[#This Row],[SIP%]]>0,_xlfn.CEILING.MATH(AllocationTable[[#This Row],[High]]-(AllocationTable[[#This Row],[High]]*3*AllocationTable[[#This Row],[SIP%]]%))&" ,Qnt: " &(_xlfn.CEILING.MATH((AllocationTable[[#This Row],[Available Quota]]*56%)/AllocationTable[[#This Row],[LTP]])),IF(AllocationTable[[#This Row],[SIP%]]<0,"EXIT","SIP")) -> 30 ,Qnt: 154 | O20: =AllocationTable[[#This Row],[CURRENT VALUE]]-AllocationTable[[#This Row],[AA]] -> 166.27359 | P20: =IFERROR(AllocationTable[[#This Row],[PROFIT]]/AllocationTable[[#This Row],[AA]],0) -> 0.015116592 | Q20: =AllocationTable[[#This Row],[QNT]]*AllocationTable[[#This Row],[LTP]] -> 11165.684 | R20: 1999.89 | S20: 3000 | T20: 0 | U20: =IF(AllocationTable[[#This Row],[TYPE]]="Stocks",IF(AllocationTable[[#This Row],[Term]]="Long Term",LongTermQuota*AllocationTable[[#This Row],[EA%]]%,SwingTradeQuota*AllocationTable[[#This Row],[EA%]]%),AllocationTable[[#This Row],[Till 2025]]+(TotalMonth*AllocationTable[[#This Row],[ESIP]])) -> 19999.89 | V20: =AllocationTable[[#This Row],[AA]]/AllocationTable[[#Totals],[AA]] -> 0.001273302 | W20: =AllocationTable[[#This Row],[QNT]]*AllocationTable[[#This Row],[AVG.]] -> 10999.41 | X20: 5
A21: ICICI Prudential Equity & Debt Fund Direct Growth | C21: Mutual Fund | D21: MF | E21: =_xlfn.IFNA(VLOOKUP(AllocationTable[[#This Row],[TRADE]],LatestDump!A:H,2,FALSE),0) + (_xlfn.IFNA(VLOOKUP(AllocationTable[[#This Row],[TRADE]],LongTerm!A:D,4,0),0)) -> 102.803 | F21: =IFERROR( ( _xlfn.IFNA(VLOOKUP(AllocationTable[[#This Row],[TRADE]],LatestDump!A:H,5,FALSE),0) + _xlfn.IFNA(VLOOKUP(AllocationTable[[#This Row],[TRADE]],AllocationTable9[[TRADE]:[AA]],14,0),0) ) / AllocationTable[[#This Row],[QNT]], 0) -> 442.56957 | G21: =_xlfn.IFNA(ROUND(VLOOKUP(AllocationTable[[#This Row],[TRADE]],LatestDump!A:H,4,FALSE),2),0) -> 443.03 | H21: 461 | I21: =AllocationTable[[#This Row],[EA]]-AllocationTable[[#This Row],[AA]] -> 35502.52 | J21: =IF(AllocationTable[[#This Row],[Term]]="Trading",IF(AllocationTable[[#This Row],[PROFIT%]]>AllocationTable[[#This Row],[Final Target %]]%,"Book Profit",IF(AllocationTable[[#This Row],[PROFIT%]]>AllocationTable[[#This Row],[Partial Profit %]]%,"Book Partial Profit",IF(AllocationTable[[#This Row],[PROFIT%]]<=AllocationTable[[#This Row],[Stop Loss %]]%,"Book Loss",IF(AllocationTable[[#This Row],[Available Quota]]>AllocationTable[[#This Row],[LTP]],"TOP UP","HOLD")))),IF(AllocationTable[[#This Row],[Available Quota]]>AllocationTable[[#This Row],[LTP]],"TOP UP","HOLD")) -> TOP UP | L21: =IF(AllocationTable[[#This Row],[SIP%]]>0,_xlfn.CEILING.MATH(AllocationTable[[#This Row],[High]]-(AllocationTable[[#This Row],[High]]*AllocationTable[[#This Row],[SIP%]]%))&" ,Qnt: " &(_xlfn.CEILING.MATH((AllocationTable[[#This Row],[Available Quota]]*14%)/AllocationTable[[#This Row],[LTP]])),IF(AllocationTable[[#This Row],[SIP%]]<0,"EXIT","SIP")) -> 438 ,Qnt: 12 | M21: =IF(AllocationTable[[#This Row],[SIP%]]>0,_xlfn.CEILING.MATH(AllocationTable[[#This Row],[High]]-(AllocationTable[[#This Row],[High]]*2*AllocationTable[[#This Row],[SIP%]]%))&" ,Qnt: " &(_xlfn.CEILING.MATH((AllocationTable[[#This Row],[Available Quota]]*30%)/AllocationTable[[#This Row],[LTP]])),IF(AllocationTable[[#This Row],[SIP%]]<0,"EXIT","SIP")) -> 415 ,Qnt: 25 | N21: =IF(AllocationTable[[#This Row],[SIP%]]>0,_xlfn.CEILING.MATH(AllocationTable[[#This Row],[High]]-(AllocationTable[[#This Row],[High]]*3*AllocationTable[[#This Row],[SIP%]]%))&" ,Qnt: " &(_xlfn.CEILING.MATH((AllocationTable[[#This Row],[Available Quota]]*56%)/AllocationTable[[#This Row],[LTP]])),IF(AllocationTable[[#This Row],[SIP%]]<0,"EXIT","SIP")) -> 392 ,Qnt: 45 | O21: =AllocationTable[[#This Row],[CURRENT VALUE]]-AllocationTable[[#This Row],[AA]] -> 47.33309 | P21: =IFERROR(AllocationTable[[#This Row],[PROFIT]]/AllocationTable[[#This Row],[AA]],0) -> 0.0010403453 | Q21: =AllocationTable[[#This Row],[QNT]]*AllocationTable[[#This Row],[LTP]] -> 45544.813 | R21: 0 | S21: 13500 | T21: 0 | U21: =IF(AllocationTable[[#This Row],[TYPE]]="Stocks",IF(AllocationTable[[#This Row],[Term]]="Long Term",LongTermQuota*AllocationTable[[#This Row],[EA%]]%,SwingTradeQuota*AllocationTable[[#This Row],[EA%]]%),AllocationTable[[#This Row],[Till 2025]]+(TotalMonth*AllocationTable[[#This Row],[ESIP]])) -> 81000 | V21: =AllocationTable[[#This Row],[AA]]/AllocationTable[[#Totals],[AA]] -> 0.0052668309 | W21: =AllocationTable[[#This Row],[QNT]]*AllocationTable[[#This Row],[AVG.]] -> 45497.48 | X21: 5
A22: NPS | B22: Fixed Return | C22: NPS | D22: Retirement | E22: =_xlfn.IFNA(VLOOKUP(AllocationTable[[#This Row],[TRADE]],LatestDump!A:H,2,FALSE),0) + (_xlfn.IFNA(VLOOKUP(AllocationTable[[#This Row],[TRADE]],LongTerm!A:D,4,0),0)) -> 103 | F22: =IFERROR( ( _xlfn.IFNA(VLOOKUP(AllocationTable[[#This Row],[TRADE]],LatestDump!A:H,5,FALSE),0) + _xlfn.IFNA(VLOOKUP(AllocationTable[[#This Row],[TRADE]],AllocationTable9[[TRADE]:[AA]],14,0),0) ) / AllocationTable[[#This Row],[QNT]], 0) -> 10098.068 | G22: =_xlfn.IFNA(ROUND(VLOOKUP(AllocationTable[[#This Row],[TRADE]],LatestDump!A:H,4,FALSE),2),0) -> 14767.18 | I22: =AllocationTable[[#This Row],[EA]]-AllocationTable[[#This Row],[AA]] -> 46545 | J22: =IF(AllocationTable[[#This Row],[Term]]="Trading",IF(AllocationTable[[#This Row],[PROFIT%]]>AllocationTable[[#This Row],[Final Target %]]%,"Book Profit",IF(AllocationTable[[#This Row],[PROFIT%]]>AllocationTable[[#This Row],[Partial Profit %]]%,"Book Partial Profit",IF(AllocationTable[[#This Row],[PROFIT%]]<=AllocationTable[[#This Row],[Stop Loss %]]%,"Book Loss",IF(AllocationTable[[#This Row],[Available Quota]]>AllocationTable[[#This Row],[LTP]],"TOP UP","HOLD")))),IF(AllocationTable[[#This Row],[Available Quota]]>AllocationTable[[#This Row],[LTP]],"TOP UP","HOLD")) -> TOP UP | L22: =IF(AllocationTable[[#This Row],[SIP%]]>0,_xlfn.CEILING.MATH(AllocationTable[[#This Row],[High]]-(AllocationTable[[#This Row],[High]]*AllocationTable[[#This Row],[SIP%]]%))&" ,Qnt: " &(_xlfn.CEILING.MATH((AllocationTable[[#This Row],[Available Quota]]*14%)/AllocationTable[[#This Row],[LTP]])),IF(AllocationTable[[#This Row],[SIP%]]<0,"EXIT","SIP")) -> SIP | M22: =IF(AllocationTable[[#This Row],[SIP%]]>0,_xlfn.CEILING.MATH(AllocationTable[[#This Row],[High]]-(AllocationTable[[#This Row],[High]]*2*AllocationTable[[#This Row],[SIP%]]%))&" ,Qnt: " &(_xlfn.CEILING.MATH((AllocationTable[[#This Row],[Available Quota]]*30%)/AllocationTable[[#This Row],[LTP]])),IF(AllocationTable[[#This Row],[SIP%]]<0,"EXIT","SIP")) -> SIP | N22: =IF(AllocationTable[[#This Row],[SIP%]]>0,_xlfn.CEILING.MATH(AllocationTable[[#This Row],[High]]-(AllocationTable[[#This Row],[High]]*3*AllocationTable[[#This Row],[SIP%]]%))&" ,Qnt: " &(_xlfn.CEILING.MATH((AllocationTable[[#This Row],[Available Quota]]*56%)/AllocationTable[[#This Row],[LTP]])),IF(AllocationTable[[#This Row],[SIP%]]<0,"EXIT","SIP")) -> SIP | O22: =AllocationTable[[#This Row],[CURRENT VALUE]]-AllocationTable[[#This Row],[AA]] -> 480918.54 | P22: =IFERROR(AllocationTable[[#This Row],[PROFIT]]/AllocationTable[[#This Row],[AA]],0) -> 0.46237677 | Q22: =AllocationTable[[#This Row],[QNT]]*AllocationTable[[#This Row],[LTP]] -> 1521019.5 | R22: 993556 | S22: 15515 | T22: 0 | U22: =IF(AllocationTable[[#This Row],[TYPE]]="Stocks",IF(AllocationTable[[#This Row],[Term]]="Long Term",LongTermQuota*AllocationTable[[#This Row],[EA%]]%,SwingTradeQuota*AllocationTable[[#This Row],[EA%]]%),AllocationTable[[#This Row],[Till 2025]]+(TotalMonth*AllocationTable[[#This Row],[ESIP]])) -> 1086646 | V22: =AllocationTable[[#This Row],[AA]]/AllocationTable[[#Totals],[AA]] -> 0.12040307 | W22: =AllocationTable[[#This Row],[QNT]]*AllocationTable[[#This Row],[AVG.]] -> 1040101 | X22: 0
A23: Flat | B23: Home | C23: Real State | D23: Flat | E23: =_xlfn.IFNA(VLOOKUP(AllocationTable[[#This Row],[TRADE]],LatestDump!A:H,2,FALSE),0) + (_xlfn.IFNA(VLOOKUP(AllocationTable[[#This Row],[TRADE]],LongTerm!A:D,4,0),0)) -> 1 | F23: =IFERROR( ( _xlfn.IFNA(VLOOKUP(AllocationTable[[#This Row],[TRADE]],LatestDump!A:H,5,FALSE),0) + _xlfn.IFNA(VLOOKUP(AllocationTable[[#This Row],[TRADE]],AllocationTable9[[TRADE]:[AA]],14,0),0) ) / AllocationTable[[#This Row],[QNT]], 0) -> 0 | G23: =_xlfn.IFNA(ROUND(VLOOKUP(AllocationTable[[#This Row],[TRADE]],LatestDump!A:H,4,FALSE),2),0) -> 0 | I23: =AllocationTable[[#This Row],[EA]]-AllocationTable[[#This Row],[AA]] -> 0 | J23: =IF(AllocationTable[[#This Row],[Term]]="Trading",IF(AllocationTable[[#This Row],[PROFIT%]]>AllocationTable[[#This Row],[Final Target %]]%,"Book Profit",IF(AllocationTable[[#This Row],[PROFIT%]]>AllocationTable[[#This Row],[Partial Profit %]]%,"Book Partial Profit",IF(AllocationTable[[#This Row],[PROFIT%]]<=AllocationTable[[#This Row],[Stop Loss %]]%,"Book Loss",IF(AllocationTable[[#This Row],[Available Quota]]>AllocationTable[[#This Row],[LTP]],"TOP UP","HOLD")))),IF(AllocationTable[[#This Row],[Available Quota]]>AllocationTable[[#This Row],[LTP]],"TOP UP","HOLD")) -> HOLD | L23: =IF(AllocationTable[[#This Row],[SIP%]]>0,_xlfn.CEILING.MATH(AllocationTable[[#This Row],[High]]-(AllocationTable[[#This Row],[High]]*AllocationTable[[#This Row],[SIP%]]%))&" ,Qnt: " &(_xlfn.CEILING.MATH((AllocationTable[[#This Row],[Available Quota]]*14%)/AllocationTable[[#This Row],[LTP]])),IF(AllocationTable[[#This Row],[SIP%]]<0,"EXIT","SIP")) -> SIP | M23: =IF(AllocationTable[[#This Row],[SIP%]]>0,_xlfn.CEILING.MATH(AllocationTable[[#This Row],[High]]-(AllocationTable[[#This Row],[High]]*2*AllocationTable[[#This Row],[SIP%]]%))&" ,Qnt: " &(_xlfn.CEILING.MATH((AllocationTable[[#This Row],[Available Quota]]*30%)/AllocationTable[[#This Row],[LTP]])),IF(AllocationTable[[#This Row],[SIP%]]<0,"EXIT","SIP")) -> SIP | N23: =IF(AllocationTable[[#This Row],[SIP%]]>0,_xlfn.CEILING.MATH(AllocationTable[[#This Row],[High]]-(AllocationTable[[#This Row],[High]]*3*AllocationTable[[#This Row],[SIP%]]%))&" ,Qnt: " &(_xlfn.CEILING.MATH((AllocationTable[[#This Row],[Available Quota]]*56%)/AllocationTable[[#This Row],[LTP]])),IF(AllocationTable[[#This Row],[SIP%]]<0,"EXIT","SIP")) -> SIP | O23: =AllocationTable[[#This Row],[CURRENT VALUE]]-AllocationTable[[#This Row],[AA]] -> 0 | P23: =IFERROR(AllocationTable[[#This Row],[PROFIT]]/AllocationTable[[#This Row],[AA]],0) -> 0 | Q23: =AllocationTable[[#This Row],[QNT]]*AllocationTable[[#This Row],[LTP]] -> 0 | R23: 0 | S23: 0 | T23: 0 | U23: =IF(AllocationTable[[#This Row],[TYPE]]="Stocks",IF(AllocationTable[[#This Row],[Term]]="Long Term",LongTermQuota*AllocationTable[[#This Row],[EA%]]%,SwingTradeQuota*AllocationTable[[#This Row],[EA%]]%),AllocationTable[[#This Row],[Till 2025]]+(TotalMonth*AllocationTable[[#This Row],[ESIP]])) -> 0 | V23: =AllocationTable[[#This Row],[AA]]/AllocationTable[[#Totals],[AA]] -> 0 | W23: =AllocationTable[[#This Row],[QNT]]*AllocationTable[[#This Row],[AVG.]] -> 0 | X23: 0
A24: SGB | B24: Gold | C24: SGB | D24: Gold | E24: =_xlfn.IFNA(VLOOKUP(AllocationTable[[#This Row],[TRADE]],LatestDump!A:H,2,FALSE),0) + (_xlfn.IFNA(VLOOKUP(AllocationTable[[#This Row],[TRADE]],LongTerm!A:D,4,0),0)) -> 36 | F24: =IFERROR( ( _xlfn.IFNA(VLOOKUP(AllocationTable[[#This Row],[TRADE]],LatestDump!A:H,5,FALSE),0) + _xlfn.IFNA(VLOOKUP(AllocationTable[[#This Row],[TRADE]],AllocationTable9[[TRADE]:[AA]],14,0),0) ) / AllocationTable[[#This Row],[QNT]], 0) -> 5555 | G24: =_xlfn.IFNA(ROUND(VLOOKUP(AllocationTable[[#This Row],[TRADE]],LatestDump!A:H,4,FALSE),2),0) -> 15285 | H24: 17000 | I24: =AllocationTable[[#This Row],[EA]]-AllocationTable[[#This Row],[AA]] -> 0 | J24: =IF(AllocationTable[[#This Row],[Term]]="Trading",IF(AllocationTable[[#This Row],[PROFIT%]]>AllocationTable[[#This Row],[Final Target %]]%,"Book Profit",IF(AllocationTable[[#This Row],[PROFIT%]]>AllocationTable[[#This Row],[Partial Profit %]]%,"Book Partial Profit",IF(AllocationTable[[#This Row],[PROFIT%]]<=AllocationTable[[#This Row],[Stop Loss %]]%,"Book Loss",IF(AllocationTable[[#This Row],[Available Quota]]>AllocationTable[[#This Row],[LTP]],"TOP UP","HOLD")))),IF(AllocationTable[[#This Row],[Available Quota]]>AllocationTable[[#This Row],[LTP]],"TOP UP","HOLD")) -> HOLD | L24: =IF(AllocationTable[[#This Row],[SIP%]]>0,_xlfn.CEILING.MATH(AllocationTable[[#This Row],[High]]-(AllocationTable[[#This Row],[High]]*AllocationTable[[#This Row],[SIP%]]%))&" ,Qnt: " &(_xlfn.CEILING.MATH((AllocationTable[[#This Row],[Available Quota]]*14%)/AllocationTable[[#This Row],[LTP]])),IF(AllocationTable[[#This Row],[SIP%]]<0,"EXIT","SIP")) -> EXIT | M24: =IF(AllocationTable[[#This Row],[SIP%]]>0,_xlfn.CEILING.MATH(AllocationTable[[#This Row],[High]]-(AllocationTable[[#This Row],[High]]*2*AllocationTable[[#This Row],[SIP%]]%))&" ,Qnt: " &(_xlfn.CEILING.MATH((AllocationTable[[#This Row],[Available Quota]]*30%)/AllocationTable[[#This Row],[LTP]])),IF(AllocationTable[[#This Row],[SIP%]]<0,"EXIT","SIP")) -> EXIT | N24: =IF(AllocationTable[[#This Row],[SIP%]]>0,_xlfn.CEILING.MATH(AllocationTable[[#This Row],[High]]-(AllocationTable[[#This Row],[High]]*3*AllocationTable[[#This Row],[SIP%]]%))&" ,Qnt: " &(_xlfn.CEILING.MATH((AllocationTable[[#This Row],[Available Quota]]*56%)/AllocationTable[[#This Row],[LTP]])),IF(AllocationTable[[#This Row],[SIP%]]<0,"EXIT","SIP")) -> EXIT | O24: =AllocationTable[[#This Row],[CURRENT VALUE]]-AllocationTable[[#This Row],[AA]] -> 350280 | P24: =IFERROR(AllocationTable[[#This Row],[PROFIT]]/AllocationTable[[#This Row],[AA]],0) -> 1.7515752 | Q24: =AllocationTable[[#This Row],[QNT]]*AllocationTable[[#This Row],[LTP]] -> 550260 | R24: 199980 | S24: 0 | T24: 0 | U24: =IF(AllocationTable[[#This Row],[TYPE]]="Stocks",IF(AllocationTable[[#This Row],[Term]]="Long Term",LongTermQuota*AllocationTable[[#This Row],[EA%]]%,SwingTradeQuota*AllocationTable[[#This Row],[EA%]]%),AllocationTable[[#This Row],[Till 2025]]+(TotalMonth*AllocationTable[[#This Row],[ESIP]])) -> 199980 | V24: =AllocationTable[[#This Row],[AA]]/AllocationTable[[#Totals],[AA]] -> 0.023149872 | W24: =AllocationTable[[#This Row],[QNT]]*AllocationTable[[#This Row],[AVG.]] -> 199980 | X24: -1
A25: ASHOKLEY | B25: AUTO ANCILLARY | C25: Stocks | D25: Long Term | E25: =_xlfn.IFNA(VLOOKUP(AllocationTable[[#This Row],[TRADE]],LatestDump!A:H,2,FALSE),0) + (_xlfn.IFNA(VLOOKUP(AllocationTable[[#This Row],[TRADE]],LongTerm!A:D,4,0),0)) -> 255 | F25: =IFERROR( ( _xlfn.IFNA(VLOOKUP(AllocationTable[[#This Row],[TRADE]],LatestDump!A:H,5,FALSE),0) + _xlfn.IFNA(VLOOKUP(AllocationTable[[#This Row],[TRADE]],AllocationTable9[[TRADE]:[AA]],14,0),0) ) / AllocationTable[[#This Row],[QNT]], 0) -> 117.26 | G25: =_xlfn.IFNA(ROUND(VLOOKUP(AllocationTable[[#This Row],[TRADE]],LatestDump!A:H,4,FALSE),2),0) -> 178.02 | H25: 216 | I25: =AllocationTable[[#This Row],[EA]]-AllocationTable[[#This Row],[AA]] -> -12656.417 | J25: =IF(AllocationTable[[#This Row],[Term]]="Trading",IF(AllocationTable[[#This Row],[PROFIT%]]>AllocationTable[[#This Row],[Final Target %]]%,"Book Profit",IF(AllocationTable[[#This Row],[PROFIT%]]>AllocationTable[[#This Row],[Partial Profit %]]%,"Book Partial Profit",IF(AllocationTable[[#This Row],[PROFIT%]]<=AllocationTable[[#This Row],[Stop Loss %]]%,"Book Loss",IF(AllocationTable[[#This Row],[Available Quota]]>AllocationTable[[#This Row],[LTP]],"TOP UP","HOLD")))),IF(AllocationTable[[#This Row],[Available Quota]]>AllocationTable[[#This Row],[LTP]],"TOP UP","HOLD")) -> HOLD | L25: =IF(AllocationTable[[#This Row],[SIP%]]>0,_xlfn.CEILING.MATH(AllocationTable[[#This Row],[High]]-(AllocationTable[[#This Row],[High]]*AllocationTable[[#This Row],[SIP%]]%))&" ,Qnt: " &(_xlfn.CEILING.MATH((AllocationTable[[#This Row],[Available Quota]]*14%)/AllocationTable[[#This Row],[LTP]])),IF(AllocationTable[[#This Row],[SIP%]]<0,"EXIT","SIP")) -> 204 ,Qnt: -9 | M25: =IF(AllocationTable[[#This Row],[SIP%]]>0,_xlfn.CEILING.MATH(AllocationTable[[#This Row],[High]]-(AllocationTable[[#This Row],[High]]*2*AllocationTable[[#This Row],[SIP%]]%))&" ,Qnt: " &(_xlfn.CEILING.MATH((AllocationTable[[#This Row],[Available Quota]]*30%)/AllocationTable[[#This Row],[LTP]])),IF(AllocationTable[[#This Row],[SIP%]]<0,"EXIT","SIP")) -> 191 ,Qnt: -21 | N25: =IF(AllocationTable[[#This Row],[SIP%]]>0,_xlfn.CEILING.MATH(AllocationTable[[#This Row],[High]]-(AllocationTable[[#This Row],[High]]*3*AllocationTable[[#This Row],[SIP%]]%))&" ,Qnt: " &(_xlfn.CEILING.MATH((AllocationTable[[#This Row],[Available Quota]]*56%)/AllocationTable[[#This Row],[LTP]])),IF(AllocationTable[[#This Row],[SIP%]]<0,"EXIT","SIP")) -> 178 ,Qnt: -39 | O25: =AllocationTable[[#This Row],[CURRENT VALUE]]-AllocationTable[[#This Row],[AA]] -> 15493.8 | P25: =IFERROR(AllocationTable[[#This Row],[PROFIT]]/AllocationTable[[#This Row],[AA]],0) -> 0.51816476 | Q25: =AllocationTable[[#This Row],[QNT]]*AllocationTable[[#This Row],[LTP]] -> 45395.1 | R25: 20092.8 | T25: 0.9 | U25: =IF(AllocationTable[[#This Row],[TYPE]]="Stocks",IF(AllocationTable[[#This Row],[Term]]="Long Term",LongTermQuota*AllocationTable[[#This Row],[EA%]]%,SwingTradeQuota*AllocationTable[[#This Row],[EA%]]%),AllocationTable[[#This Row],[Till 2025]]+(TotalMonth*AllocationTable[[#This Row],[ESIP]])) -> 17244.883 | V25: =AllocationTable[[#This Row],[AA]]/AllocationTable[[#Totals],[AA]] -> 0.0034614025 | W25: =AllocationTable[[#This Row],[QNT]]*AllocationTable[[#This Row],[AVG.]] -> 29901.3 | X25: 6 | Y25: Tier 4
A26: ATHERENERG | B26: AUTO ANCILLARY | C26: Stocks | D26: Long Term | E26: =_xlfn.IFNA(VLOOKUP(AllocationTable[[#This Row],[TRADE]],LatestDump!A:H,2,FALSE),0) + (_xlfn.IFNA(VLOOKUP(AllocationTable[[#This Row],[TRADE]],LongTerm!A:D,4,0),0)) -> 101 | F26: =IFERROR( ( _xlfn.IFNA(VLOOKUP(AllocationTable[[#This Row],[TRADE]],LatestDump!A:H,5,FALSE),0) + _xlfn.IFNA(VLOOKUP(AllocationTable[[#This Row],[TRADE]],AllocationTable9[[TRADE]:[AA]],14,0),0) ) / AllocationTable[[#This Row],[QNT]], 0) -> 319.9604 | G26: =_xlfn.IFNA(ROUND(VLOOKUP(AllocationTable[[#This Row],[TRADE]],LatestDump!A:H,4,FALSE),2),0) -> 863.45 | H26: 790 | I26: =AllocationTable[[#This Row],[EA]]-AllocationTable[[#This Row],[AA]] -> 63488.905 | J26: =IF(AllocationTable[[#This Row],[Term]]="Trading",IF(AllocationTable[[#This Row],[PROFIT%]]>AllocationTable[[#This Row],[Final Target %]]%,"Book Profit",IF(AllocationTable[[#This Row],[PROFIT%]]>AllocationTable[[#This Row],[Partial Profit %]]%,"Book Partial Profit",IF(AllocationTable[[#This Row],[PROFIT%]]<=AllocationTable[[#This Row],[Stop Loss %]]%,"Book Loss",IF(AllocationTable[[#This Row],[Available Quota]]>AllocationTable[[#This Row],[LTP]],"TOP UP","HOLD")))),IF(AllocationTable[[#This Row],[Available Quota]]>AllocationTable[[#This Row],[LTP]],"TOP UP","HOLD")) -> TOP UP | L26: =IF(AllocationTable[[#This Row],[SIP%]]>0,_xlfn.CEILING.MATH(AllocationTable[[#This Row],[High]]-(AllocationTable[[#This Row],[High]]*AllocationTable[[#This Row],[SIP%]]%))&" ,Qnt: " &(_xlfn.CEILING.MATH((AllocationTable[[#This Row],[Available Quota]]*14%)/AllocationTable[[#This Row],[LTP]])),IF(AllocationTable[[#This Row],[SIP%]]<0,"EXIT","SIP")) -> 711 ,Qnt: 11 | M26: =IF(AllocationTable[[#This Row],[SIP%]]>0,_xlfn.CEILING.MATH(AllocationTable[[#This Row],[High]]-(AllocationTable[[#This Row],[High]]*2*AllocationTable[[#This Row],[SIP%]]%))&" ,Qnt: " &(_xlfn.CEILING.MATH((AllocationTable[[#This Row],[Available Quota]]*30%)/AllocationTable[[#This Row],[LTP]])),IF(AllocationTable[[#This Row],[SIP%]]<0,"EXIT","SIP")) -> 632 ,Qnt: 23 | N26: =IF(AllocationTable[[#This Row],[SIP%]]>0,_xlfn.CEILING.MATH(AllocationTable[[#This Row],[High]]-(AllocationTable[[#This Row],[High]]*3*AllocationTable[[#This Row],[SIP%]]%))&" ,Qnt: " &(_xlfn.CEILING.MATH((AllocationTable[[#This Row],[Available Quota]]*56%)/AllocationTable[[#This Row],[LTP]])),IF(AllocationTable[[#This Row],[SIP%]]<0,"EXIT","SIP")) -> 553 ,Qnt: 42 | O26: =AllocationTable[[#This Row],[CURRENT VALUE]]-AllocationTable[[#This Row],[AA]] -> 54892.45 | P26: =IFERROR(AllocationTable[[#This Row],[PROFIT]]/AllocationTable[[#This Row],[AA]],0) -> 1.6986152 | Q26: =AllocationTable[[#This Row],[QNT]]*AllocationTable[[#This Row],[LTP]] -> 87208.45 | R26: 33386.96 | T26: 5 | U26: =IF(AllocationTable[[#This Row],[TYPE]]="Stocks",IF(AllocationTable[[#This Row],[Term]]="Long Term",LongTermQuota*AllocationTable[[#This Row],[EA%]]%,SwingTradeQuota*AllocationTable[[#This Row],[EA%]]%),AllocationTable[[#This Row],[Till 2025]]+(TotalMonth*AllocationTable[[#This Row],[ESIP]])) -> 95804.905 | V26: =AllocationTable[[#This Row],[AA]]/AllocationTable[[#Totals],[AA]] -> 0.0037409304 | W26: =AllocationTable[[#This Row],[QNT]]*AllocationTable[[#This Row],[AVG.]] -> 32316 | X26: 10 | Y26: Tier 1
A27: BELRISE | B27: AUTO ANCILLARY | C27: Stocks | D27: EXIT | E27: =_xlfn.IFNA(VLOOKUP(AllocationTable[[#This Row],[TRADE]],LatestDump!A:H,2,FALSE),0) + (_xlfn.IFNA(VLOOKUP(AllocationTable[[#This Row],[TRADE]],LongTerm!A:D,4,0),0)) -> 200 | F27: =IFERROR( ( _xlfn.IFNA(VLOOKUP(AllocationTable[[#This Row],[TRADE]],LatestDump!A:H,5,FALSE),0) + _xlfn.IFNA(VLOOKUP(AllocationTable[[#This Row],[TRADE]],AllocationTable9[[TRADE]:[AA]],14,0),0) ) / AllocationTable[[#This Row],[QNT]], 0) -> 161.0403 | G27: =_xlfn.IFNA(ROUND(VLOOKUP(AllocationTable[[#This Row],[TRADE]],LatestDump!A:H,4,FALSE),2),0) -> 206.25 | H27: 194 | I27: =AllocationTable[[#This Row],[EA]]-AllocationTable[[#This Row],[AA]] -> -32208.06 | J27: =IF(AllocationTable[[#This Row],[Term]]="Trading",IF(AllocationTable[[#This Row],[PROFIT%]]>AllocationTable[[#This Row],[Final Target %]]%,"Book Profit",IF(AllocationTable[[#This Row],[PROFIT%]]>AllocationTable[[#This Row],[Partial Profit %]]%,"Book Partial Profit",IF(AllocationTable[[#This Row],[PROFIT%]]<=AllocationTable[[#This Row],[Stop Loss %]]%,"Book Loss",IF(AllocationTable[[#This Row],[Available Quota]]>AllocationTable[[#This Row],[LTP]],"TOP UP","HOLD")))),IF(AllocationTable[[#This Row],[Available Quota]]>AllocationTable[[#This Row],[LTP]],"TOP UP","HOLD")) -> HOLD | L27: =IF(AllocationTable[[#This Row],[SIP%]]>0,_xlfn.CEILING.MATH(AllocationTable[[#This Row],[High]]-(AllocationTable[[#This Row],[High]]*AllocationTable[[#This Row],[SIP%]]%))&" ,Qnt: " &(_xlfn.CEILING.MATH((AllocationTable[[#This Row],[Available Quota]]*14%)/AllocationTable[[#This Row],[LTP]])),IF(AllocationTable[[#This Row],[SIP%]]<0,"EXIT","SIP")) -> EXIT | M27: =IF(AllocationTable[[#This Row],[SIP%]]>0,_xlfn.CEILING.MATH(AllocationTable[[#This Row],[High]]-(AllocationTable[[#This Row],[High]]*2*AllocationTable[[#This Row],[SIP%]]%))&" ,Qnt: " &(_xlfn.CEILING.MATH((AllocationTable[[#This Row],[Available Quota]]*30%)/AllocationTable[[#This Row],[LTP]])),IF(AllocationTable[[#This Row],[SIP%]]<0,"EXIT","SIP")) -> EXIT | N27: =IF(AllocationTable[[#This Row],[SIP%]]>0,_xlfn.CEILING.MATH(AllocationTable[[#This Row],[High]]-(AllocationTable[[#This Row],[High]]*3*AllocationTable[[#This Row],[SIP%]]%))&" ,Qnt: " &(_xlfn.CEILING.MATH((AllocationTable[[#This Row],[Available Quota]]*56%)/AllocationTable[[#This Row],[LTP]])),IF(AllocationTable[[#This Row],[SIP%]]<0,"EXIT","SIP")) -> EXIT | O27: =AllocationTable[[#This Row],[CURRENT VALUE]]-AllocationTable[[#This Row],[AA]] -> 9041.94 | P27: =IFERROR(AllocationTable[[#This Row],[PROFIT]]/AllocationTable[[#This Row],[AA]],0) -> 0.28073532 | Q27: =AllocationTable[[#This Row],[QNT]]*AllocationTable[[#This Row],[LTP]] -> 41250 | R27: 31208.59 | T27: 0 | U27: =IF(AllocationTable[[#This Row],[TYPE]]="Stocks",IF(AllocationTable[[#This Row],[Term]]="Long Term",LongTermQuota*AllocationTable[[#This Row],[EA%]]%,SwingTradeQuota*AllocationTable[[#This Row],[EA%]]%),AllocationTable[[#This Row],[Till 2025]]+(TotalMonth*AllocationTable[[#This Row],[ESIP]])) -> 0 | V27: =AllocationTable[[#This Row],[AA]]/AllocationTable[[#Totals],[AA]] -> 0.0037284352 | W27: =AllocationTable[[#This Row],[QNT]]*AllocationTable[[#This Row],[AVG.]] -> 32208.06 | X27: -1 | Y27: - | Z27: 0 | AA27: 0 | AB27: 0 | AC27: 0 | AD27: 0
A28: BHARATFORG | B28: AUTO ANCILLARY | C28: Stocks | D28: Trading | E28: =_xlfn.IFNA(VLOOKUP(AllocationTable[[#This Row],[TRADE]],LatestDump!A:H,2,FALSE),0) + (_xlfn.IFNA(VLOOKUP(AllocationTable[[#This Row],[TRADE]],LongTerm!A:D,4,0),0)) -> 6 | F28: =IFERROR( ( _xlfn.IFNA(VLOOKUP(AllocationTable[[#This Row],[TRADE]],LatestDump!A:H,5,FALSE),0) + _xlfn.IFNA(VLOOKUP(AllocationTable[[#This Row],[TRADE]],AllocationTable9[[TRADE]:[AA]],14,0),0) ) / AllocationTable[[#This Row],[QNT]], 0) -> 1827.5833 | G28: =_xlfn.IFNA(ROUND(VLOOKUP(AllocationTable[[#This Row],[TRADE]],LatestDump!A:H,4,FALSE),2),0) -> 1798.8 | H28: 1930 | I28: =AllocationTable[[#This Row],[EA]]-AllocationTable[[#This Row],[AA]] -> -2753.651 | J28: =IF(AllocationTable[[#This Row],[Term]]="Trading",IF(AllocationTable[[#This Row],[PROFIT%]]>AllocationTable[[#This Row],[Final Target %]]%,"Book Profit",IF(AllocationTable[[#This Row],[PROFIT%]]>AllocationTable[[#This Row],[Partial Profit %]]%,"Book Partial Profit",IF(AllocationTable[[#This Row],[PROFIT%]]<=AllocationTable[[#This Row],[Stop Loss %]]%,"Book Loss",IF(AllocationTable[[#This Row],[Available Quota]]>AllocationTable[[#This Row],[LTP]],"TOP UP","HOLD")))),IF(AllocationTable[[#This Row],[Available Quota]]>AllocationTable[[#This Row],[LTP]],"TOP UP","HOLD")) -> Book Loss | L28: =IF(AllocationTable[[#This Row],[SIP%]]>0,_xlfn.CEILING.MATH(AllocationTable[[#This Row],[High]]-(AllocationTable[[#This Row],[High]]*AllocationTable[[#This Row],[SIP%]]%))&" ,Qnt: " &(_xlfn.CEILING.MATH((AllocationTable[[#This Row],[Available Quota]]*14%)/AllocationTable[[#This Row],[LTP]])),IF(AllocationTable[[#This Row],[SIP%]]<0,"EXIT","SIP")) -> SIP | M28: =IF(AllocationTable[[#This Row],[SIP%]]>0,_xlfn.CEILING.MATH(AllocationTable[[#This Row],[High]]-(AllocationTable[[#This Row],[High]]*2*AllocationTable[[#This Row],[SIP%]]%))&" ,Qnt: " &(_xlfn.CEILING.MATH((AllocationTable[[#This Row],[Available Quota]]*30%)/AllocationTable[[#This Row],[LTP]])),IF(AllocationTable[[#This Row],[SIP%]]<0,"EXIT","SIP")) -> SIP | N28: =IF(AllocationTable[[#This Row],[SIP%]]>0,_xlfn.CEILING.MATH(AllocationTable[[#This Row],[High]]-(AllocationTable[[#This Row],[High]]*3*AllocationTable[[#This Row],[SIP%]]%))&" ,Qnt: " &(_xlfn.CEILING.MATH((AllocationTable[[#This Row],[Available Quota]]*56%)/AllocationTable[[#This Row],[LTP]])),IF(AllocationTable[[#This Row],[SIP%]]<0,"EXIT","SIP")) -> SIP | O28: =AllocationTable[[#This Row],[CURRENT VALUE]]-AllocationTable[[#This Row],[AA]] -> -172.7 | P28: =IFERROR(AllocationTable[[#This Row],[PROFIT]]/AllocationTable[[#This Row],[AA]],0) -> -0.015749396 | Q28: =AllocationTable[[#This Row],[QNT]]*AllocationTable[[#This Row],[LTP]] -> 10792.8 | T28: 1 | U28: =IF(AllocationTable[[#This Row],[TYPE]]="Stocks",IF(AllocationTable[[#This Row],[Term]]="Long Term",LongTermQuota*AllocationTable[[#This Row],[EA%]]%,SwingTradeQuota*AllocationTable[[#This Row],[EA%]]%),AllocationTable[[#This Row],[Till 2025]]+(TotalMonth*AllocationTable[[#This Row],[ESIP]])) -> 8211.849 | V28: =AllocationTable[[#This Row],[AA]]/AllocationTable[[#Totals],[AA]] -> 0.0012693766 | W28: =AllocationTable[[#This Row],[QNT]]*AllocationTable[[#This Row],[AVG.]] -> 10965.5
A29: CRAFTSMAN | B29: AUTO ANCILLARY | C29: Stocks | D29: Trading | E29: =_xlfn.IFNA(VLOOKUP(AllocationTable[[#This Row],[TRADE]],LatestDump!A:H,2,FALSE),0) + (_xlfn.IFNA(VLOOKUP(AllocationTable[[#This Row],[TRADE]],LongTerm!A:D,4,0),0)) -> 3 | F29: =IFERROR( ( _xlfn.IFNA(VLOOKUP(AllocationTable[[#This Row],[TRADE]],LatestDump!A:H,5,FALSE),0) + _xlfn.IFNA(VLOOKUP(AllocationTable[[#This Row],[TRADE]],AllocationTable9[[TRADE]:[AA]],14,0),0) ) / AllocationTable[[#This Row],[QNT]], 0) -> 7086.6667 | G29: =_xlfn.IFNA(ROUND(VLOOKUP(AllocationTable[[#This Row],[TRADE]],LatestDump!A:H,4,FALSE),2),0) -> 7430 | H29: 8220 | I29: =AllocationTable[[#This Row],[EA]]-AllocationTable[[#This Row],[AA]] -> -21260 | J29: =IF(AllocationTable[[#This Row],[Term]]="Trading",IF(AllocationTable[[#This Row],[PROFIT%]]>AllocationTable[[#This Row],[Final Target %]]%,"Book Profit",IF(AllocationTable[[#This Row],[PROFIT%]]>AllocationTable[[#This Row],[Partial Profit %]]%,"Book Partial Profit",IF(AllocationTable[[#This Row],[PROFIT%]]<=AllocationTable[[#This Row],[Stop Loss %]]%,"Book Loss",IF(AllocationTable[[#This Row],[Available Quota]]>AllocationTable[[#This Row],[LTP]],"TOP UP","HOLD")))),IF(AllocationTable[[#This Row],[Available Quota]]>AllocationTable[[#This Row],[LTP]],"TOP UP","HOLD")) -> Book Profit | L29: =IF(AllocationTable[[#This Row],[SIP%]]>0,_xlfn.CEILING.MATH(AllocationTable[[#This Row],[High]]-(AllocationTable[[#This Row],[High]]*AllocationTable[[#This Row],[SIP%]]%))&" ,Qnt: " &(_xlfn.CEILING.MATH((AllocationTable[[#This Row],[Available Quota]]*14%)/AllocationTable[[#This Row],[LTP]])),IF(AllocationTable[[#This Row],[SIP%]]<0,"EXIT","SIP")) -> SIP | M29: =IF(AllocationTable[[#This Row],[SIP%]]>0,_xlfn.CEILING.MATH(AllocationTable[[#This Row],[High]]-(AllocationTable[[#This Row],[High]]*2*AllocationTable[[#This Row],[SIP%]]%))&" ,Qnt: " &(_xlfn.CEILING.MATH((AllocationTable[[#This Row],[Available Quota]]*30%)/AllocationTable[[#This Row],[LTP]])),IF(AllocationTable[[#This Row],[SIP%]]<0,"EXIT","SIP")) -> SIP | N29: =IF(AllocationTable[[#This Row],[SIP%]]>0,_xlfn.CEILING.MATH(AllocationTable[[#This Row],[High]]-(AllocationTable[[#This Row],[High]]*3*AllocationTable[[#This Row],[SIP%]]%))&" ,Qnt: " &(_xlfn.CEILING.MATH((AllocationTable[[#This Row],[Available Quota]]*56%)/AllocationTable[[#This Row],[LTP]])),IF(AllocationTable[[#This Row],[SIP%]]<0,"EXIT","SIP")) -> SIP | O29: =AllocationTable[[#This Row],[CURRENT VALUE]]-AllocationTable[[#This Row],[AA]] -> 1030 | P29: =IFERROR(AllocationTable[[#This Row],[PROFIT]]/AllocationTable[[#This Row],[AA]],0) -> 0.048447789 | Q29: =AllocationTable[[#This Row],[QNT]]*AllocationTable[[#This Row],[LTP]] -> 22290 | U29: =IF(AllocationTable[[#This Row],[TYPE]]="Stocks",IF(AllocationTable[[#This Row],[Term]]="Long Term",LongTermQuota*AllocationTable[[#This Row],[EA%]]%,SwingTradeQuota*AllocationTable[[#This Row],[EA%]]%),AllocationTable[[#This Row],[Till 2025]]+(TotalMonth*AllocationTable[[#This Row],[ESIP]])) -> 0 | V29: =AllocationTable[[#This Row],[AA]]/AllocationTable[[#Totals],[AA]] -> 0.0024610775 | W29: =AllocationTable[[#This Row],[QNT]]*AllocationTable[[#This Row],[AVG.]] -> 21260
A30: HBLENGINE | B30: AUTO ANCILLARY | C30: Stocks | D30: Long Term | E30: =_xlfn.IFNA(VLOOKUP(AllocationTable[[#This Row],[TRADE]],LatestDump!A:H,2,FALSE),0) + (_xlfn.IFNA(VLOOKUP(AllocationTable[[#This Row],[TRADE]],LongTerm!A:D,4,0),0)) -> 360 | F30: =IFERROR( ( _xlfn.IFNA(VLOOKUP(AllocationTable[[#This Row],[TRADE]],LatestDump!A:H,5,FALSE),0) + _xlfn.IFNA(VLOOKUP(AllocationTable[[#This Row],[TRADE]],AllocationTable9[[TRADE]:[AA]],14,0),0) ) / AllocationTable[[#This Row],[QNT]], 0) -> 461.41667 | G30: =_xlfn.IFNA(ROUND(VLOOKUP(AllocationTable[[#This Row],[TRADE]],LatestDump!A:H,4,FALSE),2),0) -> 730.65 | H30: 1125 | I30: =AllocationTable[[#This Row],[EA]]-AllocationTable[[#This Row],[AA]] -> -31983.133 | J30: =IF(AllocationTable[[#This Row],[Term]]="Trading",IF(AllocationTable[[#This Row],[PROFIT%]]>AllocationTable[[#This Row],[Final Target %]]%,"Book Profit",IF(AllocationTable[[#This Row],[PROFIT%]]>AllocationTable[[#This Row],[Partial Profit %]]%,"Book Partial Profit",IF(AllocationTable[[#This Row],[PROFIT%]]<=AllocationTable[[#This Row],[Stop Loss %]]%,"Book Loss",IF(AllocationTable[[#This Row],[Available Quota]]>AllocationTable[[#This Row],[LTP]],"TOP UP","HOLD")))),IF(AllocationTable[[#This Row],[Available Quota]]>AllocationTable[[#This Row],[LTP]],"TOP UP","HOLD")) -> HOLD | L30: =IF(AllocationTable[[#This Row],[SIP%]]>0,_xlfn.CEILING.MATH(AllocationTable[[#This Row],[High]]-(AllocationTable[[#This Row],[High]]*AllocationTable[[#This Row],[SIP%]]%))&" ,Qnt: " &(_xlfn.CEILING.MATH((AllocationTable[[#This Row],[Available Quota]]*14%)/AllocationTable[[#This Row],[LTP]])),IF(AllocationTable[[#This Row],[SIP%]]<0,"EXIT","SIP")) -> 1013 ,Qnt: -6 | M30: =IF(AllocationTable[[#This Row],[SIP%]]>0,_xlfn.CEILING.MATH(AllocationTable[[#This Row],[High]]-(AllocationTable[[#This Row],[High]]*2*AllocationTable[[#This Row],[SIP%]]%))&" ,Qnt: " &(_xlfn.CEILING.MATH((AllocationTable[[#This Row],[Available Quota]]*30%)/AllocationTable[[#This Row],[LTP]])),IF(AllocationTable[[#This Row],[SIP%]]<0,"EXIT","SIP")) -> 900 ,Qnt: -13 | N30: =IF(AllocationTable[[#This Row],[SIP%]]>0,_xlfn.CEILING.MATH(AllocationTable[[#This Row],[High]]-(AllocationTable[[#This Row],[High]]*3*AllocationTable[[#This Row],[SIP%]]%))&" ,Qnt: " &(_xlfn.CEILING.MATH((AllocationTable[[#This Row],[Available Quota]]*56%)/AllocationTable[[#This Row],[LTP]])),IF(AllocationTable[[#This Row],[SIP%]]<0,"EXIT","SIP")) -> 788 ,Qnt: -24 | O30: =AllocationTable[[#This Row],[CURRENT VALUE]]-AllocationTable[[#This Row],[AA]] -> 96924 | P30: =IFERROR(AllocationTable[[#This Row],[PROFIT]]/AllocationTable[[#This Row],[AA]],0) -> 0.58349287 | Q30: =AllocationTable[[#This Row],[QNT]]*AllocationTable[[#This Row],[LTP]] -> 263034 | R30: 219001.5 | T30: 7 | U30: =IF(AllocationTable[[#This Row],[TYPE]]="Stocks",IF(AllocationTable[[#This Row],[Term]]="Long Term",LongTermQuota*AllocationTable[[#This Row],[EA%]]%,SwingTradeQuota*AllocationTable[[#This Row],[EA%]]%),AllocationTable[[#This Row],[Till 2025]]+(TotalMonth*AllocationTable[[#This Row],[ESIP]])) -> 134126.87 | V30: =AllocationTable[[#This Row],[AA]]/AllocationTable[[#Totals],[AA]] -> 0.019229049 | W30: =AllocationTable[[#This Row],[QNT]]*AllocationTable[[#This Row],[AVG.]] -> 166110 | X30: 10 | Y30: Tier 1
A31: HEROMOTOCO | B31: AUTO ANCILLARY | C31: Stocks | D31: Long Term | E31: =_xlfn.IFNA(VLOOKUP(AllocationTable[[#This Row],[TRADE]],LatestDump!A:H,2,FALSE),0) + (_xlfn.IFNA(VLOOKUP(AllocationTable[[#This Row],[TRADE]],LongTerm!A:D,4,0),0)) -> 10 | F31: =IFERROR( ( _xlfn.IFNA(VLOOKUP(AllocationTable[[#This Row],[TRADE]],LatestDump!A:H,5,FALSE),0) + _xlfn.IFNA(VLOOKUP(AllocationTable[[#This Row],[TRADE]],AllocationTable9[[TRADE]:[AA]],14,0),0) ) / AllocationTable[[#This Row],[QNT]], 0) -> 4546.37 | G31: =_xlfn.IFNA(ROUND(VLOOKUP(AllocationTable[[#This Row],[TRADE]],LatestDump!A:H,4,FALSE),2),0) -> 5468.45 | H31: 6400 | I31: =AllocationTable[[#This Row],[EA]]-AllocationTable[[#This Row],[AA]] -> -28218.817 | J31: =IF(AllocationTable[[#This Row],[Term]]="Trading",IF(AllocationTable[[#This Row],[PROFIT%]]>AllocationTable[[#This Row],[Final Target %]]%,"Book Profit",IF(AllocationTable[[#This Row],[PROFIT%]]>AllocationTable[[#This Row],[Partial Profit %]]%,"Book Partial Profit",IF(AllocationTable[[#This Row],[PROFIT%]]<=AllocationTable[[#This Row],[Stop Loss %]]%,"Book Loss",IF(AllocationTable[[#This Row],[Available Quota]]>AllocationTable[[#This Row],[LTP]],"TOP UP","HOLD")))),IF(AllocationTable[[#This Row],[Available Quota]]>AllocationTable[[#This Row],[LTP]],"TOP UP","HOLD")) -> HOLD | L31: =IF(AllocationTable[[#This Row],[SIP%]]>0,_xlfn.CEILING.MATH(AllocationTable[[#This Row],[High]]-(AllocationTable[[#This Row],[High]]*AllocationTable[[#This Row],[SIP%]]%))&" ,Qnt: " &(_xlfn.CEILING.MATH((AllocationTable[[#This Row],[Available Quota]]*14%)/AllocationTable[[#This Row],[LTP]])),IF(AllocationTable[[#This Row],[SIP%]]<0,"EXIT","SIP")) -> 6016 ,Qnt: 0 | M31: =IF(AllocationTable[[#This Row],[SIP%]]>0,_xlfn.CEILING.MATH(AllocationTable[[#This Row],[High]]-(AllocationTable[[#This Row],[High]]*2*AllocationTable[[#This Row],[SIP%]]%))&" ,Qnt: " &(_xlfn.CEILING.MATH((AllocationTable[[#This Row],[Available Quota]]*30%)/AllocationTable[[#This Row],[LTP]])),IF(AllocationTable[[#This Row],[SIP%]]<0,"EXIT","SIP")) -> 5632 ,Qnt: -1 | N31: =IF(AllocationTable[[#This Row],[SIP%]]>0,_xlfn.CEILING.MATH(AllocationTable[[#This Row],[High]]-(AllocationTable[[#This Row],[High]]*3*AllocationTable[[#This Row],[SIP%]]%))&" ,Qnt: " &(_xlfn.CEILING.MATH((AllocationTable[[#This Row],[Available Quota]]*56%)/AllocationTable[[#This Row],[LTP]])),IF(AllocationTable[[#This Row],[SIP%]]<0,"EXIT","SIP")) -> 5248 ,Qnt: -2 | O31: =AllocationTable[[#This Row],[CURRENT VALUE]]-AllocationTable[[#This Row],[AA]] -> 9220.8 | P31: =IFERROR(AllocationTable[[#This Row],[PROFIT]]/AllocationTable[[#This Row],[AA]],0) -> 0.20281675 | Q31: =AllocationTable[[#This Row],[QNT]]*AllocationTable[[#This Row],[LTP]] -> 54684.5 | R31: 34193.7 | T31: 0.9 | U31: =IF(AllocationTable[[#This Row],[TYPE]]="Stocks",IF(AllocationTable[[#This Row],[Term]]="Long Term",LongTermQuota*AllocationTable[[#This Row],[EA%]]%,SwingTradeQuota*AllocationTable[[#This Row],[EA%]]%),AllocationTable[[#This Row],[Till 2025]]+(TotalMonth*AllocationTable[[#This Row],[ESIP]])) -> 17244.883 | V31: =AllocationTable[[#This Row],[AA]]/AllocationTable[[#Totals],[AA]] -> 0.0052629205 | W31: =AllocationTable[[#This Row],[QNT]]*AllocationTable[[#This Row],[AVG.]] -> 45463.7 | X31: 6 | Y31: Tier 4
A32: M&M | B32: AUTO ANCILLARY | C32: Stocks | D32: Long Term | E32: =_xlfn.IFNA(VLOOKUP(AllocationTable[[#This Row],[TRADE]],LatestDump!A:H,2,FALSE),0) + (_xlfn.IFNA(VLOOKUP(AllocationTable[[#This Row],[TRADE]],LongTerm!A:D,4,0),0)) -> 28 | F32: =IFERROR( ( _xlfn.IFNA(VLOOKUP(AllocationTable[[#This Row],[TRADE]],LatestDump!A:H,5,FALSE),0) + _xlfn.IFNA(VLOOKUP(AllocationTable[[#This Row],[TRADE]],AllocationTable9[[TRADE]:[AA]],14,0),0) ) / AllocationTable[[#This Row],[QNT]], 0) -> 2281.6393 | G32: =_xlfn.IFNA(ROUND(VLOOKUP(AllocationTable[[#This Row],[TRADE]],LatestDump!A:H,4,FALSE),2),0) -> 3261.8 | H32: 3840 | I32: =AllocationTable[[#This Row],[EA]]-AllocationTable[[#This Row],[AA]] -> -40892.723 | J32: =IF(AllocationTable[[#This Row],[Term]]="Trading",IF(AllocationTable[[#This Row],[PROFIT%]]>AllocationTable[[#This Row],[Final Target %]]%,"Book Profit",IF(AllocationTable[[#This Row],[PROFIT%]]>AllocationTable[[#This Row],[Partial Profit %]]%,"Book Partial Profit",IF(AllocationTable[[#This Row],[PROFIT%]]<=AllocationTable[[#This Row],[Stop Loss %]]%,"Book Loss",IF(AllocationTable[[#This Row],[Available Quota]]>AllocationTable[[#This Row],[LTP]],"TOP UP","HOLD")))),IF(AllocationTable[[#This Row],[Available Quota]]>AllocationTable[[#This Row],[LTP]],"TOP UP","HOLD")) -> HOLD | L32: =IF(AllocationTable[[#This Row],[SIP%]]>0,_xlfn.CEILING.MATH(AllocationTable[[#This Row],[High]]-(AllocationTable[[#This Row],[High]]*AllocationTable[[#This Row],[SIP%]]%))&" ,Qnt: " &(_xlfn.CEILING.MATH((AllocationTable[[#This Row],[Available Quota]]*14%)/AllocationTable[[#This Row],[LTP]])),IF(AllocationTable[[#This Row],[SIP%]]<0,"EXIT","SIP")) -> 3648 ,Qnt: -1 | M32: =IF(AllocationTable[[#This Row],[SIP%]]>0,_xlfn.CEILING.MATH(AllocationTable[[#This Row],[High]]-(AllocationTable[[#This Row],[High]]*2*AllocationTable[[#This Row],[SIP%]]%))&" ,Qnt: " &(_xlfn.CEILING.MATH((AllocationTable[[#This Row],[Available Quota]]*30%)/AllocationTable[[#This Row],[LTP]])),IF(AllocationTable[[#This Row],[SIP%]]<0,"EXIT","SIP")) -> 3456 ,Qnt: -3 | N32: =IF(AllocationTable[[#This Row],[SIP%]]>0,_xlfn.CEILING.MATH(AllocationTable[[#This Row],[High]]-(AllocationTable[[#This Row],[High]]*3*AllocationTable[[#This Row],[SIP%]]%))&" ,Qnt: " &(_xlfn.CEILING.MATH((AllocationTable[[#This Row],[Available Quota]]*56%)/AllocationTable[[#This Row],[LTP]])),IF(AllocationTable[[#This Row],[SIP%]]<0,"EXIT","SIP")) -> 3264 ,Qnt: -7 | O32: =AllocationTable[[#This Row],[CURRENT VALUE]]-AllocationTable[[#This Row],[AA]] -> 27444.5 | P32: =IFERROR(AllocationTable[[#This Row],[PROFIT]]/AllocationTable[[#This Row],[AA]],0) -> 0.42958618 | Q32: =AllocationTable[[#This Row],[QNT]]*AllocationTable[[#This Row],[LTP]] -> 91330.4 | R32: 44495.6 | T32: 1.2 | U32: =IF(AllocationTable[[#This Row],[TYPE]]="Stocks",IF(AllocationTable[[#This Row],[Term]]="Long Term",LongTermQuota*AllocationTable[[#This Row],[EA%]]%,SwingTradeQuota*AllocationTable[[#This Row],[EA%]]%),AllocationTable[[#This Row],[Till 2025]]+(TotalMonth*AllocationTable[[#This Row],[ESIP]])) -> 22993.177 | V32: =AllocationTable[[#This Row],[AA]]/AllocationTable[[#Totals],[AA]] -> 0.0073954917 | W32: =AllocationTable[[#This Row],[QNT]]*AllocationTable[[#This Row],[AVG.]] -> 63885.9 | X32: 5 | Y32: Tier 4
A33: MOTHERSON | B33: AUTO ANCILLARY | C33: Stocks | D33: Trading | E33: =_xlfn.IFNA(VLOOKUP(AllocationTable[[#This Row],[TRADE]],LatestDump!A:H,2,FALSE),0) + (_xlfn.IFNA(VLOOKUP(AllocationTable[[#This Row],[TRADE]],LongTerm!A:D,4,0),0)) -> 301 | F33: =IFERROR( ( _xlfn.IFNA(VLOOKUP(AllocationTable[[#This Row],[TRADE]],LatestDump!A:H,5,FALSE),0) + _xlfn.IFNA(VLOOKUP(AllocationTable[[#This Row],[TRADE]],AllocationTable9[[TRADE]:[AA]],14,0),0) ) / AllocationTable[[#This Row],[QNT]], 0) -> 120.36289 | G33: =_xlfn.IFNA(ROUND(VLOOKUP(AllocationTable[[#This Row],[TRADE]],LatestDump!A:H,4,FALSE),2),0) -> 122.16 | H33: 136 | I33: =AllocationTable[[#This Row],[EA]]-AllocationTable[[#This Row],[AA]] -> -36229.23 | J33: =IF(AllocationTable[[#This Row],[Term]]="Trading",IF(AllocationTable[[#This Row],[PROFIT%]]>AllocationTable[[#This Row],[Final Target %]]%,"Book Profit",IF(AllocationTable[[#This Row],[PROFIT%]]>AllocationTable[[#This Row],[Partial Profit %]]%,"Book Partial Profit",IF(AllocationTable[[#This Row],[PROFIT%]]<=AllocationTable[[#This Row],[Stop Loss %]]%,"Book Loss",IF(AllocationTable[[#This Row],[Available Quota]]>AllocationTable[[#This Row],[LTP]],"TOP UP","HOLD")))),IF(AllocationTable[[#This Row],[Available Quota]]>AllocationTable[[#This Row],[LTP]],"TOP UP","HOLD")) -> Book Profit | L33: =IF(AllocationTable[[#This Row],[SIP%]]>0,_xlfn.CEILING.MATH(AllocationTable[[#This Row],[High]]-(AllocationTable[[#This Row],[High]]*AllocationTable[[#This Row],[SIP%]]%))&" ,Qnt: " &(_xlfn.CEILING.MATH((AllocationTable[[#This Row],[Available Quota]]*14%)/AllocationTable[[#This Row],[LTP]])),IF(AllocationTable[[#This Row],[SIP%]]<0,"EXIT","SIP")) -> SIP | M33: =IF(AllocationTable[[#This Row],[SIP%]]>0,_xlfn.CEILING.MATH(AllocationTable[[#This Row],[High]]-(AllocationTable[[#This Row],[High]]*2*AllocationTable[[#This Row],[SIP%]]%))&" ,Qnt: " &(_xlfn.CEILING.MATH((AllocationTable[[#This Row],[Available Quota]]*30%)/AllocationTable[[#This Row],[LTP]])),IF(AllocationTable[[#This Row],[SIP%]]<0,"EXIT","SIP")) -> SIP | N33: =IF(AllocationTable[[#This Row],[SIP%]]>0,_xlfn.CEILING.MATH(AllocationTable[[#This Row],[High]]-(AllocationTable[[#This Row],[High]]*3*AllocationTable[[#This Row],[SIP%]]%))&" ,Qnt: " &(_xlfn.CEILING.MATH((AllocationTable[[#This Row],[Available Quota]]*56%)/AllocationTable[[#This Row],[LTP]])),IF(AllocationTable[[#This Row],[SIP%]]<0,"EXIT","SIP")) -> SIP | O33: =AllocationTable[[#This Row],[CURRENT VALUE]]-AllocationTable[[#This Row],[AA]] -> 540.93 | P33: =IFERROR(AllocationTable[[#This Row],[PROFIT]]/AllocationTable[[#This Row],[AA]],0) -> 0.014930762 | Q33: =AllocationTable[[#This Row],[QNT]]*AllocationTable[[#This Row],[LTP]] -> 36770.16 | U33: =IF(AllocationTable[[#This Row],[TYPE]]="Stocks",IF(AllocationTable[[#This Row],[Term]]="Long Term",LongTermQuota*AllocationTable[[#This Row],[EA%]]%,SwingTradeQuota*AllocationTable[[#This Row],[EA%]]%),AllocationTable[[#This Row],[Till 2025]]+(TotalMonth*AllocationTable[[#This Row],[ESIP]])) -> 0 | V33: =AllocationTable[[#This Row],[AA]]/AllocationTable[[#Totals],[AA]] -> 0.0041939296 | W33: =AllocationTable[[#This Row],[QNT]]*AllocationTable[[#This Row],[AVG.]] -> 36229.23
A34: OLECTRA | B34: AUTO ANCILLARY | C34: Stocks | D34: Trading | E34: =_xlfn.IFNA(VLOOKUP(AllocationTable[[#This Row],[TRADE]],LatestDump!A:H,2,FALSE),0) + (_xlfn.IFNA(VLOOKUP(AllocationTable[[#This Row],[TRADE]],LongTerm!A:D,4,0),0)) -> 15 | F34: =IFERROR( ( _xlfn.IFNA(VLOOKUP(AllocationTable[[#This Row],[TRADE]],LatestDump!A:H,5,FALSE),0) + _xlfn.IFNA(VLOOKUP(AllocationTable[[#This Row],[TRADE]],AllocationTable9[[TRADE]:[AA]],14,0),0) ) / AllocationTable[[#This Row],[QNT]], 0) -> 914.2 | G34: =_xlfn.IFNA(ROUND(VLOOKUP(AllocationTable[[#This Row],[TRADE]],LatestDump!A:H,4,FALSE),2),0) -> 1184.25 | H34: 1715 | I34: =AllocationTable[[#This Row],[EA]]-AllocationTable[[#This Row],[AA]] -> -574.0416 | J34: =IF(AllocationTable[[#This Row],[Term]]="Trading",IF(AllocationTable[[#This Row],[PROFIT%]]>AllocationTable[[#This Row],[Final Target %]]%,"Book Profit",IF(AllocationTable[[#This Row],[PROFIT%]]>AllocationTable[[#This Row],[Partial Profit %]]%,"Book Partial Profit",IF(AllocationTable[[#This Row],[PROFIT%]]<=AllocationTable[[#This Row],[Stop Loss %]]%,"Book Loss",IF(AllocationTable[[#This Row],[Available Quota]]>AllocationTable[[#This Row],[LTP]],"TOP UP","HOLD")))),IF(AllocationTable[[#This Row],[Available Quota]]>AllocationTable[[#This Row],[LTP]],"TOP UP","HOLD")) -> Book Profit | L34: =IF(AllocationTable[[#This Row],[SIP%]]>0,_xlfn.CEILING.MATH(AllocationTable[[#This Row],[High]]-(AllocationTable[[#This Row],[High]]*AllocationTable[[#This Row],[SIP%]]%))&" ,Qnt: " &(_xlfn.CEILING.MATH((AllocationTable[[#This Row],[Available Quota]]*14%)/AllocationTable[[#This Row],[LTP]])),IF(AllocationTable[[#This Row],[SIP%]]<0,"EXIT","SIP")) -> 1544 ,Qnt: 0 | M34: =IF(AllocationTable[[#This Row],[SIP%]]>0,_xlfn.CEILING.MATH(AllocationTable[[#This Row],[High]]-(AllocationTable[[#This Row],[High]]*2*AllocationTable[[#This Row],[SIP%]]%))&" ,Qnt: " &(_xlfn.CEILING.MATH((AllocationTable[[#This Row],[Available Quota]]*30%)/AllocationTable[[#This Row],[LTP]])),IF(AllocationTable[[#This Row],[SIP%]]<0,"EXIT","SIP")) -> 1372 ,Qnt: 0 | N34: =IF(AllocationTable[[#This Row],[SIP%]]>0,_xlfn.CEILING.MATH(AllocationTable[[#This Row],[High]]-(AllocationTable[[#This Row],[High]]*3*AllocationTable[[#This Row],[SIP%]]%))&" ,Qnt: " &(_xlfn.CEILING.MATH((AllocationTable[[#This Row],[Available Quota]]*56%)/AllocationTable[[#This Row],[LTP]])),IF(AllocationTable[[#This Row],[SIP%]]<0,"EXIT","SIP")) -> 1201 ,Qnt: 0 | O34: =AllocationTable[[#This Row],[CURRENT VALUE]]-AllocationTable[[#This Row],[AA]] -> 4050.75 | P34: =IFERROR(AllocationTable[[#This Row],[PROFIT]]/AllocationTable[[#This Row],[AA]],0) -> 0.29539488 | Q34: =AllocationTable[[#This Row],[QNT]]*AllocationTable[[#This Row],[LTP]] -> 17763.75 | R34: 57586.25 | T34: 1.6 | U34: =IF(AllocationTable[[#This Row],[TYPE]]="Stocks",IF(AllocationTable[[#This Row],[Term]]="Long Term",LongTermQuota*AllocationTable[[#This Row],[EA%]]%,SwingTradeQuota*AllocationTable[[#This Row],[EA%]]%),AllocationTable[[#This Row],[Till 2025]]+(TotalMonth*AllocationTable[[#This Row],[ESIP]])) -> 13138.958 | V34: =AllocationTable[[#This Row],[AA]]/AllocationTable[[#Totals],[AA]] -> 0.0015874297 | W34: =AllocationTable[[#This Row],[QNT]]*AllocationTable[[#This Row],[AVG.]] -> 13713 | X34: 10 | Y34: Tier 1 | Z34: -12 | AA34: -12 | AB34: 15 | AC34: 25 | AD34: Trail -10% from peak after +15%
A35: SIEMENS | B35: AUTO ANCILLARY | C35: Stocks | D35: Trading | E35: =_xlfn.IFNA(VLOOKUP(AllocationTable[[#This Row],[TRADE]],LatestDump!A:H,2,FALSE),0) + (_xlfn.IFNA(VLOOKUP(AllocationTable[[#This Row],[TRADE]],LongTerm!A:D,4,0),0)) -> 2 | F35: =IFERROR( ( _xlfn.IFNA(VLOOKUP(AllocationTable[[#This Row],[TRADE]],LatestDump!A:H,5,FALSE),0) + _xlfn.IFNA(VLOOKUP(AllocationTable[[#This Row],[TRADE]],AllocationTable9[[TRADE]:[AA]],14,0),0) ) / AllocationTable[[#This Row],[QNT]], 0) -> 3320 | G35: =_xlfn.IFNA(ROUND(VLOOKUP(AllocationTable[[#This Row],[TRADE]],LatestDump!A:H,4,FALSE),2),0) -> 3390.1 | H35: 3440 | I35: =AllocationTable[[#This Row],[EA]]-AllocationTable[[#This Row],[AA]] -> -6640 | J35: =IF(AllocationTable[[#This Row],[Term]]="Trading",IF(AllocationTable[[#This Row],[PROFIT%]]>AllocationTable[[#This Row],[Final Target %]]%,"Book Profit",IF(AllocationTable[[#This Row],[PROFIT%]]>AllocationTable[[#This Row],[Partial Profit %]]%,"Book Partial Profit",IF(AllocationTable[[#This Row],[PROFIT%]]<=AllocationTable[[#This Row],[Stop Loss %]]%,"Book Loss",IF(AllocationTable[[#This Row],[Available Quota]]>AllocationTable[[#This Row],[LTP]],"TOP UP","HOLD")))),IF(AllocationTable[[#This Row],[Available Quota]]>AllocationTable[[#This Row],[LTP]],"TOP UP","HOLD")) -> Book Profit | L35: =IF(AllocationTable[[#This Row],[SIP%]]>0,_xlfn.CEILING.MATH(AllocationTable[[#This Row],[High]]-(AllocationTable[[#This Row],[High]]*AllocationTable[[#This Row],[SIP%]]%))&" ,Qnt: " &(_xlfn.CEILING.MATH((AllocationTable[[#This Row],[Available Quota]]*14%)/AllocationTable[[#This Row],[LTP]])),IF(AllocationTable[[#This Row],[SIP%]]<0,"EXIT","SIP")) -> SIP | M35: =IF(AllocationTable[[#This Row],[SIP%]]>0,_xlfn.CEILING.MATH(AllocationTable[[#This Row],[High]]-(AllocationTable[[#This Row],[High]]*2*AllocationTable[[#This Row],[SIP%]]%))&" ,Qnt: " &(_xlfn.CEILING.MATH((AllocationTable[[#This Row],[Available Quota]]*30%)/AllocationTable[[#This Row],[LTP]])),IF(AllocationTable[[#This Row],[SIP%]]<0,"EXIT","SIP")) -> SIP | N35: =IF(AllocationTable[[#This Row],[SIP%]]>0,_xlfn.CEILING.MATH(AllocationTable[[#This Row],[High]]-(AllocationTable[[#This Row],[High]]*3*AllocationTable[[#This Row],[SIP%]]%))&" ,Qnt: " &(_xlfn.CEILING.MATH((AllocationTable[[#This Row],[Available Quota]]*56%)/AllocationTable[[#This Row],[LTP]])),IF(AllocationTable[[#This Row],[SIP%]]<0,"EXIT","SIP")) -> SIP | O35: =AllocationTable[[#This Row],[CURRENT VALUE]]-AllocationTable[[#This Row],[AA]] -> 140.2 | P35: =IFERROR(AllocationTable[[#This Row],[PROFIT]]/AllocationTable[[#This Row],[AA]],0) -> 0.021114458 | Q35: =AllocationTable[[#This Row],[QNT]]*AllocationTable[[#This Row],[LTP]] -> 6780.2 | U35: =IF(AllocationTable[[#This Row],[TYPE]]="Stocks",IF(AllocationTable[[#This Row],[Term]]="Long Term",LongTermQuota*AllocationTable[[#This Row],[EA%]]%,SwingTradeQuota*AllocationTable[[#This Row],[EA%]]%),AllocationTable[[#This Row],[Till 2025]]+(TotalMonth*AllocationTable[[#This Row],[ESIP]])) -> 0 | V35: =AllocationTable[[#This Row],[AA]]/AllocationTable[[#Totals],[AA]] -> 0.00076865262 | W35: =AllocationTable[[#This Row],[QNT]]*AllocationTable[[#This Row],[AVG.]] -> 6640
A36: SONACOMS | B36: AUTO ANCILLARY | C36: Stocks | D36: Trading | E36: =_xlfn.IFNA(VLOOKUP(AllocationTable[[#This Row],[TRADE]],LatestDump!A:H,2,FALSE),0) + (_xlfn.IFNA(VLOOKUP(AllocationTable[[#This Row],[TRADE]],LongTerm!A:D,4,0),0)) -> 21 | F36: =IFERROR( ( _xlfn.IFNA(VLOOKUP(AllocationTable[[#This Row],[TRADE]],LatestDump!A:H,5,FALSE),0) + _xlfn.IFNA(VLOOKUP(AllocationTable[[#This Row],[TRADE]],AllocationTable9[[TRADE]:[AA]],14,0),0) ) / AllocationTable[[#This Row],[QNT]], 0) -> 504.39048 | G36: =_xlfn.IFNA(ROUND(VLOOKUP(AllocationTable[[#This Row],[TRADE]],LatestDump!A:H,4,FALSE),2),0) -> 554.25 | H36: 550 | I36: =AllocationTable[[#This Row],[EA]]-AllocationTable[[#This Row],[AA]] -> -10592.2 | J36: =IF(AllocationTable[[#This Row],[Term]]="Trading",IF(AllocationTable[[#This Row],[PROFIT%]]>AllocationTable[[#This Row],[Final Target %]]%,"Book Profit",IF(AllocationTable[[#This Row],[PROFIT%]]>AllocationTable[[#This Row],[Partial Profit %]]%,"Book Partial Profit",IF(AllocationTable[[#This Row],[PROFIT%]]<=AllocationTable[[#This Row],[Stop Loss %]]%,"Book Loss",IF(AllocationTable[[#This Row],[Available Quota]]>AllocationTable[[#This Row],[LTP]],"TOP UP","HOLD")))),IF(AllocationTable[[#This Row],[Available Quota]]>AllocationTable[[#This Row],[LTP]],"TOP UP","HOLD")) -> Book Profit | L36: =IF(AllocationTable[[#This Row],[SIP%]]>0,_xlfn.CEILING.MATH(AllocationTable[[#This Row],[High]]-(AllocationTable[[#This Row],[High]]*AllocationTable[[#This Row],[SIP%]]%))&" ,Qnt: " &(_xlfn.CEILING.MATH((AllocationTable[[#This Row],[Available Quota]]*14%)/AllocationTable[[#This Row],[LTP]])),IF(AllocationTable[[#This Row],[SIP%]]<0,"EXIT","SIP")) -> SIP | M36: =IF(AllocationTable[[#This Row],[SIP%]]>0,_xlfn.CEILING.MATH(AllocationTable[[#This Row],[High]]-(AllocationTable[[#This Row],[High]]*2*AllocationTable[[#This Row],[SIP%]]%))&" ,Qnt: " &(_xlfn.CEILING.MATH((AllocationTable[[#This Row],[Available Quota]]*30%)/AllocationTable[[#This Row],[LTP]])),IF(AllocationTable[[#This Row],[SIP%]]<0,"EXIT","SIP")) -> SIP | N36: =IF(AllocationTable[[#This Row],[SIP%]]>0,_xlfn.CEILING.MATH(AllocationTable[[#This Row],[High]]-(AllocationTable[[#This Row],[High]]*3*AllocationTable[[#This Row],[SIP%]]%))&" ,Qnt: " &(_xlfn.CEILING.MATH((AllocationTable[[#This Row],[Available Quota]]*56%)/AllocationTable[[#This Row],[LTP]])),IF(AllocationTable[[#This Row],[SIP%]]<0,"EXIT","SIP")) -> SIP | O36: =AllocationTable[[#This Row],[CURRENT VALUE]]-AllocationTable[[#This Row],[AA]] -> 1047.05 | P36: =IFERROR(AllocationTable[[#This Row],[PROFIT]]/AllocationTable[[#This Row],[AA]],0) -> 0.098851041 | Q36: =AllocationTable[[#This Row],[QNT]]*AllocationTable[[#This Row],[LTP]] -> 11639.25 | U36: =IF(AllocationTable[[#This Row],[TYPE]]="Stocks",IF(AllocationTable[[#This Row],[Term]]="Long Term",LongTermQuota*AllocationTable[[#This Row],[EA%]]%,SwingTradeQuota*AllocationTable[[#This Row],[EA%]]%),AllocationTable[[#This Row],[Till 2025]]+(TotalMonth*AllocationTable[[#This Row],[ESIP]])) -> 0 | V36: =AllocationTable[[#This Row],[AA]]/AllocationTable[[#Totals],[AA]] -> 0.001226163 | W36: =AllocationTable[[#This Row],[QNT]]*AllocationTable[[#This Row],[AVG.]] -> 10592.2
A37: TMCV | B37: AUTO ANCILLARY | C37: Stocks | D37: Long Term | E37: =_xlfn.IFNA(VLOOKUP(AllocationTable[[#This Row],[TRADE]],LatestDump!A:H,2,FALSE),0) + (_xlfn.IFNA(VLOOKUP(AllocationTable[[#This Row],[TRADE]],LongTerm!A:D,4,0),0)) -> 141 | F37: =IFERROR( ( _xlfn.IFNA(VLOOKUP(AllocationTable[[#This Row],[TRADE]],LatestDump!A:H,5,FALSE),0) + _xlfn.IFNA(VLOOKUP(AllocationTable[[#This Row],[TRADE]],AllocationTable9[[TRADE]:[AA]],14,0),0) ) / AllocationTable[[#This Row],[QNT]], 0) -> 255.21993 | G37: =_xlfn.IFNA(ROUND(VLOOKUP(AllocationTable[[#This Row],[TRADE]],LatestDump!A:H,4,FALSE),2),0) -> 444.55 | H37: 509 | I37: =AllocationTable[[#This Row],[EA]]-AllocationTable[[#This Row],[AA]] -> 2335.952 | J37: =IF(AllocationTable[[#This Row],[Term]]="Trading",IF(AllocationTable[[#This Row],[PROFIT%]]>AllocationTable[[#This Row],[Final Target %]]%,"Book Profit",IF(AllocationTable[[#This Row],[PROFIT%]]>AllocationTable[[#This Row],[Partial Profit %]]%,"Book Partial Profit",IF(AllocationTable[[#This Row],[PROFIT%]]<=AllocationTable[[#This Row],[Stop Loss %]]%,"Book Loss",IF(AllocationTable[[#This Row],[Available Quota]]>AllocationTable[[#This Row],[LTP]],"TOP UP","HOLD")))),IF(AllocationTable[[#This Row],[Available Quota]]>AllocationTable[[#This Row],[LTP]],"TOP UP","HOLD")) -> TOP UP | L37: =IF(AllocationTable[[#This Row],[SIP%]]>0,_xlfn.CEILING.MATH(AllocationTable[[#This Row],[High]]-(AllocationTable[[#This Row],[High]]*AllocationTable[[#This Row],[SIP%]]%))&" ,Qnt: " &(_xlfn.CEILING.MATH((AllocationTable[[#This Row],[Available Quota]]*14%)/AllocationTable[[#This Row],[LTP]])),IF(AllocationTable[[#This Row],[SIP%]]<0,"EXIT","SIP")) -> 459 ,Qnt: 1 | M37: =IF(AllocationTable[[#This Row],[SIP%]]>0,_xlfn.CEILING.MATH(AllocationTable[[#This Row],[High]]-(AllocationTable[[#This Row],[High]]*2*AllocationTable[[#This Row],[SIP%]]%))&" ,Qnt: " &(_xlfn.CEILING.MATH((AllocationTable[[#This Row],[Available Quota]]*30%)/AllocationTable[[#This Row],[LTP]])),IF(AllocationTable[[#This Row],[SIP%]]<0,"EXIT","SIP")) -> 408 ,Qnt: 2 | N37: =IF(AllocationTable[[#This Row],[SIP%]]>0,_xlfn.CEILING.MATH(AllocationTable[[#This Row],[High]]-(AllocationTable[[#This Row],[High]]*3*AllocationTable[[#This Row],[SIP%]]%))&" ,Qnt: " &(_xlfn.CEILING.MATH((AllocationTable[[#This Row],[Available Quota]]*56%)/AllocationTable[[#This Row],[LTP]])),IF(AllocationTable[[#This Row],[SIP%]]<0,"EXIT","SIP")) -> 357 ,Qnt: 3 | O37: =AllocationTable[[#This Row],[CURRENT VALUE]]-AllocationTable[[#This Row],[AA]] -> 26695.54 | P37: =IFERROR(AllocationTable[[#This Row],[PROFIT]]/AllocationTable[[#This Row],[AA]],0) -> 0.74183106 | Q37: =AllocationTable[[#This Row],[QNT]]*AllocationTable[[#This Row],[LTP]] -> 62681.55 | R37: 21834.21 | T37: 2 | U37: =IF(AllocationTable[[#This Row],[TYPE]]="Stocks",IF(AllocationTable[[#This Row],[Term]]="Long Term",LongTermQuota*AllocationTable[[#This Row],[EA%]]%,SwingTradeQuota*AllocationTable[[#This Row],[EA%]]%),AllocationTable[[#This Row],[Till 2025]]+(TotalMonth*AllocationTable[[#This Row],[ESIP]])) -> 38321.962 | V37: =AllocationTable[[#This Row],[AA]]/AllocationTable[[#Totals],[AA]] -> 0.0041657742 | W37: =AllocationTable[[#This Row],[QNT]]*AllocationTable[[#This Row],[AVG.]] -> 35986.01 | X37: 10 | Y37: Tier 3
A38: EICHERMOT | B38: AUTO ANCILLARY | C38: Stocks | D38: Trading | E38: =_xlfn.IFNA(VLOOKUP(AllocationTable[[#This Row],[TRADE]],LatestDump!A:H,2,FALSE),0) + (_xlfn.IFNA(VLOOKUP(AllocationTable[[#This Row],[TRADE]],LongTerm!A:D,4,0),0)) -> 1 | F38: =IFERROR( ( _xlfn.IFNA(VLOOKUP(AllocationTable[[#This Row],[TRADE]],LatestDump!A:H,5,FALSE),0) + _xlfn.IFNA(VLOOKUP(AllocationTable[[#This Row],[TRADE]],AllocationTable9[[TRADE]:[AA]],14,0),0) ) / AllocationTable[[#This Row],[QNT]], 0) -> 7410 | G38: =_xlfn.IFNA(ROUND(VLOOKUP(AllocationTable[[#This Row],[TRADE]],LatestDump!A:H,4,FALSE),2),0) -> 7424 | H38: 9000 | I38: =AllocationTable[[#This Row],[EA]]-AllocationTable[[#This Row],[AA]] -> 9013.698 | J38: =IF(AllocationTable[[#This Row],[Term]]="Trading",IF(AllocationTable[[#This Row],[PROFIT%]]>AllocationTable[[#This Row],[Final Target %]]%,"Book Profit",IF(AllocationTable[[#This Row],[PROFIT%]]>AllocationTable[[#This Row],[Partial Profit %]]%,"Book Partial Profit",IF(AllocationTable[[#This Row],[PROFIT%]]<=AllocationTable[[#This Row],[Stop Loss %]]%,"Book Loss",IF(AllocationTable[[#This Row],[Available Quota]]>AllocationTable[[#This Row],[LTP]],"TOP UP","HOLD")))),IF(AllocationTable[[#This Row],[Available Quota]]>AllocationTable[[#This Row],[LTP]],"TOP UP","HOLD")) -> Book Profit | L38: =IF(AllocationTable[[#This Row],[SIP%]]>0,_xlfn.CEILING.MATH(AllocationTable[[#This Row],[High]]-(AllocationTable[[#This Row],[High]]*AllocationTable[[#This Row],[SIP%]]%))&" ,Qnt: " &(_xlfn.CEILING.MATH((AllocationTable[[#This Row],[Available Quota]]*14%)/AllocationTable[[#This Row],[LTP]])),IF(AllocationTable[[#This Row],[SIP%]]<0,"EXIT","SIP")) -> 8100 ,Qnt: 1 | M38: =IF(AllocationTable[[#This Row],[SIP%]]>0,_xlfn.CEILING.MATH(AllocationTable[[#This Row],[High]]-(AllocationTable[[#This Row],[High]]*2*AllocationTable[[#This Row],[SIP%]]%))&" ,Qnt: " &(_xlfn.CEILING.MATH((AllocationTable[[#This Row],[Available Quota]]*30%)/AllocationTable[[#This Row],[LTP]])),IF(AllocationTable[[#This Row],[SIP%]]<0,"EXIT","SIP")) -> 7200 ,Qnt: 1 | N38: =IF(AllocationTable[[#This Row],[SIP%]]>0,_xlfn.CEILING.MATH(AllocationTable[[#This Row],[High]]-(AllocationTable[[#This Row],[High]]*3*AllocationTable[[#This Row],[SIP%]]%))&" ,Qnt: " &(_xlfn.CEILING.MATH((AllocationTable[[#This Row],[Available Quota]]*56%)/AllocationTable[[#This Row],[LTP]])),IF(AllocationTable[[#This Row],[SIP%]]<0,"EXIT","SIP")) -> 6300 ,Qnt: 1 | O38: =AllocationTable[[#This Row],[CURRENT VALUE]]-AllocationTable[[#This Row],[AA]] -> 14 | P38: =IFERROR(AllocationTable[[#This Row],[PROFIT]]/AllocationTable[[#This Row],[AA]],0) -> 0.0018893387 | Q38: =AllocationTable[[#This Row],[QNT]]*AllocationTable[[#This Row],[LTP]] -> 7424 | T38: 2 | U38: =IF(AllocationTable[[#This Row],[TYPE]]="Stocks",IF(AllocationTable[[#This Row],[Term]]="Long Term",LongTermQuota*AllocationTable[[#This Row],[EA%]]%,SwingTradeQuota*AllocationTable[[#This Row],[EA%]]%),AllocationTable[[#This Row],[Till 2025]]+(TotalMonth*AllocationTable[[#This Row],[ESIP]])) -> 16423.698 | V38: =AllocationTable[[#This Row],[AA]]/AllocationTable[[#Totals],[AA]] -> 0.00085778854 | W38: =AllocationTable[[#This Row],[QNT]]*AllocationTable[[#This Row],[AVG.]] -> 7410 | X38: 10
A39: TMPV | B39: AUTO ANCILLARY | C39: Stocks | D39: Long Term | E39: =_xlfn.IFNA(VLOOKUP(AllocationTable[[#This Row],[TRADE]],LatestDump!A:H,2,FALSE),0) + (_xlfn.IFNA(VLOOKUP(AllocationTable[[#This Row],[TRADE]],LongTerm!A:D,4,0),0)) -> 70 | F39: =IFERROR( ( _xlfn.IFNA(VLOOKUP(AllocationTable[[#This Row],[TRADE]],LatestDump!A:H,5,FALSE),0) + _xlfn.IFNA(VLOOKUP(AllocationTable[[#This Row],[TRADE]],AllocationTable9[[TRADE]:[AA]],14,0),0) ) / AllocationTable[[#This Row],[QNT]], 0) -> 341.35 | G39: =_xlfn.IFNA(ROUND(VLOOKUP(AllocationTable[[#This Row],[TRADE]],LatestDump!A:H,4,FALSE),2),0) -> 342.6 | H39: 420 | I39: =AllocationTable[[#This Row],[EA]]-AllocationTable[[#This Row],[AA]] -> -8565.7152 | J39: =IF(AllocationTable[[#This Row],[Term]]="Trading",IF(AllocationTable[[#This Row],[PROFIT%]]>AllocationTable[[#This Row],[Final Target %]]%,"Book Profit",IF(AllocationTable[[#This Row],[PROFIT%]]>AllocationTable[[#This Row],[Partial Profit %]]%,"Book Partial Profit",IF(AllocationTable[[#This Row],[PROFIT%]]<=AllocationTable[[#This Row],[Stop Loss %]]%,"Book Loss",IF(AllocationTable[[#This Row],[Available Quota]]>AllocationTable[[#This Row],[LTP]],"TOP UP","HOLD")))),IF(AllocationTable[[#This Row],[Available Quota]]>AllocationTable[[#This Row],[LTP]],"TOP UP","HOLD")) -> HOLD | L39: =IF(AllocationTable[[#This Row],[SIP%]]>0,_xlfn.CEILING.MATH(AllocationTable[[#This Row],[High]]-(AllocationTable[[#This Row],[High]]*AllocationTable[[#This Row],[SIP%]]%))&" ,Qnt: " &(_xlfn.CEILING.MATH((AllocationTable[[#This Row],[Available Quota]]*14%)/AllocationTable[[#This Row],[LTP]])),IF(AllocationTable[[#This Row],[SIP%]]<0,"EXIT","SIP")) -> 378 ,Qnt: -3 | M39: =IF(AllocationTable[[#This Row],[SIP%]]>0,_xlfn.CEILING.MATH(AllocationTable[[#This Row],[High]]-(AllocationTable[[#This Row],[High]]*2*AllocationTable[[#This Row],[SIP%]]%))&" ,Qnt: " &(_xlfn.CEILING.MATH((AllocationTable[[#This Row],[Available Quota]]*30%)/AllocationTable[[#This Row],[LTP]])),IF(AllocationTable[[#This Row],[SIP%]]<0,"EXIT","SIP")) -> 336 ,Qnt: -7 | N39: =IF(AllocationTable[[#This Row],[SIP%]]>0,_xlfn.CEILING.MATH(AllocationTable[[#This Row],[High]]-(AllocationTable[[#This Row],[High]]*3*AllocationTable[[#This Row],[SIP%]]%))&" ,Qnt: " &(_xlfn.CEILING.MATH((AllocationTable[[#This Row],[Available Quota]]*56%)/AllocationTable[[#This Row],[LTP]])),IF(AllocationTable[[#This Row],[SIP%]]<0,"EXIT","SIP")) -> 294 ,Qnt: -14 | O39: =AllocationTable[[#This Row],[CURRENT VALUE]]-AllocationTable[[#This Row],[AA]] -> 87.5 | P39: =IFERROR(AllocationTable[[#This Row],[PROFIT]]/AllocationTable[[#This Row],[AA]],0) -> 0.0036619306 | Q39: =AllocationTable[[#This Row],[QNT]]*AllocationTable[[#This Row],[LTP]] -> 23982 | R39: 45072.34 | T39: 0.8 | U39: =IF(AllocationTable[[#This Row],[TYPE]]="Stocks",IF(AllocationTable[[#This Row],[Term]]="Long Term",LongTermQuota*AllocationTable[[#This Row],[EA%]]%,SwingTradeQuota*AllocationTable[[#This Row],[EA%]]%),AllocationTable[[#This Row],[Till 2025]]+(TotalMonth*AllocationTable[[#This Row],[ESIP]])) -> 15328.785 | V39: =AllocationTable[[#This Row],[AA]]/AllocationTable[[#Totals],[AA]] -> 0.0027660497 | W39: =AllocationTable[[#This Row],[QNT]]*AllocationTable[[#This Row],[AVG.]] -> 23894.5 | X39: 10 | Y39: Tier 3 | Z39: -8 | AA39: -8 | AB39: 0 | AC39: 15 | AD39: No trailing
A40: ULTRACEMCO | B40: BUILDING MATERIALS | C40: Stocks | D40: EXIT | E40: =_xlfn.IFNA(VLOOKUP(AllocationTable[[#This Row],[TRADE]],LatestDump!A:H,2,FALSE),0) + (_xlfn.IFNA(VLOOKUP(AllocationTable[[#This Row],[TRADE]],LongTerm!A:D,4,0),0)) -> 1 | F40: =IFERROR( ( _xlfn.IFNA(VLOOKUP(AllocationTable[[#This Row],[TRADE]],LatestDump!A:H,5,FALSE),0) + _xlfn.IFNA(VLOOKUP(AllocationTable[[#This Row],[TRADE]],AllocationTable9[[TRADE]:[AA]],14,0),0) ) / AllocationTable[[#This Row],[QNT]], 0) -> 11674 | G40: =_xlfn.IFNA(ROUND(VLOOKUP(AllocationTable[[#This Row],[TRADE]],LatestDump!A:H,4,FALSE),2),0) -> 11589.9 | H40: 12000 | I40: =AllocationTable[[#This Row],[EA]]-AllocationTable[[#This Row],[AA]] -> -11674 | J40: =IF(AllocationTable[[#This Row],[Term]]="Trading",IF(AllocationTable[[#This Row],[PROFIT%]]>AllocationTable[[#This Row],[Final Target %]]%,"Book Profit",IF(AllocationTable[[#This Row],[PROFIT%]]>AllocationTable[[#This Row],[Partial Profit %]]%,"Book Partial Profit",IF(AllocationTable[[#This Row],[PROFIT%]]<=AllocationTable[[#This Row],[Stop Loss %]]%,"Book Loss",IF(AllocationTable[[#This Row],[Available Quota]]>AllocationTable[[#This Row],[LTP]],"TOP UP","HOLD")))),IF(AllocationTable[[#This Row],[Available Quota]]>AllocationTable[[#This Row],[LTP]],"TOP UP","HOLD")) -> HOLD | L40: =IF(AllocationTable[[#This Row],[SIP%]]>0,_xlfn.CEILING.MATH(AllocationTable[[#This Row],[High]]-(AllocationTable[[#This Row],[High]]*AllocationTable[[#This Row],[SIP%]]%))&" ,Qnt: " &(_xlfn.CEILING.MATH((AllocationTable[[#This Row],[Available Quota]]*14%)/AllocationTable[[#This Row],[LTP]])),IF(AllocationTable[[#This Row],[SIP%]]<0,"EXIT","SIP")) -> EXIT | M40: =IF(AllocationTable[[#This Row],[SIP%]]>0,_xlfn.CEILING.MATH(AllocationTable[[#This Row],[High]]-(AllocationTable[[#This Row],[High]]*2*AllocationTable[[#This Row],[SIP%]]%))&" ,Qnt: " &(_xlfn.CEILING.MATH((AllocationTable[[#This Row],[Available Quota]]*30%)/AllocationTable[[#This Row],[LTP]])),IF(AllocationTable[[#This Row],[SIP%]]<0,"EXIT","SIP")) -> EXIT | N40: =IF(AllocationTable[[#This Row],[SIP%]]>0,_xlfn.CEILING.MATH(AllocationTable[[#This Row],[High]]-(AllocationTable[[#This Row],[High]]*3*AllocationTable[[#This Row],[SIP%]]%))&" ,Qnt: " &(_xlfn.CEILING.MATH((AllocationTable[[#This Row],[Available Quota]]*56%)/AllocationTable[[#This Row],[LTP]])),IF(AllocationTable[[#This Row],[SIP%]]<0,"EXIT","SIP")) -> EXIT | O40: =AllocationTable[[#This Row],[CURRENT VALUE]]-AllocationTable[[#This Row],[AA]] -> -84.1 | P40: =IFERROR(AllocationTable[[#This Row],[PROFIT]]/AllocationTable[[#This Row],[AA]],0) -> -0.0072040432 | Q40: =AllocationTable[[#This Row],[QNT]]*AllocationTable[[#This Row],[LTP]] -> 11589.9 | R40: 20494.85 | T40: 0 | U40: =IF(AllocationTable[[#This Row],[TYPE]]="Stocks",IF(AllocationTable[[#This Row],[Term]]="Long Term",LongTermQuota*AllocationTable[[#This Row],[EA%]]%,SwingTradeQuota*AllocationTable[[#This Row],[EA%]]%),AllocationTable[[#This Row],[Till 2025]]+(TotalMonth*AllocationTable[[#This Row],[ESIP]])) -> 0 | V40: =AllocationTable[[#This Row],[AA]]/AllocationTable[[#Totals],[AA]] -> 0.0013513932 | W40: =AllocationTable[[#This Row],[QNT]]*AllocationTable[[#This Row],[AVG.]] -> 11674 | X40: -1 | Y40: - | Z40: 0 | AA40: 0 | AB40: 0 | AC40: 0 | AD40: 0
A41: GODREJIND | B41: CHEMICALS | C41: Stocks | D41: Trading | E41: =_xlfn.IFNA(VLOOKUP(AllocationTable[[#This Row],[TRADE]],LatestDump!A:H,2,FALSE),0) + (_xlfn.IFNA(VLOOKUP(AllocationTable[[#This Row],[TRADE]],LongTerm!A:D,4,0),0)) -> 25 | F41: =IFERROR( ( _xlfn.IFNA(VLOOKUP(AllocationTable[[#This Row],[TRADE]],LatestDump!A:H,5,FALSE),0) + _xlfn.IFNA(VLOOKUP(AllocationTable[[#This Row],[TRADE]],AllocationTable9[[TRADE]:[AA]],14,0),0) ) / AllocationTable[[#This Row],[QNT]], 0) -> 910.088 | G41: =_xlfn.IFNA(ROUND(VLOOKUP(AllocationTable[[#This Row],[TRADE]],LatestDump!A:H,4,FALSE),2),0) -> 892.05 | H41: 1390 | I41: =AllocationTable[[#This Row],[EA]]-AllocationTable[[#This Row],[AA]] -> -12897.981 | J41: =IF(AllocationTable[[#This Row],[Term]]="Trading",IF(AllocationTable[[#This Row],[PROFIT%]]>AllocationTable[[#This Row],[Final Target %]]%,"Book Profit",IF(AllocationTable[[#This Row],[PROFIT%]]>AllocationTable[[#This Row],[Partial Profit %]]%,"Book Partial Profit",IF(AllocationTable[[#This Row],[PROFIT%]]<=AllocationTable[[#This Row],[Stop Loss %]]%,"Book Loss",IF(AllocationTable[[#This Row],[Available Quota]]>AllocationTable[[#This Row],[LTP]],"TOP UP","HOLD")))),IF(AllocationTable[[#This Row],[Available Quota]]>AllocationTable[[#This Row],[LTP]],"TOP UP","HOLD")) -> HOLD | L41: =IF(AllocationTable[[#This Row],[SIP%]]>0,_xlfn.CEILING.MATH(AllocationTable[[#This Row],[High]]-(AllocationTable[[#This Row],[High]]*AllocationTable[[#This Row],[SIP%]]%))&" ,Qnt: " &(_xlfn.CEILING.MATH((AllocationTable[[#This Row],[Available Quota]]*14%)/AllocationTable[[#This Row],[LTP]])),IF(AllocationTable[[#This Row],[SIP%]]<0,"EXIT","SIP")) -> 1251 ,Qnt: -2 | M41: =IF(AllocationTable[[#This Row],[SIP%]]>0,_xlfn.CEILING.MATH(AllocationTable[[#This Row],[High]]-(AllocationTable[[#This Row],[High]]*2*AllocationTable[[#This Row],[SIP%]]%))&" ,Qnt: " &(_xlfn.CEILING.MATH((AllocationTable[[#This Row],[Available Quota]]*30%)/AllocationTable[[#This Row],[LTP]])),IF(AllocationTable[[#This Row],[SIP%]]<0,"EXIT","SIP")) -> 1112 ,Qnt: -4 | N41: =IF(AllocationTable[[#This Row],[SIP%]]>0,_xlfn.CEILING.MATH(AllocationTable[[#This Row],[High]]-(AllocationTable[[#This Row],[High]]*3*AllocationTable[[#This Row],[SIP%]]%))&" ,Qnt: " &(_xlfn.CEILING.MATH((AllocationTable[[#This Row],[Available Quota]]*56%)/AllocationTable[[#This Row],[LTP]])),IF(AllocationTable[[#This Row],[SIP%]]<0,"EXIT","SIP")) -> 973 ,Qnt: -8 | O41: =AllocationTable[[#This Row],[CURRENT VALUE]]-AllocationTable[[#This Row],[AA]] -> -450.95 | P41: =IFERROR(AllocationTable[[#This Row],[PROFIT]]/AllocationTable[[#This Row],[AA]],0) -> -0.019820061 | Q41: =AllocationTable[[#This Row],[QNT]]*AllocationTable[[#This Row],[LTP]] -> 22301.25 | R41: 43308.85 | T41: 1.2 | U41: =IF(AllocationTable[[#This Row],[TYPE]]="Stocks",IF(AllocationTable[[#This Row],[Term]]="Long Term",LongTermQuota*AllocationTable[[#This Row],[EA%]]%,SwingTradeQuota*AllocationTable[[#This Row],[EA%]]%),AllocationTable[[#This Row],[Till 2025]]+(TotalMonth*AllocationTable[[#This Row],[ESIP]])) -> 9854.2188 | V41: =AllocationTable[[#This Row],[AA]]/AllocationTable[[#Totals],[AA]] -> 0.002633816 | W41: =AllocationTable[[#This Row],[QNT]]*AllocationTable[[#This Row],[AVG.]] -> 22752.2 | X41: 10 | Y41: Tier 2 | Z41: -10 | AA41: -10 | AB41: 15 | AC41: 20 | AD41: Trail -8% from peak after +12%
A42: LGEINDIA | B42: CONSUMER DURABLES | C42: Stocks | D42: Long Term | E42: =_xlfn.IFNA(VLOOKUP(AllocationTable[[#This Row],[TRADE]],LatestDump!A:H,2,FALSE),0) + (_xlfn.IFNA(VLOOKUP(AllocationTable[[#This Row],[TRADE]],LongTerm!A:D,4,0),0)) -> 7 | F42: =IFERROR( ( _xlfn.IFNA(VLOOKUP(AllocationTable[[#This Row],[TRADE]],LatestDump!A:H,5,FALSE),0) + _xlfn.IFNA(VLOOKUP(AllocationTable[[#This Row],[TRADE]],AllocationTable9[[TRADE]:[AA]],14,0),0) ) / AllocationTable[[#This Row],[QNT]], 0) -> 1385.6 | G42: =_xlfn.IFNA(ROUND(VLOOKUP(AllocationTable[[#This Row],[TRADE]],LatestDump!A:H,4,FALSE),2),0) -> 1477.7 | H42: 1750 | I42: =AllocationTable[[#This Row],[EA]]-AllocationTable[[#This Row],[AA]] -> 13293.977 | J42: =IF(AllocationTable[[#This Row],[Term]]="Trading",IF(AllocationTable[[#This Row],[PROFIT%]]>AllocationTable[[#This Row],[Final Target %]]%,"Book Profit",IF(AllocationTable[[#This Row],[PROFIT%]]>AllocationTable[[#This Row],[Partial Profit %]]%,"Book Partial Profit",IF(AllocationTable[[#This Row],[PROFIT%]]<=AllocationTable[[#This Row],[Stop Loss %]]%,"Book Loss",IF(AllocationTable[[#This Row],[Available Quota]]>AllocationTable[[#This Row],[LTP]],"TOP UP","HOLD")))),IF(AllocationTable[[#This Row],[Available Quota]]>AllocationTable[[#This Row],[LTP]],"TOP UP","HOLD")) -> TOP UP | L42: =IF(AllocationTable[[#This Row],[SIP%]]>0,_xlfn.CEILING.MATH(AllocationTable[[#This Row],[High]]-(AllocationTable[[#This Row],[High]]*AllocationTable[[#This Row],[SIP%]]%))&" ,Qnt: " &(_xlfn.CEILING.MATH((AllocationTable[[#This Row],[Available Quota]]*14%)/AllocationTable[[#This Row],[LTP]])),IF(AllocationTable[[#This Row],[SIP%]]<0,"EXIT","SIP")) -> 1575 ,Qnt: 2 | M42: =IF(AllocationTable[[#This Row],[SIP%]]>0,_xlfn.CEILING.MATH(AllocationTable[[#This Row],[High]]-(AllocationTable[[#This Row],[High]]*2*AllocationTable[[#This Row],[SIP%]]%))&" ,Qnt: " &(_xlfn.CEILING.MATH((AllocationTable[[#This Row],[Available Quota]]*30%)/AllocationTable[[#This Row],[LTP]])),IF(AllocationTable[[#This Row],[SIP%]]<0,"EXIT","SIP")) -> 1400 ,Qnt: 3 | N42: =IF(AllocationTable[[#This Row],[SIP%]]>0,_xlfn.CEILING.MATH(AllocationTable[[#This Row],[High]]-(AllocationTable[[#This Row],[High]]*3*AllocationTable[[#This Row],[SIP%]]%))&" ,Qnt: " &(_xlfn.CEILING.MATH((AllocationTable[[#This Row],[Available Quota]]*56%)/AllocationTable[[#This Row],[LTP]])),IF(AllocationTable[[#This Row],[SIP%]]<0,"EXIT","SIP")) -> 1225 ,Qnt: 6 | O42: =AllocationTable[[#This Row],[CURRENT VALUE]]-AllocationTable[[#This Row],[AA]] -> 644.7 | P42: =IFERROR(AllocationTable[[#This Row],[PROFIT]]/AllocationTable[[#This Row],[AA]],0) -> 0.0664694 | Q42: =AllocationTable[[#This Row],[QNT]]*AllocationTable[[#This Row],[LTP]] -> 10343.9 | R42: 7900 | T42: 1.2 | U42: =IF(AllocationTable[[#This Row],[TYPE]]="Stocks",IF(AllocationTable[[#This Row],[Term]]="Long Term",LongTermQuota*AllocationTable[[#This Row],[EA%]]%,SwingTradeQuota*AllocationTable[[#This Row],[EA%]]%),AllocationTable[[#This Row],[Till 2025]]+(TotalMonth*AllocationTable[[#This Row],[ESIP]])) -> 22993.177 | V42: =AllocationTable[[#This Row],[AA]]/AllocationTable[[#Totals],[AA]] -> 0.0011227885 | W42: =AllocationTable[[#This Row],[QNT]]*AllocationTable[[#This Row],[AVG.]] -> 9699.2 | X42: 10 | Y42: Tier 2
